Workbook
Name ACT: #REF!
Name ACTIVIDAD: #REF!
Name ADMINISTRACION: #REF!
Name AGRICULTURA: #REF!
Name AMORTBI: '[1]Bal1202-200603'!$U$226
Name AMORTBU: '[1]Bal1202-200603'!$U$225
Name BASEDATOS: #REF!
Name BOVINOS: #REF!
Name CAPRINOS: #REF!
Name COMBUSTIBLE: #REF!
Name EOAF: '[1]Bal1202-200603'!$E$10:$R$251
Name EOAF1: '[1]Bal1202-200603'!$R$10:$R$251
Name EST: #REF!
Name ESTADO: [2]LISTAS!$O$3:$O$6
Name ESTRUCTURA: #REF!
Name FORRAJE: #REF!
Name FR: #REF!
Name GANADERIA: #REF!
Name GENERAL: #REF!
Name IMPUESTOS: #REF!
Name INTERESES: #REF!
Name MAQUINARIA: #REF!
Name OVINO: #REF!
Name PORCINOS: #REF!
Name SEGUROS: #REF!
Name SEMILLAS: [3]!Tabla4[#All]
Name SOCIOS: #REF!
Name SUELDOS: #REF!
Name TIPO_FACT: [2]LISTAS!$S$3:$S$7

Sheet RESUMEN
A1: RESUMEN DE ACTIVIDADES 2025
A3: Etiquetas de fila | B3: Suma de EGRESOS | C3: Suma de INGRESOS | D3: Suma de EGRES USD | E3: Suma de INGRES USD
A4: ADMINISTRACION | B4: 38560494 | C4: 6437252.5 | D4: 26593.444 | E4: 4439.4845
A5: GASTOS_ADM | B5: 215693.81 | C5: 53700 | D5: 148.75435 | E5: 37.034483
A6: MANTENIMIENTO | B6: 0 | C6: 53700 | D6: 0 | E6: 37.034483
A7: SEGUROS | B7: 16134 | C7: 0 | D7: 11.126897 | E7: 0
A8: PLAN DE PAGOS | B8: 199559.81 | C8: 0 | D8: 137.62746 | E8: 0
A9: GASTOS_BANC | B9: 1654959.7 | C9: 13287.53 | D9: 1141.3515 | E9: 9.1638138
A10: COMISIONES | B10: 462413.68 | C10: 0 | D10: 318.90599 | E10: 0
A11: IMPUESTOS | B11: 1192546 | C11: 13287.53 | D11: 822.44554 | E11: 9.1638138
A12: GASTOS_FIN | B12: 2638047 | C12: 0 | D12: 1819.3428 | E12: 0
A13: INTERESES | B13: 2638047 | C13: 0 | D13: 1819.3428 | E13: 0
A14: PERSONAL | B14: 9732583.7 | C14: 0 | D14: 6712.1267 | E14: 0
A15: JORNALES | B15: 3149421 | C15: 0 | D15: 2172.0145 | E15: 0
... A69: Total general | B69: 2.3365279e+08 | C69: 2.2952879e+08 | D69: 161139.85 | E69: 158295.71

Sheet ACTIVIDADES
B1: IMPUTACION DE MONTOS DE LAS ACTIVIDADES PRODUCTIVAS 2025
B15: ACTIVIDADES | C15: ENERO | D15: FEBRERO | E15: MARZO | F15: ABRIL | G15: MAYO | H15: JUNIO | I15: JULIO | J15: AGOSTO | K15: SEPTIEMBRE | L15: OCTUBRE | M15: NOVIEMBRE | N15: DICIEMBRE | O15: TOTAL | P15: ESTIMADO | Q15: % | R15: USD | S15: USD/HA
B16: AGRICULTURA | C16: =SUM(C17,C18,C28) -> 3129704.7 | D16: =SUM(D17,D18,D28) -> 0 | E16: =SUM(E17,E18,E28) -> 0 | F16: =SUM(F17,F18,F28) -> 0 | G16: =SUM(G17,G18,G28) -> #REF! | H16: =SUM(H17,H18,H28) -> #REF! | I16: =SUM(I17,I18,I28) -> 0 | J16: =SUM(J17,J18,J28) -> 0 | ... N16: =SUM(N17,N18,N28) -> 0 | O16: =SUM(O17:O35) -> 3129704.7 | P16: =SUM(P17:P35) -> 3.4298105e+08 | Q16: =Tabla4[[#This Row],[TOTAL]]/Tabla4[[#This Row],[ESTIMADO]] -> 0.0091250075 | R16: =SUM(R17:R35) -> 296890.58
B17: ASESORAMIENTO | C17: =SUMIFS(Tabla3[[#All],[EGRESOS]],Tabla3[[#All],[PERIODO]],Tabla4[[#Headers],[ENERO]],Tabla3[[#All],[ACTIVIDAD]],ACTIVIDADES!$B$16,Tabla3[[#All],[CONCEPTO]],Tabla4[[#This Row],[ACTIVIDADES]]) -> 0 | D17: =SUMIFS(Tabla3[[#All],[EGRESOS]],Tabla3[[#All],[PERIODO]],Tabla4[[#Headers],[FEBRERO]],Tabla3[[#All],[ACTIVIDAD]],ACTIVIDADES!$B$16,Tabla3[[#All],[CONCEPTO]],Tabla4[[#This Row],[ACTIVIDADES]]) -> 0 | E17: =SUMIFS(Tabla3[[#All],[EGRESOS]],Tabla3[[#All],[PERIODO]],Tabla4[[#Headers],[MARZO]],Tabla3[[#All],[ACTIVIDAD]],ACTIVIDADES!$B$16,Tabla3[[#All],[CONCEPTO]],Tabla4[[#This Row],[ACTIVIDADES]]) -> 0 | F17: =SUMIFS(Tabla3[[#All],[EGRESOS]],Tabla3[[#All],[PERIODO]],Tabla4[[#Headers],[ABRIL]],Tabla3[[#All],[ACTIVIDAD]],ACTIVIDADES!$B$16,Tabla3[[#All],[CONCEPTO]],Tabla4[[#This Row],[ACTIVIDADES]]) -> 0 | G17: =SUMIFS(Tabla3[[#All],[EGRESOS]],Tabla3[[#All],[PERIODO]],Tabla4[[#Headers],[MAYO]],Tabla3[[#All],[ACTIVIDAD]],ACTIVIDADES!$B$16,Tabla3[[#All],[CONCEPTO]],Tabla4[[#This Row],[ACTIVIDADES]]) -> 0 | H17: =SUMIFS(Tabla3[[#All],[EGRESOS]],Tabla3[[#All],[PERIODO]],Tabla4[[#Headers],[JUNIO]],Tabla3[[#All],[ACTIVIDAD]],ACTIVIDADES!$B$16,Tabla3[[#All],[CONCEPTO]],Tabla4[[#This Row],[ACTIVIDADES]]) -> 0 | I17: =SUMIFS(Tabla3[[#All],[EGRESOS]],Tabla3[[#All],[PERIODO]],Tabla4[[#Headers],[JULIO]],Tabla3[[#All],[ACTIVIDAD]],ACTIVIDADES!$B$16,Tabla3[[#All],[CONCEPTO]],Tabla4[[#This Row],[ACTIVIDADES]]) -> 0 | J17: =SUMIFS(Tabla3[[#All],[EGRESOS]],Tabla3[[#All],[PERIODO]],Tabla4[[#Headers],[AGOSTO]],Tabla3[[#All],[ACTIVIDAD]],ACTIVIDADES!$B$16,Tabla3[[#All],[CONCEPTO]],Tabla4[[#This Row],[ACTIVIDADES]]) -> 0 | K17: =SUMIFS(Tabla3[[#All],[EGRESOS]],Tabla3[[#All],[PERIODO]],Tabla4[[#Headers],[SEPTIEMBRE]],Tabla3[[#All],[ACTIVIDAD]],ACTIVIDADES!$B$16,Tabla3[[#All],[CONCEPTO]],Tabla4[[#This Row],[ACTIVIDADES]]) -> 0 | L17: =SUMIFS(Tabla3[[#All],[EGRESOS]],Tabla3[[#All],[PERIODO]],Tabla4[[#Headers],[OCTUBRE]],Tabla3[[#All],[ACTIVIDAD]],ACTIVIDADES!$B$16,Tabla3[[#All],[CONCEPTO]],Tabla4[[#This Row],[ACTIVIDADES]]) -> 0 | O17: =SUM(Tabla4[[#This Row],[ENERO]:[DICIEMBRE]]) -> 0 | P17: 7826025 | Q17: =Tabla4[[#This Row],[TOTAL]]/Tabla4[[#This Row],[ESTIMADO]] -> 0 | R17: =Tabla4[[#This Row],[ESTIMADO]]/1140 -> 6864.9342 | S17: =Tabla4[[#This Row],[USD]]/(350) -> 19.614098
B18: SOJA | C18: =SUBTOTAL(109,C19:C27) -> 3129704.7 | D18: =SUBTOTAL(109,D19:D27) -> 0 | E18: =SUBTOTAL(109,E19:E27) -> 0 | F18: =SUBTOTAL(109,F19:F27) -> 0 | G18: =SUBTOTAL(109,G19:G27) -> #REF! | H18: =SUBTOTAL(109,H19:H27) -> #REF! | I18: =SUBTOTAL(109,I19:I27) -> 0 | J18: =SUBTOTAL(109,J19:J27) -> 0 | ... M18: =SUBTOTAL(109,M19:M27) -> 0 | N18: =SUBTOTAL(109,N19:N26) -> 0
B19: SIEMBRA | C19: =SUMIFS(Tabla3[[#All],[EGRESOS]],Tabla3[[#All],[PERIODO]],Tabla4[[#Headers],[ENERO]],Tabla3[[#All],[ACTIVIDAD]],ACTIVIDADES!$B$16,Tabla3[[#All],[CONCEPTO]],ACTIVIDADES!$B$18,Tabla3[[#All],[DETALLES]],Tabla4[[#This Row],[ACTIVIDADES]]) -> 0 | D19: =SUMIFS(Tabla3[EGRESOS],Tabla3[ACTIVIDAD],ACTIVIDADES!$B$18,Tabla3[PERIODO],Tabla4[[#Headers],[FEBRERO]],Tabla3[CONCEPTO],ACTIVIDADES!B16,Tabla3[DETALLES],Tabla4[[#This Row],[ACTIVIDADES]]) -> 0 | E19: =SUMIFS(Tabla3[[#All],[EGRESOS]],Tabla3[[#All],[PERIODO]],Tabla4[[#Headers],[MARZO]],Tabla3[[#All],[ACTIVIDAD]],ACTIVIDADES!B16,Tabla3[[#All],[CONCEPTO]],ACTIVIDADES!B18,Tabla3[[#All],[DETALLES]],Tabla4[[#This Row],[ACTIVIDADES]]) -> 0 | F19: =SUMIFS(Tabla3[[#All],[EGRESOS]],Tabla3[[#All],[PERIODO]],Tabla4[[#Headers],[ABRIL]],Tabla3[[#All],[ACTIVIDAD]],ACTIVIDADES!B16,Tabla3[[#All],[CONCEPTO]],ACTIVIDADES!B18,Tabla3[[#All],[DETALLES]],Tabla4[[#This Row],[ACTIVIDADES]]) -> 0 | G19: =SUMIFS(Tabla3[[#All],[EGRESOS]],Tabla3[[#All],[PERIODO]],Tabla4[[#Headers],[MAYO]],Tabla3[[#All],[ACTIVIDAD]],ACTIVIDADES!B16,Tabla3[[#All],[CONCEPTO]],ACTIVIDADES!B18,Tabla3[[#All],[DETALLES]],Tabla4[[#This Row],[ACTIVIDADES]]) -> 0 | H19: =SUMIFS(Tabla3[[#All],[EGRESOS]],Tabla3[[#All],[PERIODO]],Tabla4[[#Headers],[JUNIO]],Tabla3[[#All],[ACTIVIDAD]],ACTIVIDADES!B16,Tabla3[[#All],[CONCEPTO]],ACTIVIDADES!B18,Tabla3[[#All],[DETALLES]],Tabla4[[#This Row],[ACTIVIDADES]]) -> 0 | I19: =SUMIFS(Tabla3[[#All],[EGRESOS]],Tabla3[[#All],[PERIODO]],Tabla4[[#Headers],[JULIO]],Tabla3[[#All],[ACTIVIDAD]],ACTIVIDADES!B16,Tabla3[[#All],[CONCEPTO]],ACTIVIDADES!B18,Tabla3[[#All],[DETALLES]],Tabla4[[#This Row],[ACTIVIDADES]]) -> 0 | J19: =SUMIFS(Tabla3[[#All],[EGRESOS]],Tabla3[[#All],[PERIODO]],Tabla4[[#Headers],[AGOSTO]],Tabla3[[#All],[ACTIVIDAD]],ACTIVIDADES!B16,Tabla3[[#All],[CONCEPTO]],ACTIVIDADES!B18,Tabla3[[#All],[DETALLES]],Tabla4[[#This Row],[ACTIVIDADES]]) -> 0 | K19: =SUMIFS(Tabla3[[#All],[EGRESOS]],Tabla3[[#All],[PERIODO]],Tabla4[[#Headers],[SEPTIEMBRE]],Tabla3[[#All],[ACTIVIDAD]],ACTIVIDADES!B16,Tabla3[[#All],[CONCEPTO]],ACTIVIDADES!B18,Tabla3[[#All],[DETALLES]],B19) -> 0 | L19: =SUMIFS(Tabla3[[#All],[EGRESOS]],Tabla3[[#All],[PERIODO]],Tabla4[[#Headers],[OCTUBRE]],Tabla3[[#All],[ACTIVIDAD]],$B$16,Tabla3[[#All],[CONCEPTO]],$B$18,Tabla3[[#All],[DETALLES]],B19) -> 0 | M19: =SUMIFS(Tabla3[[#All],[EGRESOS]],Tabla3[[#All],[PERIODO]],Tabla4[[#Headers],[NOVIEMBRE]],Tabla3[[#All],[ACTIVIDAD]],$B$16,Tabla3[[#All],[CONCEPTO]],$B$18,Tabla3[[#All],[DETALLES]],B19) -> 0 | O19: =SUM(Tabla4[[#This Row],[ENERO]:[DICIEMBRE]]) -> 0 | P19: =14974524*1.21 -> 18119174 | Q19: =Tabla4[[#This Row],[TOTAL]]/Tabla4[[#This Row],[ESTIMADO]] -> 0 | R19: =Tabla4[[#This Row],[ESTIMADO]]/1140 -> 15894.012 | S19: =Tabla4[[#This Row],[USD]]/(350) -> 45.411464
B20: SEMILLAS | C20: =SUMIFS(Tabla3[[#All],[EGRESOS]],Tabla3[[#All],[PERIODO]],Tabla4[[#Headers],[ENERO]],Tabla3[[#All],[ACTIVIDAD]],ACTIVIDADES!$B$16,Tabla3[[#All],[CONCEPTO]],ACTIVIDADES!$B$18,Tabla3[[#All],[DETALLES]],Tabla4[[#This Row],[ACTIVIDADES]]) -> 0 | D20: =SUMIFS(Tabla3[EGRESOS],Tabla3[ACTIVIDAD],ACTIVIDADES!$B$16,Tabla3[PERIODO],Tabla4[[#Headers],[FEBRERO]],Tabla3[CONCEPTO],ACTIVIDADES!B18,Tabla3[DETALLES],Tabla4[[#This Row],[ACTIVIDADES]]) -> 0 | E20: =SUMIFS(Tabla3[[#All],[EGRESOS]],Tabla3[[#All],[PERIODO]],Tabla4[[#Headers],[MARZO]],Tabla3[[#All],[ACTIVIDAD]],ACTIVIDADES!B17,Tabla3[[#All],[CONCEPTO]],ACTIVIDADES!B18,Tabla3[[#All],[DETALLES]],Tabla4[[#This Row],[ACTIVIDADES]]) -> 0 | F20: =SUMIFS(Tabla3[[#All],[EGRESOS]],Tabla3[[#All],[PERIODO]],Tabla4[[#Headers],[ABRIL]],Tabla3[[#All],[ACTIVIDAD]],ACTIVIDADES!B16,Tabla3[[#All],[CONCEPTO]],ACTIVIDADES!B18,Tabla3[[#All],[DETALLES]],Tabla4[[#This Row],[ACTIVIDADES]]) -> 0 | G20: =SUMIFS(Tabla3[[#All],[EGRESOS]],Tabla3[[#All],[PERIODO]],Tabla4[[#Headers],[MAYO]],Tabla3[[#All],[ACTIVIDAD]],ACTIVIDADES!$B$16,Tabla3[[#All],[CONCEPTO]],ACTIVIDADES!$B$18,Tabla3[[#All],[DETALLES]],Tabla4[[#This Row],[ACTIVIDADES]]) -> 0 | H20: =SUMIFS(Tabla3[[#All],[EGRESOS]],Tabla3[[#All],[PERIODO]],Tabla4[[#Headers],[JUNIO]],Tabla3[[#All],[ACTIVIDAD]],ACTIVIDADES!B16,Tabla3[[#All],[CONCEPTO]],ACTIVIDADES!B18,Tabla3[[#All],[DETALLES]],Tabla4[[#This Row],[ACTIVIDADES]]) -> 0 | J20: =SUMIFS(Tabla3[[#All],[EGRESOS]],Tabla3[[#All],[PERIODO]],Tabla4[[#Headers],[AGOSTO]],Tabla3[[#All],[ACTIVIDAD]],ACTIVIDADES!B16,Tabla3[[#All],[CONCEPTO]],ACTIVIDADES!B18,Tabla3[[#All],[DETALLES]],Tabla4[[#This Row],[ACTIVIDADES]]) -> 0 | K20: =SUMIFS(Tabla3[[#All],[EGRESOS]],Tabla3[[#All],[PERIODO]],Tabla4[[#Headers],[SEPTIEMBRE]],Tabla3[[#All],[ACTIVIDAD]],ACTIVIDADES!B16,Tabla3[[#All],[CONCEPTO]],ACTIVIDADES!B18,Tabla3[[#All],[DETALLES]],B20) -> 0 | L20: =SUMIFS(Tabla3[[#All],[EGRESOS]],Tabla3[[#All],[PERIODO]],Tabla4[[#Headers],[OCTUBRE]],Tabla3[[#All],[ACTIVIDAD]],$B$16,Tabla3[[#All],[CONCEPTO]],$B$18,Tabla3[[#All],[DETALLES]],B20) -> 0 | M20: =SUMIFS(Tabla3[[#All],[EGRESOS]],Tabla3[[#All],[PERIODO]],Tabla4[[#Headers],[NOVIEMBRE]],Tabla3[[#All],[ACTIVIDAD]],$B$16,Tabla3[[#All],[CONCEPTO]],$B$18,Tabla3[[#All],[DETALLES]],B20) -> 0 | O20: =SUM(Tabla4[[#This Row],[ENERO]:[DICIEMBRE]]) -> 0 | P20: =Tabla4[[#This Row],[USD]]*1140 -> 11427280 | Q20: =Tabla4[[#This Row],[TOTAL]]/Tabla4[[#This Row],[ESTIMADO]] -> 0 | R20: 10023.93 | S20: =Tabla4[[#This Row],[USD]]/(350) -> 28.6398
B21: APLICACIONES | C21: =SUMIFS(Tabla3[[#All],[EGRESOS]],Tabla3[[#All],[PERIODO]],Tabla4[[#Headers],[ENERO]],Tabla3[[#All],[ACTIVIDAD]],ACTIVIDADES!$B$16,Tabla3[[#All],[CONCEPTO]],ACTIVIDADES!$B$18,Tabla3[[#All],[DETALLES]],Tabla4[[#This Row],[ACTIVIDADES]]) -> 3129704.7 | D21: =SUMIFS(Tabla3[EGRESOS],Tabla3[ACTIVIDAD],ACTIVIDADES!$B$16,Tabla3[PERIODO],Tabla4[[#Headers],[FEBRERO]],Tabla3[CONCEPTO],ACTIVIDADES!B18,Tabla3[DETALLES],Tabla4[[#This Row],[ACTIVIDADES]]) -> 0 | E21: =SUMIFS(Tabla3[[#All],[EGRESOS]],Tabla3[[#All],[PERIODO]],Tabla4[[#Headers],[MARZO]],Tabla3[[#All],[ACTIVIDAD]],ACTIVIDADES!$B$16,Tabla3[[#All],[CONCEPTO]],ACTIVIDADES!$B$18,Tabla3[[#All],[DETALLES]],Tabla4[[#This Row],[ACTIVIDADES]]) -> 0 | F21: =SUMIFS(Tabla3[[#All],[EGRESOS]],Tabla3[[#All],[PERIODO]],Tabla4[[#Headers],[ABRIL]],Tabla3[[#All],[ACTIVIDAD]],ACTIVIDADES!B16,Tabla3[[#All],[CONCEPTO]],ACTIVIDADES!B18,Tabla3[[#All],[DETALLES]],Tabla4[[#This Row],[ACTIVIDADES]]) -> 0 | G21: =SUMIFS(Tabla3[[#All],[EGRESOS]],Tabla3[[#All],[PERIODO]],Tabla4[[#Headers],[MAYO]],Tabla3[[#All],[ACTIVIDAD]],ACTIVIDADES!$B$16,Tabla3[[#All],[CONCEPTO]],ACTIVIDADES!$B$18,Tabla3[[#All],[DETALLES]],Tabla4[[#This Row],[ACTIVIDADES]]) -> 0 | H21: =SUMIFS(Tabla3[[#All],[EGRESOS]],Tabla3[[#All],[PERIODO]],Tabla4[[#Headers],[JUNIO]],Tabla3[[#All],[ACTIVIDAD]],ACTIVIDADES!$B$16,Tabla3[[#All],[CONCEPTO]],ACTIVIDADES!$B$18,Tabla3[[#All],[DETALLES]],Tabla4[[#This Row],[ACTIVIDADES]]) -> 0 | I21: =SUMIFS(Tabla3[[#All],[EGRESOS]],Tabla3[[#All],[PERIODO]],Tabla4[[#Headers],[JULIO]],Tabla3[[#All],[ACTIVIDAD]],ACTIVIDADES!$B$16,Tabla3[[#All],[CONCEPTO]],ACTIVIDADES!$B$18,Tabla3[[#All],[DETALLES]],Tabla4[[#This Row],[ACTIVIDADES]]) -> 0 | J21: =SUMIFS(Tabla3[[#All],[EGRESOS]],Tabla3[[#All],[PERIODO]],Tabla4[[#Headers],[AGOSTO]],Tabla3[[#All],[ACTIVIDAD]],ACTIVIDADES!B16,Tabla3[[#All],[CONCEPTO]],ACTIVIDADES!B18,Tabla3[[#All],[DETALLES]],Tabla4[[#This Row],[ACTIVIDADES]]) -> 0 | K21: =SUMIFS(Tabla3[[#All],[EGRESOS]],Tabla3[[#All],[PERIODO]],Tabla4[[#Headers],[SEPTIEMBRE]],Tabla3[[#All],[ACTIVIDAD]],ACTIVIDADES!B16,Tabla3[[#All],[CONCEPTO]],ACTIVIDADES!B18,Tabla3[[#All],[DETALLES]],B21) -> 0 | L21: =SUMIFS(Tabla3[[#All],[EGRESOS]],Tabla3[[#All],[PERIODO]],Tabla4[[#Headers],[OCTUBRE]],Tabla3[[#All],[ACTIVIDAD]],$B$16,Tabla3[[#All],[CONCEPTO]],$B$18,Tabla3[[#All],[DETALLES]],B21) -> 0 | M21: =SUMIFS(Tabla3[[#All],[EGRESOS]],Tabla3[[#All],[PERIODO]],Tabla4[[#Headers],[NOVIEMBRE]],Tabla3[[#All],[ACTIVIDAD]],$B$16,Tabla3[[#All],[CONCEPTO]],$B$18,Tabla3[[#All],[DETALLES]],B21) -> 0 | O21: =SUM(Tabla4[[#This Row],[ENERO]:[DICIEMBRE]]) -> 3129704.7 | P21: =Tabla4[[#This Row],[USD]]*1140 -> 17912683 | Q21: =Tabla4[[#This Row],[TOTAL]]/Tabla4[[#This Row],[ESTIMADO]] -> 0.17472004 | R21: 15712.88 | S21: =Tabla4[[#This Row],[USD]]/(350) -> 44.893943
B22: INSUMOS 2025 | C22: =SUMIFS(Tabla3[[#All],[EGRESOS]],Tabla3[[#All],[PERIODO]],Tabla4[[#Headers],[ENERO]],Tabla3[[#All],[ACTIVIDAD]],ACTIVIDADES!$B$16,Tabla3[[#All],[CONCEPTO]],ACTIVIDADES!$B$18,Tabla3[[#All],[DETALLES]],Tabla4[[#This Row],[ACTIVIDADES]]) -> 0 | D22: =SUMIFS(Tabla3[EGRESOS],Tabla3[ACTIVIDAD],ACTIVIDADES!$B$16,Tabla3[PERIODO],Tabla4[[#Headers],[FEBRERO]],Tabla3[CONCEPTO],ACTIVIDADES!B18,Tabla3[DETALLES],Tabla4[[#This Row],[ACTIVIDADES]]) -> 0 | E22: =SUMIFS(Tabla3[[#All],[EGRESOS]],Tabla3[[#All],[PERIODO]],Tabla4[[#Headers],[MARZO]],Tabla3[[#All],[ACTIVIDAD]],ACTIVIDADES!$B$16,Tabla3[[#All],[CONCEPTO]],ACTIVIDADES!$B$18,Tabla3[[#All],[DETALLES]],Tabla4[[#This Row],[ACTIVIDADES]]) -> 0 | F22: =SUMIFS(Tabla3[[#All],[EGRESOS]],Tabla3[[#All],[PERIODO]],Tabla4[[#Headers],[ABRIL]],Tabla3[[#All],[ACTIVIDAD]],ACTIVIDADES!B16,Tabla3[[#All],[CONCEPTO]],ACTIVIDADES!B18,Tabla3[[#All],[DETALLES]],Tabla4[[#This Row],[ACTIVIDADES]]) -> 0 | G22: =SUMIFS(Tabla3[[#All],[EGRESOS]],Tabla3[[#All],[PERIODO]],Tabla4[[#Headers],[MAYO]],Tabla3[[#All],[ACTIVIDAD]],ACTIVIDADES!$B$16,Tabla3[[#All],[CONCEPTO]],ACTIVIDADES!$B$18,Tabla3[[#All],[DETALLES]],Tabla4[[#This Row],[ACTIVIDADES]]) -> 0 | H22: =SUMIFS(Tabla3[[#All],[EGRESOS]],Tabla3[[#All],[PERIODO]],Tabla4[[#Headers],[JUNIO]],Tabla3[[#All],[ACTIVIDAD]],ACTIVIDADES!B16,Tabla3[[#All],[CONCEPTO]],ACTIVIDADES!B18,Tabla3[[#All],[DETALLES]],Tabla4[[#This Row],[ACTIVIDADES]]) -> 0 | I22: =SUMIFS(Tabla3[[#All],[EGRESOS]],Tabla3[[#All],[PERIODO]],Tabla4[[#Headers],[JULIO]],Tabla3[[#All],[ACTIVIDAD]],ACTIVIDADES!B16,Tabla3[[#All],[CONCEPTO]],ACTIVIDADES!B18,Tabla3[[#All],[DETALLES]],Tabla4[[#This Row],[ACTIVIDADES]]) -> 0 | J22: =SUMIFS(Tabla3[[#All],[EGRESOS]],Tabla3[[#All],[PERIODO]],Tabla4[[#Headers],[AGOSTO]],Tabla3[[#All],[ACTIVIDAD]],ACTIVIDADES!B16,Tabla3[[#All],[CONCEPTO]],ACTIVIDADES!B18,Tabla3[[#All],[DETALLES]],Tabla4[[#This Row],[ACTIVIDADES]]) -> 0 | K22: =SUMIFS(Tabla3[[#All],[EGRESOS]],Tabla3[[#All],[PERIODO]],Tabla4[[#Headers],[SEPTIEMBRE]],Tabla3[[#All],[ACTIVIDAD]],ACTIVIDADES!B16,Tabla3[[#All],[CONCEPTO]],ACTIVIDADES!B18,Tabla3[[#All],[DETALLES]],B22) -> 0 | L22: =SUMIFS(Tabla3[[#All],[EGRESOS]],Tabla3[[#All],[PERIODO]],Tabla4[[#Headers],[OCTUBRE]],Tabla3[[#All],[ACTIVIDAD]],$B$16,Tabla3[[#All],[CONCEPTO]],$B$18,Tabla3[[#All],[DETALLES]],B22) -> 0 | M22: =SUMIFS(Tabla3[[#All],[EGRESOS]],Tabla3[[#All],[PERIODO]],Tabla4[[#Headers],[NOVIEMBRE]],Tabla3[[#All],[ACTIVIDAD]],$B$16,Tabla3[[#All],[CONCEPTO]],$B$18,Tabla3[[#All],[DETALLES]],B22) -> 0 | O22: =SUM(Tabla4[[#This Row],[ENERO]:[DICIEMBRE]]) -> 0 | P22: 52777452 | Q22: =Tabla4[[#This Row],[TOTAL]]/Tabla4[[#This Row],[ESTIMADO]] -> 0 | R22: 47589.805 | S22: =Tabla4[[#This Row],[USD]]/(350) -> 135.97087
B23: FLETES | C23: =SUMIFS(Tabla3[[#All],[EGRESOS]],Tabla3[[#All],[PERIODO]],Tabla4[[#Headers],[ENERO]],Tabla3[[#All],[ACTIVIDAD]],ACTIVIDADES!$B$16,Tabla3[[#All],[CONCEPTO]],ACTIVIDADES!$B$18,Tabla3[[#All],[DETALLES]],Tabla4[[#This Row],[ACTIVIDADES]]) -> 0 | D23: =SUMIFS(Tabla3[EGRESOS],Tabla3[ACTIVIDAD],ACTIVIDADES!$B$16,Tabla3[PERIODO],Tabla4[[#Headers],[FEBRERO]],Tabla3[CONCEPTO],ACTIVIDADES!B18,Tabla3[DETALLES],Tabla4[[#This Row],[ACTIVIDADES]]) -> 0 | E23: =SUMIFS(Tabla3[[#All],[EGRESOS]],Tabla3[[#All],[PERIODO]],Tabla4[[#Headers],[MARZO]],Tabla3[[#All],[ACTIVIDAD]],ACTIVIDADES!$B$16,Tabla3[[#All],[CONCEPTO]],ACTIVIDADES!$B$18,Tabla3[[#All],[DETALLES]],Tabla4[[#This Row],[ACTIVIDADES]]) -> 0 | F23: =SUMIFS(Tabla3[[#All],[EGRESOS]],Tabla3[[#All],[PERIODO]],Tabla4[[#Headers],[ABRIL]],Tabla3[[#All],[ACTIVIDAD]],ACTIVIDADES!B16,Tabla3[[#All],[CONCEPTO]],ACTIVIDADES!B18,Tabla3[[#All],[DETALLES]],Tabla4[[#This Row],[ACTIVIDADES]]) -> 0 | G23: =SUMIFS(Tabla3[[#All],[EGRESOS]],Tabla3[[#All],[PERIODO]],Tabla4[[#Headers],[MAYO]],Tabla3[[#All],[ACTIVIDAD]],ACTIVIDADES!$B$16,Tabla3[[#All],[CONCEPTO]],ACTIVIDADES!$B$18,Tabla3[[#All],[DETALLES]],Tabla4[[#This Row],[ACTIVIDADES]]) -> 0 | H23: =SUMIFS(Tabla3[[#All],[EGRESOS]],Tabla3[[#All],[PERIODO]],Tabla4[[#Headers],[JUNIO]],Tabla3[[#All],[ACTIVIDAD]],ACTIVIDADES!B16,Tabla3[[#All],[CONCEPTO]],ACTIVIDADES!B18,Tabla3[[#All],[DETALLES]],Tabla4[[#This Row],[ACTIVIDADES]]) -> 0 | I23: =SUMIFS(Tabla3[[#All],[EGRESOS]],Tabla3[[#All],[PERIODO]],Tabla4[[#Headers],[JULIO]],Tabla3[[#All],[ACTIVIDAD]],ACTIVIDADES!B16,Tabla3[[#All],[CONCEPTO]],ACTIVIDADES!B18,Tabla3[[#All],[DETALLES]],Tabla4[[#This Row],[ACTIVIDADES]]) -> 0 | J23: =SUMIFS(Tabla3[[#All],[EGRESOS]],Tabla3[[#All],[PERIODO]],Tabla4[[#Headers],[AGOSTO]],Tabla3[[#All],[ACTIVIDAD]],ACTIVIDADES!B16,Tabla3[[#All],[CONCEPTO]],ACTIVIDADES!B18,Tabla3[[#All],[DETALLES]],Tabla4[[#This Row],[ACTIVIDADES]]) -> 0 | K23: =SUMIFS(Tabla3[[#All],[EGRESOS]],Tabla3[[#All],[PERIODO]],Tabla4[[#Headers],[SEPTIEMBRE]],Tabla3[[#All],[ACTIVIDAD]],ACTIVIDADES!B16,Tabla3[[#All],[CONCEPTO]],ACTIVIDADES!B18,Tabla3[[#All],[DETALLES]],B23) -> 0 | L23: =SUMIFS(Tabla3[[#All],[EGRESOS]],Tabla3[[#All],[PERIODO]],Tabla4[[#Headers],[OCTUBRE]],Tabla3[[#All],[ACTIVIDAD]],$B$16,Tabla3[[#All],[CONCEPTO]],$B$18,Tabla3[[#All],[DETALLES]],B23) -> 0 | M23: =SUMIFS(Tabla3[[#All],[EGRESOS]],Tabla3[[#All],[PERIODO]],Tabla4[[#Headers],[NOVIEMBRE]],Tabla3[[#All],[ACTIVIDAD]],$B$16,Tabla3[[#All],[CONCEPTO]],$B$18,Tabla3[[#All],[DETALLES]],B23) -> 0 | O23: =SUM(Tabla4[[#This Row],[ENERO]:[DICIEMBRE]]) -> 0 | P23: 37735800 | Q23: =Tabla4[[#This Row],[TOTAL]]/Tabla4[[#This Row],[ESTIMADO]] -> 0 | R23: =Tabla4[[#This Row],[ESTIMADO]]/1140 -> 33101.579 | S23: =Tabla4[[#This Row],[USD]]/(350) -> 94.575941
B24: DESYUYADOR | C24: =SUMIFS(Tabla3[[#All],[EGRESOS]],Tabla3[[#All],[PERIODO]],Tabla4[[#Headers],[ENERO]],Tabla3[[#All],[ACTIVIDAD]],ACTIVIDADES!$B$16,Tabla3[[#All],[CONCEPTO]],ACTIVIDADES!$B$18,Tabla3[[#All],[DETALLES]],Tabla4[[#This Row],[ACTIVIDADES]]) -> 0 | D24: =SUMIFS(Tabla3[EGRESOS],Tabla3[ACTIVIDAD],ACTIVIDADES!$B$16,Tabla3[PERIODO],Tabla4[[#Headers],[FEBRERO]],Tabla3[CONCEPTO],ACTIVIDADES!B18,Tabla3[DETALLES],Tabla4[[#This Row],[ACTIVIDADES]]) -> 0 | E24: =SUMIFS(Tabla3[[#All],[EGRESOS]],Tabla3[[#All],[PERIODO]],Tabla4[[#Headers],[MARZO]],Tabla3[[#All],[ACTIVIDAD]],ACTIVIDADES!$B$16,Tabla3[[#All],[CONCEPTO]],ACTIVIDADES!$B$18,Tabla3[[#All],[DETALLES]],Tabla4[[#This Row],[ACTIVIDADES]]) -> 0 | F24: =SUMIFS(Tabla3[[#All],[EGRESOS]],Tabla3[[#All],[PERIODO]],Tabla4[[#Headers],[ABRIL]],Tabla3[[#All],[ACTIVIDAD]],ACTIVIDADES!B16,Tabla3[[#All],[CONCEPTO]],ACTIVIDADES!B18,Tabla3[[#All],[DETALLES]],Tabla4[[#This Row],[ACTIVIDADES]]) -> 0 | G24: =SUMIFS(Tabla3[[#All],[EGRESOS]],Tabla3[[#All],[PERIODO]],Tabla4[[#Headers],[MAYO]],Tabla3[[#All],[ACTIVIDAD]],ACTIVIDADES!$B$16,Tabla3[[#All],[CONCEPTO]],ACTIVIDADES!$B$18,Tabla3[[#All],[DETALLES]],Tabla4[[#This Row],[ACTIVIDADES]]) -> 0 | H24: =SUMIFS(Tabla3[[#All],[EGRESOS]],Tabla3[[#All],[PERIODO]],Tabla4[[#Headers],[JUNIO]],Tabla3[[#All],[ACTIVIDAD]],ACTIVIDADES!B16,Tabla3[[#All],[CONCEPTO]],ACTIVIDADES!B18,Tabla3[[#All],[DETALLES]],Tabla4[[#This Row],[ACTIVIDADES]]) -> 0 | I24: =SUMIFS(Tabla3[[#All],[EGRESOS]],Tabla3[[#All],[PERIODO]],Tabla4[[#Headers],[JULIO]],Tabla3[[#All],[ACTIVIDAD]],ACTIVIDADES!B16,Tabla3[[#All],[CONCEPTO]],ACTIVIDADES!B18,Tabla3[[#All],[DETALLES]],Tabla4[[#This Row],[ACTIVIDADES]]) -> 0 | J24: =SUMIFS(Tabla3[[#All],[EGRESOS]],Tabla3[[#All],[PERIODO]],Tabla4[[#Headers],[AGOSTO]],Tabla3[[#All],[ACTIVIDAD]],ACTIVIDADES!B16,Tabla3[[#All],[CONCEPTO]],ACTIVIDADES!B18,Tabla3[[#All],[DETALLES]],Tabla4[[#This Row],[ACTIVIDADES]]) -> 0 | K24: =SUMIFS(Tabla3[[#All],[EGRESOS]],Tabla3[[#All],[PERIODO]],Tabla4[[#Headers],[SEPTIEMBRE]],Tabla3[[#All],[ACTIVIDAD]],ACTIVIDADES!B16,Tabla3[[#All],[CONCEPTO]],ACTIVIDADES!B18,Tabla3[[#All],[DETALLES]],B24) -> 0 | L24: =SUMIFS(Tabla3[[#All],[EGRESOS]],Tabla3[[#All],[PERIODO]],Tabla4[[#Headers],[OCTUBRE]],Tabla3[[#All],[ACTIVIDAD]],$B$16,Tabla3[[#All],[CONCEPTO]],$B$18,Tabla3[[#All],[DETALLES]],B24) -> 0 | M24: =SUMIFS(Tabla3[[#All],[EGRESOS]],Tabla3[[#All],[PERIODO]],Tabla4[[#Headers],[NOVIEMBRE]],Tabla3[[#All],[ACTIVIDAD]],$B$16,Tabla3[[#All],[CONCEPTO]],$B$18,Tabla3[[#All],[DETALLES]],B24) -> 0 | O24: =SUM(Tabla4[[#This Row],[ENERO]:[DICIEMBRE]]) -> 0 | P24: 1100000 | Q24: =Tabla4[[#This Row],[TOTAL]]/Tabla4[[#This Row],[ESTIMADO]] -> 0 | R24: =Tabla4[[#This Row],[ESTIMADO]]/1140 -> 964.91228 | S24: =Tabla4[[#This Row],[USD]]/(350) -> 2.7568922
B25: COSECHA 114 HAS | C25: =SUMIFS(Tabla3[[#All],[EGRESOS]],Tabla3[[#All],[PERIODO]],Tabla4[[#Headers],[ENERO]],Tabla3[[#All],[ACTIVIDAD]],ACTIVIDADES!$B$16,Tabla3[[#All],[CONCEPTO]],ACTIVIDADES!$B$18,Tabla3[[#All],[DETALLES]],Tabla4[[#This Row],[ACTIVIDADES]]) -> 0 | D25: =SUMIFS(Tabla3[EGRESOS],Tabla3[ACTIVIDAD],ACTIVIDADES!$B$16,Tabla3[PERIODO],Tabla4[[#Headers],[FEBRERO]],Tabla3[CONCEPTO],ACTIVIDADES!B18,Tabla3[DETALLES],Tabla4[[#This Row],[ACTIVIDADES]]) -> 0 | E25: =SUMIFS(Tabla3[[#All],[EGRESOS]],Tabla3[[#All],[PERIODO]],Tabla4[[#Headers],[MARZO]],Tabla3[[#All],[ACTIVIDAD]],ACTIVIDADES!$B$16,Tabla3[[#All],[CONCEPTO]],ACTIVIDADES!$B$18,Tabla3[[#All],[DETALLES]],Tabla4[[#This Row],[ACTIVIDADES]]) -> 0 | F25: =SUMIFS(Tabla3[[#All],[EGRESOS]],Tabla3[[#All],[PERIODO]],Tabla4[[#Headers],[ABRIL]],Tabla3[[#All],[ACTIVIDAD]],ACTIVIDADES!B16,Tabla3[[#All],[CONCEPTO]],ACTIVIDADES!B18,Tabla3[[#All],[DETALLES]],Tabla4[[#This Row],[ACTIVIDADES]]) -> 0 | G25: =SUMIFS(Tabla3[[#All],[EGRESOS]],Tabla3[[#All],[PERIODO]],Tabla4[[#Headers],[MAYO]],Tabla3[[#All],[ACTIVIDAD]],ACTIVIDADES!$B$16,Tabla3[[#All],[CONCEPTO]],ACTIVIDADES!$B$18,Tabla3[[#All],[DETALLES]],Tabla4[[#This Row],[ACTIVIDADES]]) -> 0 | H25: =SUMIFS(Tabla3[[#All],[EGRESOS]],Tabla3[[#All],[PERIODO]],Tabla4[[#Headers],[JUNIO]],Tabla3[[#All],[ACTIVIDAD]],ACTIVIDADES!$B$16,Tabla3[[#All],[CONCEPTO]],ACTIVIDADES!$B$18,Tabla3[[#All],[DETALLES]],Tabla4[[#This Row],[ACTIVIDADES]]) -> 0 | I25: =SUMIFS(Tabla3[[#All],[EGRESOS]],Tabla3[[#All],[PERIODO]],Tabla4[[#Headers],[JULIO]],Tabla3[[#All],[ACTIVIDAD]],ACTIVIDADES!B16,Tabla3[[#All],[CONCEPTO]],ACTIVIDADES!B18,Tabla3[[#All],[DETALLES]],Tabla4[[#This Row],[ACTIVIDADES]]) -> 0 | J25: =SUMIFS(Tabla3[[#All],[EGRESOS]],Tabla3[[#All],[PERIODO]],Tabla4[[#Headers],[AGOSTO]],Tabla3[[#All],[ACTIVIDAD]],ACTIVIDADES!B16,Tabla3[[#All],[CONCEPTO]],ACTIVIDADES!B18,Tabla3[[#All],[DETALLES]],Tabla4[[#This Row],[ACTIVIDADES]]) -> 0 | K25: =SUMIFS(Tabla3[[#All],[EGRESOS]],Tabla3[[#All],[PERIODO]],Tabla4[[#Headers],[SEPTIEMBRE]],Tabla3[[#All],[ACTIVIDAD]],ACTIVIDADES!B16,Tabla3[[#All],[CONCEPTO]],ACTIVIDADES!B18,Tabla3[[#All],[DETALLES]],B25) -> 0 | L25: =SUMIFS(Tabla3[[#All],[EGRESOS]],Tabla3[[#All],[PERIODO]],Tabla4[[#Headers],[OCTUBRE]],Tabla3[[#All],[ACTIVIDAD]],$B$16,Tabla3[[#All],[CONCEPTO]],$B$18,Tabla3[[#All],[DETALLES]],B25) -> 0 | M25: =SUMIFS(Tabla3[[#All],[EGRESOS]],Tabla3[[#All],[PERIODO]],Tabla4[[#Headers],[NOVIEMBRE]],Tabla3[[#All],[ACTIVIDAD]],$B$16,Tabla3[[#All],[CONCEPTO]],$B$18,Tabla3[[#All],[DETALLES]],B25) -> 0 | O25: =SUM(Tabla4[[#This Row],[ENERO]:[DICIEMBRE]]) -> 0 | P25: =Tabla4[[#This Row],[USD]]*1360 -> 37095360 | Q25: =Tabla4[[#This Row],[TOTAL]]/Tabla4[[#This Row],[ESTIMADO]] -> 0 | R25: 27276 | S25: =Tabla4[[#This Row],[USD]]/(350) -> 77.931429
B26: EXTRACCION | C26: =SUMIFS(Tabla3[[#All],[EGRESOS]],Tabla3[[#All],[PERIODO]],Tabla4[[#Headers],[ENERO]],Tabla3[[#All],[ACTIVIDAD]],ACTIVIDADES!$B$16,Tabla3[[#All],[CONCEPTO]],ACTIVIDADES!$B$18,Tabla3[[#All],[DETALLES]],Tabla4[[#This Row],[ACTIVIDADES]]) -> 0 | D26: =SUMIFS(Tabla3[EGRESOS],Tabla3[ACTIVIDAD],ACTIVIDADES!$B$16,Tabla3[PERIODO],Tabla4[[#Headers],[FEBRERO]],Tabla3[CONCEPTO],ACTIVIDADES!B19,Tabla3[DETALLES],Tabla4[[#This Row],[ACTIVIDADES]]) -> 0 | E26: =SUMIFS(Tabla3[[#All],[EGRESOS]],Tabla3[[#All],[PERIODO]],Tabla4[[#Headers],[MARZO]],Tabla3[[#All],[ACTIVIDAD]],ACTIVIDADES!$B$16,Tabla3[[#All],[CONCEPTO]],ACTIVIDADES!$B$18,Tabla3[[#All],[DETALLES]],Tabla4[[#This Row],[ACTIVIDADES]]) -> 0 | F26: =SUMIFS(Tabla3[[#All],[EGRESOS]],Tabla3[[#All],[PERIODO]],Tabla4[[#Headers],[ABRIL]],Tabla3[[#All],[ACTIVIDAD]],ACTIVIDADES!B17,Tabla3[[#All],[CONCEPTO]],ACTIVIDADES!B19,Tabla3[[#All],[DETALLES]],Tabla4[[#This Row],[ACTIVIDADES]]) -> 0 | G26: =SUMIFS(Tabla3[[#All],[EGRESOS]],Tabla3[[#All],[PERIODO]],Tabla4[[#Headers],[MAYO]],Tabla3[[#All],[ACTIVIDAD]],ACTIVIDADES!$B$16,Tabla3[[#All],[CONCEPTO]],ACTIVIDADES!$B$18,Tabla3[[#All],[DETALLES]],Tabla4[[#This Row],[ACTIVIDADES]]) -> 0 | H26: =SUMIFS(Tabla3[[#All],[EGRESOS]],Tabla3[[#All],[PERIODO]],Tabla4[[#Headers],[JUNIO]],Tabla3[[#All],[ACTIVIDAD]],ACTIVIDADES!$B$16,Tabla3[[#All],[CONCEPTO]],ACTIVIDADES!$B$18,Tabla3[[#All],[DETALLES]],Tabla4[[#This Row],[ACTIVIDADES]]) -> 0 | I26: =SUMIFS(Tabla3[[#All],[EGRESOS]],Tabla3[[#All],[PERIODO]],Tabla4[[#Headers],[JULIO]],Tabla3[[#All],[ACTIVIDAD]],ACTIVIDADES!B17,Tabla3[[#All],[CONCEPTO]],ACTIVIDADES!B19,Tabla3[[#All],[DETALLES]],Tabla4[[#This Row],[ACTIVIDADES]]) -> 0 | J26: =SUMIFS(Tabla3[[#All],[EGRESOS]],Tabla3[[#All],[PERIODO]],Tabla4[[#Headers],[AGOSTO]],Tabla3[[#All],[ACTIVIDAD]],ACTIVIDADES!B17,Tabla3[[#All],[CONCEPTO]],ACTIVIDADES!B19,Tabla3[[#All],[DETALLES]],Tabla4[[#This Row],[ACTIVIDADES]]) -> 0 | K26: =SUMIFS(Tabla3[[#All],[EGRESOS]],Tabla3[[#All],[PERIODO]],Tabla4[[#Headers],[SEPTIEMBRE]],Tabla3[[#All],[ACTIVIDAD]],ACTIVIDADES!B17,Tabla3[[#All],[CONCEPTO]],ACTIVIDADES!B19,Tabla3[[#All],[DETALLES]],B26) -> 0 | L26: =SUMIFS(Tabla3[[#All],[EGRESOS]],Tabla3[[#All],[PERIODO]],Tabla4[[#Headers],[OCTUBRE]],Tabla3[[#All],[ACTIVIDAD]],$B$16,Tabla3[[#All],[CONCEPTO]],$B$18,Tabla3[[#All],[DETALLES]],B26) -> 0 | M26: =SUMIFS(Tabla3[[#All],[EGRESOS]],Tabla3[[#All],[PERIODO]],Tabla4[[#Headers],[NOVIEMBRE]],Tabla3[[#All],[ACTIVIDAD]],$B$16,Tabla3[[#All],[CONCEPTO]],$B$18,Tabla3[[#All],[DETALLES]],B26) -> 0 | O26: =SUM(Tabla4[[#This Row],[ENERO]:[DICIEMBRE]]) -> 0 | P26: 3550000 | Q26: =Tabla4[[#This Row],[TOTAL]]/Tabla4[[#This Row],[ESTIMADO]] -> 0 | R26: =Tabla4[[#This Row],[ESTIMADO]]/1140 -> 3114.0351 | S26: =Tabla4[[#This Row],[USD]]/(350) -> 8.8972431
B27: SOJA P EXPELLER | C27: =SUMIFS(Tabla3[[#All],[FACTURA]],Tabla3[[#All],[RUBRO]],Tabla4[[#Headers],[ENERO]],Tabla3[[#All],[EGRESOS]],$B$16,Tabla3[[#All],[SALDO]],$B$18,Tabla3[[#All],[SALDO BANCO]],#REF!) -> 0 | D27: =SUMIFS(Tabla3[[#All],[RDS]],Tabla3[[#All],[CONCEPTO]],Tabla4[[#Headers],[FEBRERO]],Tabla3[[#All],[INGRESOS]],$B$16,Tabla3[[#All],[SALDO BANCO]],$B$18,Tabla3[[#All],[TC]],#REF!) -> 0 | E27: =SUMIFS(Tabla3[[#All],[SOCIO]],Tabla3[[#All],[DETALLES]],Tabla4[[#Headers],[MARZO]],Tabla3[[#All],[SALDO]],$B$16,Tabla3[[#All],[TC]],$B$18,Tabla3[[#All],[EGRES USD]],#REF!) -> 0 | F27: =SUMIFS(Tabla3[[#All],[CAMPAÑA]],Tabla3[[#All],[PROVEEDOR CLIENTE]],Tabla4[[#Headers],[ABRIL]],Tabla3[[#All],[SALDO BANCO]],$B$16,Tabla3[[#All],[EGRES USD]],$B$18,Tabla3[[#All],[INGRES USD]],#REF!) -> 0 | G27: =SUMIFS(#REF!,Tabla3[[#All],[FACTURA]],Tabla4[[#Headers],[MAYO]],Tabla3[[#All],[TC]],$B$16,Tabla3[[#All],[INGRES USD]],$B$18,Tabla3[[#All],[MONEDA]],#REF!) -> #REF! | H27: =SUMIFS(#REF!,Tabla3[[#All],[RDS]],Tabla4[[#Headers],[JUNIO]],Tabla3[[#All],[EGRES USD]],$B$16,Tabla3[[#All],[MONEDA]],$B$18,Tabla3[[#All],[CUENTA]],#REF!) -> #REF! | I27: =SUMIFS(Tabla3[[#All],[PERIODO]],Tabla3[[#All],[SOCIO]],Tabla4[[#Headers],[JULIO]],Tabla3[[#All],[INGRES USD]],$B$16,Tabla3[[#All],[CUENTA]],$B$18,Tabla3[[#All],[BANCO]],#REF!) -> 0 | J27: =SUMIFS(Tabla3[[#All],[FECHA]],Tabla3[[#All],[CAMPAÑA]],Tabla4[[#Headers],[AGOSTO]],Tabla3[[#All],[MONEDA]],$B$16,Tabla3[[#All],[BANCO]],$B$18,Tabla3[[#All],[ACTIVIDAD]],#REF!) -> 0 | K27: =SUMIFS(Tabla3[[#All],[DESCRIPCION]],#REF!,Tabla4[[#Headers],[SEPTIEMBRE]],Tabla3[[#All],[CUENTA]],$B$16,Tabla3[[#All],[ACTIVIDAD]],$B$18,Tabla3[[#All],[RUBRO]],#REF!) -> #REF! | L27: =SUMIFS(Tabla3[[#All],[N DE REFERENCIA]],#REF!,Tabla4[[#Headers],[OCTUBRE]],Tabla3[[#All],[BANCO]],$B$16,Tabla3[[#All],[RUBRO]],$B$18,Tabla3[[#All],[CONCEPTO]],A27) -> #REF! | M27: =SUMIFS(Tabla3[[#All],[EGRESOS]],Tabla3[[#All],[PERIODO]],Tabla4[[#Headers],[NOVIEMBRE]],Tabla3[[#All],[ACTIVIDAD]],$B$16,Tabla3[[#All],[CONCEPTO]],$B$18,Tabla3[[#All],[DETALLES]],B27) -> 0
B28: MAIZ | C28: =SUBTOTAL(109,C29:C37) -> 0 | D28: =SUBTOTAL(109,D29:D37) -> 0 | E28: =SUBTOTAL(109,E29:E37) -> 0 | F28: =SUBTOTAL(109,F29:F37) -> 0 | G28: =SUBTOTAL(109,G29:G37) -> 0 | H28: =SUBTOTAL(109,H29:H37) -> 0 | I28: =SUBTOTAL(109,I29:I37) -> 0 | J28: =SUBTOTAL(109,J29:J37) -> 0 | ... N28: =SUBTOTAL(109,N29:N37) -> 0
B29: SIEMBRA | C29: =SUMIFS(Tabla3[[#All],[EGRESOS]],Tabla3[[#All],[PERIODO]],Tabla4[[#Headers],[ENERO]],Tabla3[[#All],[ACTIVIDAD]],ACTIVIDADES!$B$16,Tabla3[[#All],[CONCEPTO]],ACTIVIDADES!$B$28,Tabla3[[#All],[DETALLES]],Tabla4[[#This Row],[ACTIVIDADES]]) -> 0 | D29: =SUMIFS(Tabla3[EGRESOS],Tabla3[ACTIVIDAD],ACTIVIDADES!$B$16,Tabla3[PERIODO],Tabla4[[#Headers],[FEBRERO]],Tabla3[CONCEPTO],ACTIVIDADES!B28,Tabla3[DETALLES],Tabla4[[#This Row],[ACTIVIDADES]]) -> 0 | E29: =SUMIFS(Tabla3[[#All],[EGRESOS]],Tabla3[[#All],[PERIODO]],Tabla4[[#Headers],[MARZO]],Tabla3[[#All],[ACTIVIDAD]],ACTIVIDADES!$B$16,Tabla3[[#All],[CONCEPTO]],ACTIVIDADES!$B$28,Tabla3[[#All],[DETALLES]],Tabla4[[#This Row],[ACTIVIDADES]]) -> 0 | F29: =SUMIFS(Tabla3[[#All],[EGRESOS]],Tabla3[[#All],[PERIODO]],Tabla4[[#Headers],[ABRIL]],Tabla3[[#All],[ACTIVIDAD]],ACTIVIDADES!B16,Tabla3[[#All],[CONCEPTO]],ACTIVIDADES!B28,Tabla3[[#All],[DETALLES]],Tabla4[[#This Row],[ACTIVIDADES]]) -> 0 | G29: =SUMIFS(Tabla3[[#All],[EGRESOS]],Tabla3[[#All],[PERIODO]],Tabla4[[#Headers],[MAYO]],Tabla3[[#All],[ACTIVIDAD]],ACTIVIDADES!$B$16,Tabla3[[#All],[CONCEPTO]],ACTIVIDADES!$B$28,Tabla3[[#All],[DETALLES]],Tabla4[[#This Row],[ACTIVIDADES]]) -> 0 | H29: =SUMIFS(Tabla3[[#All],[EGRESOS]],Tabla3[[#All],[PERIODO]],Tabla4[[#Headers],[JUNIO]],Tabla3[[#All],[ACTIVIDAD]],ACTIVIDADES!B16,Tabla3[[#All],[CONCEPTO]],ACTIVIDADES!B28,Tabla3[[#All],[DETALLES]],Tabla4[[#This Row],[ACTIVIDADES]]) -> 0 | I29: =SUMIFS(Tabla3[[#All],[EGRESOS]],Tabla3[[#All],[PERIODO]],Tabla4[[#Headers],[JULIO]],Tabla3[[#All],[ACTIVIDAD]],ACTIVIDADES!B16,Tabla3[[#All],[CONCEPTO]],ACTIVIDADES!B28,Tabla3[[#All],[DETALLES]],Tabla4[[#This Row],[ACTIVIDADES]]) -> 0 | J29: =SUMIFS(Tabla3[[#All],[EGRESOS]],Tabla3[[#All],[PERIODO]],Tabla4[[#Headers],[AGOSTO]],Tabla3[[#All],[ACTIVIDAD]],ACTIVIDADES!B16,Tabla3[[#All],[CONCEPTO]],ACTIVIDADES!B28,Tabla3[[#All],[DETALLES]],Tabla4[[#This Row],[ACTIVIDADES]]) -> 0 | K29: =SUMIFS(Tabla3[[#All],[EGRESOS]],Tabla3[[#All],[PERIODO]],Tabla4[[#Headers],[SEPTIEMBRE]],Tabla3[[#All],[ACTIVIDAD]],ACTIVIDADES!B16,Tabla3[[#All],[CONCEPTO]],ACTIVIDADES!B28,Tabla3[[#All],[DETALLES]],B29) -> 0 | L29: =SUMIFS(Tabla3[[#All],[EGRESOS]],Tabla3[[#All],[PERIODO]],Tabla4[[#Headers],[OCTUBRE]],Tabla3[[#All],[ACTIVIDAD]],$B$16,Tabla3[[#All],[CONCEPTO]],$B$28,Tabla3[[#All],[DETALLES]],B29) -> 0 | M29: =SUMIFS(Tabla3[[#All],[EGRESOS]],Tabla3[[#All],[PERIODO]],Tabla4[[#Headers],[NOVIEMBRE]],Tabla3[[#All],[ACTIVIDAD]],$B$16,Tabla3[[#All],[CONCEPTO]],$B$28,Tabla3[[#All],[DETALLES]],B29) -> 0 | O29: =SUM(Tabla4[[#This Row],[ENERO]:[DICIEMBRE]]) -> 0 | P29: =Tabla4[[#This Row],[USD]]*1140 -> 8508500 | Q29: =Tabla4[[#This Row],[TOTAL]]/Tabla4[[#This Row],[ESTIMADO]] -> 0 | R29: 7463.5965 | S29: =Tabla4[[#This Row],[USD]]/140 -> 53.311404
B30: SEMILLAS | C30: =SUMIFS(Tabla3[[#All],[EGRESOS]],Tabla3[[#All],[PERIODO]],Tabla4[[#Headers],[ENERO]],Tabla3[[#All],[ACTIVIDAD]],ACTIVIDADES!$B$16,Tabla3[[#All],[CONCEPTO]],ACTIVIDADES!$B$28,Tabla3[[#All],[DETALLES]],Tabla4[[#This Row],[ACTIVIDADES]]) -> 0 | D30: =SUMIFS(Tabla3[EGRESOS],Tabla3[ACTIVIDAD],ACTIVIDADES!$B$16,Tabla3[PERIODO],Tabla4[[#Headers],[FEBRERO]],Tabla3[CONCEPTO],ACTIVIDADES!B28,Tabla3[DETALLES],Tabla4[[#This Row],[ACTIVIDADES]]) -> 0 | E30: =SUMIFS(Tabla3[[#All],[EGRESOS]],Tabla3[[#All],[PERIODO]],Tabla4[[#Headers],[MARZO]],Tabla3[[#All],[ACTIVIDAD]],ACTIVIDADES!$B$16,Tabla3[[#All],[CONCEPTO]],ACTIVIDADES!$B$28,Tabla3[[#All],[DETALLES]],Tabla4[[#This Row],[ACTIVIDADES]]) -> 0 | F30: =SUMIFS(Tabla3[[#All],[EGRESOS]],Tabla3[[#All],[PERIODO]],Tabla4[[#Headers],[ABRIL]],Tabla3[[#All],[ACTIVIDAD]],ACTIVIDADES!B16,Tabla3[[#All],[CONCEPTO]],ACTIVIDADES!B28,Tabla3[[#All],[DETALLES]],Tabla4[[#This Row],[ACTIVIDADES]]) -> 0 | G30: =SUMIFS(Tabla3[[#All],[EGRESOS]],Tabla3[[#All],[PERIODO]],Tabla4[[#Headers],[MAYO]],Tabla3[[#All],[ACTIVIDAD]],ACTIVIDADES!$B$16,Tabla3[[#All],[CONCEPTO]],ACTIVIDADES!$B$28,Tabla3[[#All],[DETALLES]],Tabla4[[#This Row],[ACTIVIDADES]]) -> 0 | H30: =SUMIFS(Tabla3[[#All],[EGRESOS]],Tabla3[[#All],[PERIODO]],Tabla4[[#Headers],[JUNIO]],Tabla3[[#All],[ACTIVIDAD]],ACTIVIDADES!B16,Tabla3[[#All],[CONCEPTO]],ACTIVIDADES!B28,Tabla3[[#All],[DETALLES]],Tabla4[[#This Row],[ACTIVIDADES]]) -> 0 | I30: =SUMIFS(Tabla3[[#All],[EGRESOS]],Tabla3[[#All],[PERIODO]],Tabla4[[#Headers],[JULIO]],Tabla3[[#All],[ACTIVIDAD]],ACTIVIDADES!B16,Tabla3[[#All],[CONCEPTO]],ACTIVIDADES!B28,Tabla3[[#All],[DETALLES]],Tabla4[[#This Row],[ACTIVIDADES]]) -> 0 | J30: =SUMIFS(Tabla3[[#All],[EGRESOS]],Tabla3[[#All],[PERIODO]],Tabla4[[#Headers],[AGOSTO]],Tabla3[[#All],[ACTIVIDAD]],ACTIVIDADES!B16,Tabla3[[#All],[CONCEPTO]],ACTIVIDADES!B28,Tabla3[[#All],[DETALLES]],Tabla4[[#This Row],[ACTIVIDADES]]) -> 0 | K30: =SUMIFS(Tabla3[[#All],[EGRESOS]],Tabla3[[#All],[PERIODO]],Tabla4[[#Headers],[SEPTIEMBRE]],Tabla3[[#All],[ACTIVIDAD]],ACTIVIDADES!B16,Tabla3[[#All],[CONCEPTO]],ACTIVIDADES!B28,Tabla3[[#All],[DETALLES]],B30) -> 0 | L30: =SUMIFS(Tabla3[[#All],[EGRESOS]],Tabla3[[#All],[PERIODO]],Tabla4[[#Headers],[OCTUBRE]],Tabla3[[#All],[ACTIVIDAD]],$B$16,Tabla3[[#All],[CONCEPTO]],$B$28,Tabla3[[#All],[DETALLES]],B30) -> 0 | M30: =SUMIFS(Tabla3[[#All],[EGRESOS]],Tabla3[[#All],[PERIODO]],Tabla4[[#Headers],[NOVIEMBRE]],Tabla3[[#All],[ACTIVIDAD]],$B$16,Tabla3[[#All],[CONCEPTO]],$B$28,Tabla3[[#All],[DETALLES]],B30) -> 0 | O30: =SUM(Tabla4[[#This Row],[ENERO]:[DICIEMBRE]]) -> 0 | P30: =Tabla4[[#This Row],[USD]]*1140 -> 31920000 | Q30: =Tabla4[[#This Row],[TOTAL]]/Tabla4[[#This Row],[ESTIMADO]] -> 0 | R30: 28000 | S30: =Tabla4[[#This Row],[USD]]/140 -> 200
B31: APLICACIONES | C31: =SUMIFS(Tabla3[[#All],[EGRESOS]],Tabla3[[#All],[PERIODO]],Tabla4[[#Headers],[ENERO]],Tabla3[[#All],[ACTIVIDAD]],ACTIVIDADES!$B$16,Tabla3[[#All],[CONCEPTO]],ACTIVIDADES!$B$28,Tabla3[[#All],[DETALLES]],Tabla4[[#This Row],[ACTIVIDADES]]) -> 0 | D31: =SUMIFS(Tabla3[EGRESOS],Tabla3[ACTIVIDAD],ACTIVIDADES!$B$16,Tabla3[PERIODO],Tabla4[[#Headers],[FEBRERO]],Tabla3[CONCEPTO],ACTIVIDADES!B28,Tabla3[DETALLES],Tabla4[[#This Row],[ACTIVIDADES]]) -> 0 | E31: =SUMIFS(Tabla3[[#All],[EGRESOS]],Tabla3[[#All],[PERIODO]],Tabla4[[#Headers],[MARZO]],Tabla3[[#All],[ACTIVIDAD]],ACTIVIDADES!$B$16,Tabla3[[#All],[CONCEPTO]],ACTIVIDADES!$B$28,Tabla3[[#All],[DETALLES]],Tabla4[[#This Row],[ACTIVIDADES]]) -> 0 | F31: =SUMIFS(Tabla3[[#All],[EGRESOS]],Tabla3[[#All],[PERIODO]],Tabla4[[#Headers],[ABRIL]],Tabla3[[#All],[ACTIVIDAD]],ACTIVIDADES!B16,Tabla3[[#All],[CONCEPTO]],ACTIVIDADES!B28,Tabla3[[#All],[DETALLES]],Tabla4[[#This Row],[ACTIVIDADES]]) -> 0 | G31: =SUMIFS(Tabla3[[#All],[EGRESOS]],Tabla3[[#All],[PERIODO]],Tabla4[[#Headers],[MAYO]],Tabla3[[#All],[ACTIVIDAD]],ACTIVIDADES!$B$16,Tabla3[[#All],[CONCEPTO]],ACTIVIDADES!$B$28,Tabla3[[#All],[DETALLES]],Tabla4[[#This Row],[ACTIVIDADES]]) -> 0 | H31: =SUMIFS(Tabla3[[#All],[EGRESOS]],Tabla3[[#All],[PERIODO]],Tabla4[[#Headers],[JUNIO]],Tabla3[[#All],[ACTIVIDAD]],ACTIVIDADES!B16,Tabla3[[#All],[CONCEPTO]],ACTIVIDADES!B28,Tabla3[[#All],[DETALLES]],Tabla4[[#This Row],[ACTIVIDADES]]) -> 0 | I31: =SUMIFS(Tabla3[[#All],[EGRESOS]],Tabla3[[#All],[PERIODO]],Tabla4[[#Headers],[JULIO]],Tabla3[[#All],[ACTIVIDAD]],ACTIVIDADES!B16,Tabla3[[#All],[CONCEPTO]],ACTIVIDADES!B28,Tabla3[[#All],[DETALLES]],Tabla4[[#This Row],[ACTIVIDADES]]) -> 0 | J31: =SUMIFS(Tabla3[[#All],[EGRESOS]],Tabla3[[#All],[PERIODO]],Tabla4[[#Headers],[AGOSTO]],Tabla3[[#All],[ACTIVIDAD]],ACTIVIDADES!B16,Tabla3[[#All],[CONCEPTO]],ACTIVIDADES!B28,Tabla3[[#All],[DETALLES]],Tabla4[[#This Row],[ACTIVIDADES]]) -> 0 | K31: =SUMIFS(Tabla3[[#All],[EGRESOS]],Tabla3[[#All],[PERIODO]],Tabla4[[#Headers],[SEPTIEMBRE]],Tabla3[[#All],[ACTIVIDAD]],ACTIVIDADES!B16,Tabla3[[#All],[CONCEPTO]],ACTIVIDADES!B28,Tabla3[[#All],[DETALLES]],B31) -> 0 | L31: =SUMIFS(Tabla3[[#All],[EGRESOS]],Tabla3[[#All],[PERIODO]],Tabla4[[#Headers],[OCTUBRE]],Tabla3[[#All],[ACTIVIDAD]],$B$16,Tabla3[[#All],[CONCEPTO]],$B$28,Tabla3[[#All],[DETALLES]],B31) -> 0 | M31: =SUMIFS(Tabla3[[#All],[EGRESOS]],Tabla3[[#All],[PERIODO]],Tabla4[[#Headers],[NOVIEMBRE]],Tabla3[[#All],[ACTIVIDAD]],$B$16,Tabla3[[#All],[CONCEPTO]],$B$28,Tabla3[[#All],[DETALLES]],B31) -> 0 | O31: =SUM(Tabla4[[#This Row],[ENERO]:[DICIEMBRE]]) -> 0 | P31: =Tabla4[[#This Row],[USD]]*1140 -> 5432942.7 | Q31: =Tabla4[[#This Row],[TOTAL]]/Tabla4[[#This Row],[ESTIMADO]] -> 0 | R31: 4765.7392 | S31: =Tabla4[[#This Row],[USD]]/140 -> 34.040994
B32: FLETES FERTILIZANTE | C32: =SUMIFS(Tabla3[[#All],[EGRESOS]],Tabla3[[#All],[PERIODO]],Tabla4[[#Headers],[ENERO]],Tabla3[[#All],[ACTIVIDAD]],ACTIVIDADES!$B$16,Tabla3[[#All],[CONCEPTO]],ACTIVIDADES!$B$28,Tabla3[[#All],[DETALLES]],Tabla4[[#This Row],[ACTIVIDADES]]) -> 0 | D32: =SUMIFS(Tabla3[EGRESOS],Tabla3[ACTIVIDAD],ACTIVIDADES!$B$16,Tabla3[PERIODO],Tabla4[[#Headers],[FEBRERO]],Tabla3[CONCEPTO],ACTIVIDADES!B28,Tabla3[DETALLES],Tabla4[[#This Row],[ACTIVIDADES]]) -> 0 | E32: =SUMIFS(Tabla3[[#All],[EGRESOS]],Tabla3[[#All],[PERIODO]],Tabla4[[#Headers],[MARZO]],Tabla3[[#All],[ACTIVIDAD]],ACTIVIDADES!$B$16,Tabla3[[#All],[CONCEPTO]],ACTIVIDADES!$B$28,Tabla3[[#All],[DETALLES]],Tabla4[[#This Row],[ACTIVIDADES]]) -> 0 | F32: =SUMIFS(Tabla3[[#All],[EGRESOS]],Tabla3[[#All],[PERIODO]],Tabla4[[#Headers],[ABRIL]],Tabla3[[#All],[ACTIVIDAD]],ACTIVIDADES!B16,Tabla3[[#All],[CONCEPTO]],ACTIVIDADES!B28,Tabla3[[#All],[DETALLES]],Tabla4[[#This Row],[ACTIVIDADES]]) -> 0 | G32: =SUMIFS(Tabla3[[#All],[EGRESOS]],Tabla3[[#All],[PERIODO]],Tabla4[[#Headers],[MAYO]],Tabla3[[#All],[ACTIVIDAD]],ACTIVIDADES!$B$16,Tabla3[[#All],[CONCEPTO]],ACTIVIDADES!$B$28,Tabla3[[#All],[DETALLES]],Tabla4[[#This Row],[ACTIVIDADES]]) -> 0 | H32: =SUMIFS(Tabla3[[#All],[EGRESOS]],Tabla3[[#All],[PERIODO]],Tabla4[[#Headers],[JUNIO]],Tabla3[[#All],[ACTIVIDAD]],ACTIVIDADES!B16,Tabla3[[#All],[CONCEPTO]],ACTIVIDADES!B28,Tabla3[[#All],[DETALLES]],Tabla4[[#This Row],[ACTIVIDADES]]) -> 0 | I32: =SUMIFS(Tabla3[[#All],[EGRESOS]],Tabla3[[#All],[PERIODO]],Tabla4[[#Headers],[JULIO]],Tabla3[[#All],[ACTIVIDAD]],ACTIVIDADES!B16,Tabla3[[#All],[CONCEPTO]],ACTIVIDADES!B28,Tabla3[[#All],[DETALLES]],Tabla4[[#This Row],[ACTIVIDADES]]) -> 0 | J32: =SUMIFS(Tabla3[[#All],[EGRESOS]],Tabla3[[#All],[PERIODO]],Tabla4[[#Headers],[AGOSTO]],Tabla3[[#All],[ACTIVIDAD]],ACTIVIDADES!B16,Tabla3[[#All],[CONCEPTO]],ACTIVIDADES!B28,Tabla3[[#All],[DETALLES]],Tabla4[[#This Row],[ACTIVIDADES]]) -> 0 | K32: =SUMIFS(Tabla3[[#All],[EGRESOS]],Tabla3[[#All],[PERIODO]],Tabla4[[#Headers],[SEPTIEMBRE]],Tabla3[[#All],[ACTIVIDAD]],ACTIVIDADES!B16,Tabla3[[#All],[CONCEPTO]],ACTIVIDADES!B28,Tabla3[[#All],[DETALLES]],B32) -> 0 | L32: =SUMIFS(Tabla3[[#All],[EGRESOS]],Tabla3[[#All],[PERIODO]],Tabla4[[#Headers],[OCTUBRE]],Tabla3[[#All],[ACTIVIDAD]],$B$16,Tabla3[[#All],[CONCEPTO]],$B$28,Tabla3[[#All],[DETALLES]],B32) -> 0 | M32: =SUMIFS(Tabla3[[#All],[EGRESOS]],Tabla3[[#All],[PERIODO]],Tabla4[[#Headers],[NOVIEMBRE]],Tabla3[[#All],[ACTIVIDAD]],$B$16,Tabla3[[#All],[CONCEPTO]],$B$28,Tabla3[[#All],[DETALLES]],B32) -> 0 | O32: =SUM(Tabla4[[#This Row],[ENERO]:[DICIEMBRE]]) -> 0 | P32: =Tabla4[[#This Row],[USD]]*1140 -> 500000 | Q32: =Tabla4[[#This Row],[TOTAL]]/Tabla4[[#This Row],[ESTIMADO]] -> 0 | R32: 438.59649 | S32: =Tabla4[[#This Row],[USD]]/140 -> 3.1328321
B33: INSUMOS 2025 | C33: =SUMIFS(Tabla3[[#All],[EGRESOS]],Tabla3[[#All],[PERIODO]],Tabla4[[#Headers],[ENERO]],Tabla3[[#All],[ACTIVIDAD]],ACTIVIDADES!$B$16,Tabla3[[#All],[CONCEPTO]],ACTIVIDADES!$B$28,Tabla3[[#All],[DETALLES]],Tabla4[[#This Row],[ACTIVIDADES]]) -> 0 | D33: =SUMIFS(Tabla3[EGRESOS],Tabla3[ACTIVIDAD],ACTIVIDADES!$B$16,Tabla3[PERIODO],Tabla4[[#Headers],[FEBRERO]],Tabla3[CONCEPTO],ACTIVIDADES!B28,Tabla3[DETALLES],Tabla4[[#This Row],[ACTIVIDADES]]) -> 0 | E33: =SUMIFS(Tabla3[[#All],[EGRESOS]],Tabla3[[#All],[PERIODO]],Tabla4[[#Headers],[MARZO]],Tabla3[[#All],[ACTIVIDAD]],ACTIVIDADES!$B$16,Tabla3[[#All],[CONCEPTO]],ACTIVIDADES!$B$28,Tabla3[[#All],[DETALLES]],Tabla4[[#This Row],[ACTIVIDADES]]) -> 0 | F33: =SUMIFS(Tabla3[[#All],[EGRESOS]],Tabla3[[#All],[PERIODO]],Tabla4[[#Headers],[ABRIL]],Tabla3[[#All],[ACTIVIDAD]],ACTIVIDADES!B16,Tabla3[[#All],[CONCEPTO]],ACTIVIDADES!B28,Tabla3[[#All],[DETALLES]],Tabla4[[#This Row],[ACTIVIDADES]]) -> 0 | G33: =SUMIFS(Tabla3[[#All],[EGRESOS]],Tabla3[[#All],[PERIODO]],Tabla4[[#Headers],[MAYO]],Tabla3[[#All],[ACTIVIDAD]],ACTIVIDADES!$B$16,Tabla3[[#All],[CONCEPTO]],ACTIVIDADES!$B$28,Tabla3[[#All],[DETALLES]],Tabla4[[#This Row],[ACTIVIDADES]]) -> 0 | H33: =SUMIFS(Tabla3[[#All],[EGRESOS]],Tabla3[[#All],[PERIODO]],Tabla4[[#Headers],[JUNIO]],Tabla3[[#All],[ACTIVIDAD]],ACTIVIDADES!B16,Tabla3[[#All],[CONCEPTO]],ACTIVIDADES!B28,Tabla3[[#All],[DETALLES]],Tabla4[[#This Row],[ACTIVIDADES]]) -> 0 | I33: =SUMIFS(Tabla3[[#All],[EGRESOS]],Tabla3[[#All],[PERIODO]],Tabla4[[#Headers],[JULIO]],Tabla3[[#All],[ACTIVIDAD]],ACTIVIDADES!B16,Tabla3[[#All],[CONCEPTO]],ACTIVIDADES!B28,Tabla3[[#All],[DETALLES]],Tabla4[[#This Row],[ACTIVIDADES]]) -> 0 | J33: =SUMIFS(Tabla3[[#All],[EGRESOS]],Tabla3[[#All],[PERIODO]],Tabla4[[#Headers],[AGOSTO]],Tabla3[[#All],[ACTIVIDAD]],ACTIVIDADES!B16,Tabla3[[#All],[CONCEPTO]],ACTIVIDADES!B28,Tabla3[[#All],[DETALLES]],Tabla4[[#This Row],[ACTIVIDADES]]) -> 0 | K33: =SUMIFS(Tabla3[[#All],[EGRESOS]],Tabla3[[#All],[PERIODO]],Tabla4[[#Headers],[SEPTIEMBRE]],Tabla3[[#All],[ACTIVIDAD]],ACTIVIDADES!B16,Tabla3[[#All],[CONCEPTO]],ACTIVIDADES!B28,Tabla3[[#All],[DETALLES]],B33) -> 0 | L33: =SUMIFS(Tabla3[[#All],[EGRESOS]],Tabla3[[#All],[PERIODO]],Tabla4[[#Headers],[OCTUBRE]],Tabla3[[#All],[ACTIVIDAD]],$B$16,Tabla3[[#All],[CONCEPTO]],$B$28,Tabla3[[#All],[DETALLES]],B33) -> 0 | M33: =SUMIFS(Tabla3[[#All],[EGRESOS]],Tabla3[[#All],[PERIODO]],Tabla4[[#Headers],[NOVIEMBRE]],Tabla3[[#All],[ACTIVIDAD]],$B$16,Tabla3[[#All],[CONCEPTO]],$B$28,Tabla3[[#All],[DETALLES]],B33) -> 0 | O33: =SUM(Tabla4[[#This Row],[ENERO]:[DICIEMBRE]]) -> 0 | P33: =Tabla4[[#This Row],[USD]]*1140 -> 56517052 | Q33: =Tabla4[[#This Row],[TOTAL]]/Tabla4[[#This Row],[ESTIMADO]] -> 0 | R33: 49576.362 | S33: =Tabla4[[#This Row],[USD]]/140 -> 354.11687
B34: FLETES | C34: =SUMIFS(Tabla3[[#All],[EGRESOS]],Tabla3[[#All],[PERIODO]],Tabla4[[#Headers],[ENERO]],Tabla3[[#All],[ACTIVIDAD]],ACTIVIDADES!$B$16,Tabla3[[#All],[CONCEPTO]],ACTIVIDADES!$B$28,Tabla3[[#All],[DETALLES]],Tabla4[[#This Row],[ACTIVIDADES]]) -> 0 | D34: =SUMIFS(Tabla3[EGRESOS],Tabla3[ACTIVIDAD],ACTIVIDADES!$B$16,Tabla3[PERIODO],Tabla4[[#Headers],[FEBRERO]],Tabla3[CONCEPTO],ACTIVIDADES!B28,Tabla3[DETALLES],Tabla4[[#This Row],[ACTIVIDADES]]) -> 0 | E34: =SUMIFS(Tabla3[[#All],[EGRESOS]],Tabla3[[#All],[PERIODO]],Tabla4[[#Headers],[MARZO]],Tabla3[[#All],[ACTIVIDAD]],ACTIVIDADES!$B$16,Tabla3[[#All],[CONCEPTO]],ACTIVIDADES!$B$28,Tabla3[[#All],[DETALLES]],Tabla4[[#This Row],[ACTIVIDADES]]) -> 0 | F34: =SUMIFS(Tabla3[[#All],[EGRESOS]],Tabla3[[#All],[PERIODO]],Tabla4[[#Headers],[ABRIL]],Tabla3[[#All],[ACTIVIDAD]],ACTIVIDADES!B16,Tabla3[[#All],[CONCEPTO]],ACTIVIDADES!B28,Tabla3[[#All],[DETALLES]],Tabla4[[#This Row],[ACTIVIDADES]]) -> 0 | G34: =SUMIFS(Tabla3[[#All],[EGRESOS]],Tabla3[[#All],[PERIODO]],Tabla4[[#Headers],[MAYO]],Tabla3[[#All],[ACTIVIDAD]],ACTIVIDADES!$B$16,Tabla3[[#All],[CONCEPTO]],ACTIVIDADES!$B$28,Tabla3[[#All],[DETALLES]],Tabla4[[#This Row],[ACTIVIDADES]]) -> 0 | H34: =SUMIFS(Tabla3[[#All],[EGRESOS]],Tabla3[[#All],[PERIODO]],Tabla4[[#Headers],[JUNIO]],Tabla3[[#All],[ACTIVIDAD]],ACTIVIDADES!B16,Tabla3[[#All],[CONCEPTO]],ACTIVIDADES!B28,Tabla3[[#All],[DETALLES]],Tabla4[[#This Row],[ACTIVIDADES]]) -> 0 | I34: =SUMIFS(Tabla3[[#All],[EGRESOS]],Tabla3[[#All],[PERIODO]],Tabla4[[#Headers],[JULIO]],Tabla3[[#All],[ACTIVIDAD]],ACTIVIDADES!B16,Tabla3[[#All],[CONCEPTO]],ACTIVIDADES!B28,Tabla3[[#All],[DETALLES]],Tabla4[[#This Row],[ACTIVIDADES]]) -> 0 | J34: =SUMIFS(Tabla3[[#All],[EGRESOS]],Tabla3[[#All],[PERIODO]],Tabla4[[#Headers],[AGOSTO]],Tabla3[[#All],[ACTIVIDAD]],ACTIVIDADES!B16,Tabla3[[#All],[CONCEPTO]],ACTIVIDADES!B28,Tabla3[[#All],[DETALLES]],Tabla4[[#This Row],[ACTIVIDADES]]) -> 0 | K34: =SUMIFS(Tabla3[[#All],[EGRESOS]],Tabla3[[#All],[PERIODO]],Tabla4[[#Headers],[SEPTIEMBRE]],Tabla3[[#All],[ACTIVIDAD]],ACTIVIDADES!B16,Tabla3[[#All],[CONCEPTO]],ACTIVIDADES!B28,Tabla3[[#All],[DETALLES]],B34) -> 0 | L34: =SUMIFS(Tabla3[[#All],[EGRESOS]],Tabla3[[#All],[PERIODO]],Tabla4[[#Headers],[OCTUBRE]],Tabla3[[#All],[ACTIVIDAD]],$B$16,Tabla3[[#All],[CONCEPTO]],$B$28,Tabla3[[#All],[DETALLES]],B34) -> 0 | M34: =SUMIFS(Tabla3[[#All],[EGRESOS]],Tabla3[[#All],[PERIODO]],Tabla4[[#Headers],[NOVIEMBRE]],Tabla3[[#All],[ACTIVIDAD]],$B$16,Tabla3[[#All],[CONCEPTO]],$B$28,Tabla3[[#All],[DETALLES]],B34) -> 0 | O34: =SUM(Tabla4[[#This Row],[ENERO]:[DICIEMBRE]]) -> 0 | P34: =Tabla4[[#This Row],[USD]]*1140 -> 38818659 | Q34: =Tabla4[[#This Row],[TOTAL]]/Tabla4[[#This Row],[ESTIMADO]] -> 0 | R34: 34051.456 | S34: =Tabla4[[#This Row],[USD]]/140 -> 243.22468
B35: COSECHA MAIZ | C35: =SUMIFS(Tabla3[[#All],[EGRESOS]],Tabla3[[#All],[PERIODO]],Tabla4[[#Headers],[ENERO]],Tabla3[[#All],[ACTIVIDAD]],ACTIVIDADES!$B$16,Tabla3[[#All],[CONCEPTO]],ACTIVIDADES!$B$28,Tabla3[[#All],[DETALLES]],Tabla4[[#This Row],[ACTIVIDADES]]) -> 0 | D35: =SUMIFS(Tabla3[EGRESOS],Tabla3[ACTIVIDAD],ACTIVIDADES!$B$16,Tabla3[PERIODO],Tabla4[[#Headers],[FEBRERO]],Tabla3[CONCEPTO],ACTIVIDADES!B28,Tabla3[DETALLES],Tabla4[[#This Row],[ACTIVIDADES]]) -> 0 | E35: =SUMIFS(Tabla3[[#All],[EGRESOS]],Tabla3[[#All],[PERIODO]],Tabla4[[#Headers],[MARZO]],Tabla3[[#All],[ACTIVIDAD]],ACTIVIDADES!$B$16,Tabla3[[#All],[CONCEPTO]],ACTIVIDADES!$B$28,Tabla3[[#All],[DETALLES]],Tabla4[[#This Row],[ACTIVIDADES]]) -> 0 | F35: =SUMIFS(Tabla3[[#All],[EGRESOS]],Tabla3[[#All],[PERIODO]],Tabla4[[#Headers],[ABRIL]],Tabla3[[#All],[ACTIVIDAD]],ACTIVIDADES!B16,Tabla3[[#All],[CONCEPTO]],ACTIVIDADES!B28,Tabla3[[#All],[DETALLES]],Tabla4[[#This Row],[ACTIVIDADES]]) -> 0 | G35: =SUMIFS(Tabla3[[#All],[EGRESOS]],Tabla3[[#All],[PERIODO]],Tabla4[[#Headers],[MAYO]],Tabla3[[#All],[ACTIVIDAD]],ACTIVIDADES!$B$16,Tabla3[[#All],[CONCEPTO]],ACTIVIDADES!$B$28,Tabla3[[#All],[DETALLES]],Tabla4[[#This Row],[ACTIVIDADES]]) -> 0 | H35: =SUMIFS(Tabla3[[#All],[EGRESOS]],Tabla3[[#All],[PERIODO]],Tabla4[[#Headers],[JUNIO]],Tabla3[[#All],[ACTIVIDAD]],ACTIVIDADES!B16,Tabla3[[#All],[CONCEPTO]],ACTIVIDADES!B28,Tabla3[[#All],[DETALLES]],Tabla4[[#This Row],[ACTIVIDADES]]) -> 0 | I35: =SUMIFS(Tabla3[[#All],[EGRESOS]],Tabla3[[#All],[PERIODO]],Tabla4[[#Headers],[JULIO]],Tabla3[[#All],[ACTIVIDAD]],ACTIVIDADES!B16,Tabla3[[#All],[CONCEPTO]],ACTIVIDADES!B28,Tabla3[[#All],[DETALLES]],Tabla4[[#This Row],[ACTIVIDADES]]) -> 0 | J35: =SUMIFS(Tabla3[[#All],[EGRESOS]],Tabla3[[#All],[PERIODO]],Tabla4[[#Headers],[AGOSTO]],Tabla3[[#All],[ACTIVIDAD]],ACTIVIDADES!B16,Tabla3[[#All],[CONCEPTO]],ACTIVIDADES!B28,Tabla3[[#All],[DETALLES]],Tabla4[[#This Row],[ACTIVIDADES]]) -> 0 | K35: =SUMIFS(Tabla3[[#All],[EGRESOS]],Tabla3[[#All],[PERIODO]],Tabla4[[#Headers],[SEPTIEMBRE]],Tabla3[[#All],[ACTIVIDAD]],ACTIVIDADES!B16,Tabla3[[#All],[CONCEPTO]],ACTIVIDADES!B28,Tabla3[[#All],[DETALLES]],B35) -> 0 | L35: =SUMIFS(Tabla3[[#All],[EGRESOS]],Tabla3[[#All],[PERIODO]],Tabla4[[#Headers],[OCTUBRE]],Tabla3[[#All],[ACTIVIDAD]],$B$16,Tabla3[[#All],[CONCEPTO]],$B$28,Tabla3[[#All],[DETALLES]],B35) -> 0 | M35: =SUMIFS(Tabla3[[#All],[EGRESOS]],Tabla3[[#All],[PERIODO]],Tabla4[[#Headers],[NOVIEMBRE]],Tabla3[[#All],[ACTIVIDAD]],$B$16,Tabla3[[#All],[CONCEPTO]],$B$28,Tabla3[[#All],[DETALLES]],B35) -> 0 | O35: =SUM(Tabla4[[#This Row],[ENERO]:[DICIEMBRE]]) -> 0 | P35: =Tabla4[[#This Row],[USD]]*1140 -> 13740125 | Q35: =Tabla4[[#This Row],[TOTAL]]/Tabla4[[#This Row],[ESTIMADO]] -> 0 | R35: 12052.741 | S35: =Tabla4[[#This Row],[USD]]/140 -> 86.09101
B36: PICADO | C36: =SUMIFS(Tabla3[[#All],[EGRESOS]],Tabla3[[#All],[PERIODO]],Tabla4[[#Headers],[ENERO]],Tabla3[[#All],[ACTIVIDAD]],ACTIVIDADES!$B$15,Tabla3[[#All],[CONCEPTO]],ACTIVIDADES!$B$28,Tabla3[[#All],[DETALLES]],Tabla4[[#This Row],[ACTIVIDADES]]) -> 0 | D36: =SUMIFS(Tabla3[[#All],[INGRESOS]],Tabla3[[#All],[FECHA]],Tabla4[[#Headers],[FEBRERO]],Tabla3[[#All],[RUBRO]],ACTIVIDADES!$B$15,Tabla3[[#All],[DETALLES]],ACTIVIDADES!$B$28,Tabla3[[#All],[PROVEEDOR CLIENTE]],Tabla4[[#This Row],[ACTIVIDADES]]) -> 0 | E36: =SUMIFS(Tabla3[[#All],[EGRESOS]],Tabla3[[#All],[PERIODO]],Tabla4[[#Headers],[MARZO]],Tabla3[[#All],[ACTIVIDAD]],ACTIVIDADES!B16,Tabla3[[#All],[CONCEPTO]],ACTIVIDADES!B28,Tabla3[[#All],[DETALLES]],Tabla4[[#This Row],[ACTIVIDADES]]) -> 0 | F36: =SUMIFS(Tabla3[[#All],[EGRESOS]],Tabla3[[#All],[PERIODO]],Tabla4[[#Headers],[ABRIL]],Tabla3[[#All],[ACTIVIDAD]],ACTIVIDADES!B16,Tabla3[[#All],[CONCEPTO]],ACTIVIDADES!B28,Tabla3[[#All],[DETALLES]],Tabla4[[#This Row],[ACTIVIDADES]]) -> 0 | G36: =SUMIFS(Tabla3[[#All],[EGRESOS]],Tabla3[[#All],[PERIODO]],Tabla4[[#Headers],[MAYO]],Tabla3[[#All],[ACTIVIDAD]],ACTIVIDADES!B16,Tabla3[[#All],[CONCEPTO]],ACTIVIDADES!B28,Tabla3[[#All],[DETALLES]],Tabla4[[#This Row],[ACTIVIDADES]]) -> 0 | H36: =SUMIFS(Tabla3[[#All],[EGRESOS]],Tabla3[[#All],[PERIODO]],Tabla4[[#Headers],[JUNIO]],Tabla3[[#All],[ACTIVIDAD]],ACTIVIDADES!B16,Tabla3[[#All],[CONCEPTO]],ACTIVIDADES!B28,Tabla3[[#All],[DETALLES]],Tabla4[[#This Row],[ACTIVIDADES]]) -> 0 | I36: =SUMIFS(Tabla3[[#All],[EGRESOS]],Tabla3[[#All],[PERIODO]],Tabla4[[#Headers],[JULIO]],Tabla3[[#All],[ACTIVIDAD]],ACTIVIDADES!B16,Tabla3[[#All],[CONCEPTO]],ACTIVIDADES!B28,Tabla3[[#All],[DETALLES]],Tabla4[[#This Row],[ACTIVIDADES]]) -> 0 | J36: =SUMIFS(Tabla3[[#All],[EGRESOS]],Tabla3[[#All],[PERIODO]],Tabla4[[#Headers],[AGOSTO]],Tabla3[[#All],[ACTIVIDAD]],ACTIVIDADES!B16,Tabla3[[#All],[CONCEPTO]],ACTIVIDADES!B28,Tabla3[[#All],[DETALLES]],Tabla4[[#This Row],[ACTIVIDADES]]) -> 0 | K36: =SUMIFS(Tabla3[[#All],[EGRESOS]],Tabla3[[#All],[PERIODO]],Tabla4[[#Headers],[SEPTIEMBRE]],Tabla3[[#All],[ACTIVIDAD]],ACTIVIDADES!B16,Tabla3[[#All],[CONCEPTO]],ACTIVIDADES!B28,Tabla3[[#All],[DETALLES]],B36) -> 0 | L36: =SUMIFS(Tabla3[[#All],[EGRESOS]],Tabla3[[#All],[PERIODO]],Tabla4[[#Headers],[OCTUBRE]],Tabla3[[#All],[ACTIVIDAD]],$B$16,Tabla3[[#All],[CONCEPTO]],$B$28,Tabla3[[#All],[DETALLES]],B36) -> 0 | M36: =SUMIFS(Tabla3[[#All],[EGRESOS]],Tabla3[[#All],[PERIODO]],Tabla4[[#Headers],[NOVIEMBRE]],Tabla3[[#All],[ACTIVIDAD]],$B$16,Tabla3[[#All],[CONCEPTO]],$B$28,Tabla3[[#All],[DETALLES]],B36) -> 0 | O36: =SUM(Tabla4[[#This Row],[ENERO]:[DICIEMBRE]]) -> 0 | P36: =Tabla4[[#This Row],[USD]]*1400 -> 29400000 | Q36: =Tabla4[[#This Row],[TOTAL]]/Tabla4[[#This Row],[ESTIMADO]] -> 0 | R36: 21000 | S36: =Tabla4[[#This Row],[USD]]/140 -> 150
B37: ACARREO | K37: =SUMIFS(Tabla3[[#All],[EGRESOS]],Tabla3[[#All],[PERIODO]],Tabla4[[#Headers],[SEPTIEMBRE]],Tabla3[[#All],[ACTIVIDAD]],ACTIVIDADES!B16,Tabla3[[#All],[CONCEPTO]],ACTIVIDADES!B28,Tabla3[[#All],[DETALLES]],B37) -> 0 | L37: =SUMIFS(Tabla3[[#All],[EGRESOS]],Tabla3[[#All],[PERIODO]],Tabla4[[#Headers],[OCTUBRE]],Tabla3[[#All],[ACTIVIDAD]],$B$16,Tabla3[[#All],[CONCEPTO]],$B$28,Tabla3[[#All],[DETALLES]],B37) -> 0 | M37: =SUMIFS(Tabla3[[#All],[EGRESOS]],Tabla3[[#All],[PERIODO]],Tabla4[[#Headers],[NOVIEMBRE]],Tabla3[[#All],[ACTIVIDAD]],$B$16,Tabla3[[#All],[CONCEPTO]],$B$28,Tabla3[[#All],[DETALLES]],B37) -> 0 | O37: =SUM(Tabla4[[#This Row],[ENERO]:[DICIEMBRE]]) -> 0 | P37: =Tabla4[[#This Row],[USD]]*1400 -> 280000 | Q37: =Tabla4[[#This Row],[TOTAL]]/Tabla4[[#This Row],[ESTIMADO]] -> 0 | R37: 200 | S37: =Tabla4[[#This Row],[USD]]/140 -> 1.4285714
B38: GANADERIA | C38: =SUBTOTAL(109,C39:C43) -> 1187657.1 | D38: =SUBTOTAL(109,D39:D43) -> 1370600 | E38: =SUBTOTAL(109,E39:E43) -> 0 | F38: =SUBTOTAL(109,F39:F43) -> 0 | G38: =SUBTOTAL(109,G39:G43) -> 0 | H38: =SUBTOTAL(109,H39:H43) -> 0 | I38: =SUBTOTAL(109,I39:I43) -> 0 | J38: =SUBTOTAL(109,J39:J43) -> 0 | ... P38: =SUBTOTAL(109,P39:P43) -> 448600000 | Q38: =Tabla4[[#This Row],[TOTAL]]/Tabla4[[#This Row],[ESTIMADO]] -> 0.0057027577 | R38: =SUBTOTAL(109,R39:R43) -> 383418.8
B39: VETERINARIA | C39: =SUMIFS(Tabla3[[#All],[EGRESOS]],Tabla3[[#All],[PERIODO]],Tabla4[[#Headers],[ENERO]],Tabla3[[#All],[ACTIVIDAD]],ACTIVIDADES!B38,Tabla3[[#All],[CONCEPTO]],Tabla4[[#This Row],[ACTIVIDADES]]) -> 570657.08 | D39: =SUMIFS(Tabla3[EGRESOS],Tabla3[ACTIVIDAD],ACTIVIDADES!$B$38,Tabla3[CONCEPTO],ACTIVIDADES!B39,Tabla3[PERIODO],Tabla4[[#Headers],[FEBRERO]]) -> 662600.02 | E39: =SUMIFS(Tabla3[[#All],[EGRESOS]],Tabla3[[#All],[PERIODO]],Tabla4[[#Headers],[MARZO]],Tabla3[[#All],[ACTIVIDAD]],ACTIVIDADES!B38,Tabla3[[#All],[CONCEPTO]],Tabla4[[#This Row],[ACTIVIDADES]]) -> 0 | F39: =SUMIFS(Tabla3[[#All],[EGRESOS]],Tabla3[[#All],[PERIODO]],Tabla4[[#Headers],[ABRIL]],Tabla3[[#All],[ACTIVIDAD]],ACTIVIDADES!B38,Tabla3[[#All],[CONCEPTO]],Tabla4[[#This Row],[ACTIVIDADES]]) -> 0 | G39: =SUMIFS(Tabla3[[#All],[EGRESOS]],Tabla3[[#All],[PERIODO]],Tabla4[[#Headers],[MAYO]],Tabla3[[#All],[ACTIVIDAD]],ACTIVIDADES!B38,Tabla3[[#All],[CONCEPTO]],Tabla4[[#This Row],[ACTIVIDADES]]) -> 0 | H39: =SUMIFS(Tabla3[[#All],[EGRESOS]],Tabla3[[#All],[PERIODO]],Tabla4[[#Headers],[JUNIO]],Tabla3[[#All],[ACTIVIDAD]],ACTIVIDADES!B38,Tabla3[[#All],[CONCEPTO]],Tabla4[[#This Row],[ACTIVIDADES]]) -> 0 | I39: =SUMIFS(Tabla3[[#All],[EGRESOS]],Tabla3[[#All],[PERIODO]],Tabla4[[#Headers],[JULIO]],Tabla3[[#All],[ACTIVIDAD]],ACTIVIDADES!B38,Tabla3[[#All],[CONCEPTO]],Tabla4[[#This Row],[ACTIVIDADES]]) -> 0 | J39: =SUMIFS(Tabla3[[#All],[EGRESOS]],Tabla3[[#All],[PERIODO]],Tabla4[[#Headers],[AGOSTO]],Tabla3[[#All],[ACTIVIDAD]],ACTIVIDADES!B38,Tabla3[[#All],[CONCEPTO]],Tabla4[[#This Row],[ACTIVIDADES]]) -> 0 | K39: =SUMIFS(Tabla3[[#All],[EGRESOS]],Tabla3[[#All],[PERIODO]],Tabla4[[#Headers],[SEPTIEMBRE]],Tabla3[[#All],[ACTIVIDAD]],ACTIVIDADES!B38,Tabla3[[#All],[CONCEPTO]],Tabla4[[#This Row],[ACTIVIDADES]]) -> 0 | L39: =SUMIFS(Tabla3[[#All],[EGRESOS]],Tabla3[[#All],[PERIODO]],Tabla4[[#Headers],[OCTUBRE]],Tabla3[[#All],[ACTIVIDAD]],$B$38,Tabla3[[#All],[CONCEPTO]],Tabla4[[#This Row],[ACTIVIDADES]]) -> 0 | M39: =SUMIFS(Tabla3[[#All],[EGRESOS]],Tabla3[[#All],[PERIODO]],Tabla4[[#Headers],[NOVIEMBRE]],Tabla3[[#All],[ACTIVIDAD]],$B$38,Tabla3[[#All],[CONCEPTO]],Tabla4[[#This Row],[ACTIVIDADES]]) -> 0 | O39: =SUM(Tabla4[[#This Row],[ENERO]:[DICIEMBRE]]) -> 1233257.1 | P39: 8000000 | Q39: =Tabla4[[#This Row],[TOTAL]]/Tabla4[[#This Row],[ESTIMADO]] -> 0.15415714 | R39: =Tabla4[[#This Row],[ESTIMADO]]/1170 -> 6837.6068
B40: LABORATORIO | C40: =SUMIFS(Tabla3[[#All],[EGRESOS]],Tabla3[[#All],[PERIODO]],Tabla4[[#Headers],[ENERO]],Tabla3[[#All],[ACTIVIDAD]],ACTIVIDADES!B38,Tabla3[[#All],[CONCEPTO]],Tabla4[[#This Row],[ACTIVIDADES]]) -> 0 | D40: =SUMIFS(Tabla3[EGRESOS],Tabla3[ACTIVIDAD],ACTIVIDADES!$B$38,Tabla3[CONCEPTO],ACTIVIDADES!B40,Tabla3[PERIODO],Tabla4[[#Headers],[FEBRERO]]) -> 48000 | E40: =SUMIFS(Tabla3[[#All],[EGRESOS]],Tabla3[[#All],[PERIODO]],Tabla4[[#Headers],[MARZO]],Tabla3[[#All],[ACTIVIDAD]],ACTIVIDADES!B38,Tabla3[[#All],[CONCEPTO]],Tabla4[[#This Row],[ACTIVIDADES]]) -> 0 | F40: =SUMIFS(Tabla3[[#All],[EGRESOS]],Tabla3[[#All],[PERIODO]],Tabla4[[#Headers],[ABRIL]],Tabla3[[#All],[ACTIVIDAD]],ACTIVIDADES!B38,Tabla3[[#All],[CONCEPTO]],Tabla4[[#This Row],[ACTIVIDADES]]) -> 0 | G40: =SUMIFS(Tabla3[[#All],[EGRESOS]],Tabla3[[#All],[PERIODO]],Tabla4[[#Headers],[MAYO]],Tabla3[[#All],[ACTIVIDAD]],ACTIVIDADES!B38,Tabla3[[#All],[CONCEPTO]],Tabla4[[#This Row],[ACTIVIDADES]]) -> 0 | H40: =SUMIFS(Tabla3[[#All],[EGRESOS]],Tabla3[[#All],[PERIODO]],Tabla4[[#Headers],[JUNIO]],Tabla3[[#All],[ACTIVIDAD]],ACTIVIDADES!B38,Tabla3[[#All],[CONCEPTO]],Tabla4[[#This Row],[ACTIVIDADES]]) -> 0 | I40: =SUMIFS(Tabla3[[#All],[EGRESOS]],Tabla3[[#All],[PERIODO]],Tabla4[[#Headers],[JULIO]],Tabla3[[#All],[ACTIVIDAD]],ACTIVIDADES!B38,Tabla3[[#All],[CONCEPTO]],Tabla4[[#This Row],[ACTIVIDADES]]) -> 0 | J40: =SUMIFS(Tabla3[[#All],[EGRESOS]],Tabla3[[#All],[PERIODO]],Tabla4[[#Headers],[AGOSTO]],Tabla3[[#All],[ACTIVIDAD]],ACTIVIDADES!B38,Tabla3[[#All],[CONCEPTO]],Tabla4[[#This Row],[ACTIVIDADES]]) -> 0 | K40: =SUMIFS(Tabla3[[#All],[EGRESOS]],Tabla3[[#All],[PERIODO]],Tabla4[[#Headers],[SEPTIEMBRE]],Tabla3[[#All],[ACTIVIDAD]],ACTIVIDADES!B38,Tabla3[[#All],[CONCEPTO]],Tabla4[[#This Row],[ACTIVIDADES]]) -> 0 | L40: =SUMIFS(Tabla3[[#All],[EGRESOS]],Tabla3[[#All],[PERIODO]],Tabla4[[#Headers],[OCTUBRE]],Tabla3[[#All],[ACTIVIDAD]],$B$38,Tabla3[[#All],[CONCEPTO]],Tabla4[[#This Row],[ACTIVIDADES]]) -> 0 | M40: =SUMIFS(Tabla3[[#All],[EGRESOS]],Tabla3[[#All],[PERIODO]],Tabla4[[#Headers],[NOVIEMBRE]],Tabla3[[#All],[ACTIVIDAD]],$B$38,Tabla3[[#All],[CONCEPTO]],Tabla4[[#This Row],[ACTIVIDADES]]) -> 0 | O40: =SUM(Tabla4[[#This Row],[ENERO]:[DICIEMBRE]]) -> 48000 | P40: 100000 | Q40: =Tabla4[[#This Row],[TOTAL]]/Tabla4[[#This Row],[ESTIMADO]] -> 0.48 | R40: =Tabla4[[#This Row],[ESTIMADO]]/1170 -> 85.470085
B41: ASESORAMIENTO | C41: =SUMIFS(Tabla3[[#All],[EGRESOS]],Tabla3[[#All],[PERIODO]],Tabla4[[#Headers],[ENERO]],Tabla3[[#All],[ACTIVIDAD]],ACTIVIDADES!B38,Tabla3[[#All],[CONCEPTO]],Tabla4[[#This Row],[ACTIVIDADES]]) -> 617000 | D41: =SUMIFS(Tabla3[[#All],[EGRESOS]],Tabla3[[#All],[PERIODO]],Tabla4[[#Headers],[FEBRERO]],Tabla3[[#All],[ACTIVIDAD]],ACTIVIDADES!B38,Tabla3[[#All],[CONCEPTO]],Tabla4[[#This Row],[ACTIVIDADES]]) -> 660000 | E41: =SUMIFS(Tabla3[[#All],[EGRESOS]],Tabla3[[#All],[PERIODO]],Tabla4[[#Headers],[MARZO]],Tabla3[[#All],[ACTIVIDAD]],ACTIVIDADES!B38,Tabla3[[#All],[CONCEPTO]],Tabla4[[#This Row],[ACTIVIDADES]]) -> 0 | F41: =SUMIFS(Tabla3[[#All],[EGRESOS]],Tabla3[[#All],[PERIODO]],Tabla4[[#Headers],[ABRIL]],Tabla3[[#All],[ACTIVIDAD]],ACTIVIDADES!B38,Tabla3[[#All],[CONCEPTO]],Tabla4[[#This Row],[ACTIVIDADES]]) -> 0 | G41: =SUMIFS(Tabla3[[#All],[EGRESOS]],Tabla3[[#All],[PERIODO]],Tabla4[[#Headers],[MAYO]],Tabla3[[#All],[ACTIVIDAD]],ACTIVIDADES!B38,Tabla3[[#All],[CONCEPTO]],Tabla4[[#This Row],[ACTIVIDADES]]) -> 0 | H41: =SUMIFS(Tabla3[[#All],[EGRESOS]],Tabla3[[#All],[PERIODO]],Tabla4[[#Headers],[JUNIO]],Tabla3[[#All],[ACTIVIDAD]],ACTIVIDADES!B38,Tabla3[[#All],[CONCEPTO]],Tabla4[[#This Row],[ACTIVIDADES]]) -> 0 | I41: =SUMIFS(Tabla3[[#All],[EGRESOS]],Tabla3[[#All],[PERIODO]],Tabla4[[#Headers],[JULIO]],Tabla3[[#All],[ACTIVIDAD]],ACTIVIDADES!B38,Tabla3[[#All],[CONCEPTO]],Tabla4[[#This Row],[ACTIVIDADES]]) -> 0 | J41: =SUMIFS(Tabla3[[#All],[EGRESOS]],Tabla3[[#All],[PERIODO]],Tabla4[[#Headers],[AGOSTO]],Tabla3[[#All],[ACTIVIDAD]],ACTIVIDADES!B38,Tabla3[[#All],[CONCEPTO]],Tabla4[[#This Row],[ACTIVIDADES]]) -> 0 | K41: =SUMIFS(Tabla3[[#All],[EGRESOS]],Tabla3[[#All],[PERIODO]],Tabla4[[#Headers],[SEPTIEMBRE]],Tabla3[[#All],[ACTIVIDAD]],ACTIVIDADES!B38,Tabla3[[#All],[CONCEPTO]],Tabla4[[#This Row],[ACTIVIDADES]]) -> 0 | L41: =SUMIFS(Tabla3[[#All],[EGRESOS]],Tabla3[[#All],[PERIODO]],Tabla4[[#Headers],[OCTUBRE]],Tabla3[[#All],[ACTIVIDAD]],$B$38,Tabla3[[#All],[CONCEPTO]],Tabla4[[#This Row],[ACTIVIDADES]]) -> 0 | M41: =SUMIFS(Tabla3[[#All],[EGRESOS]],Tabla3[[#All],[PERIODO]],Tabla4[[#Headers],[NOVIEMBRE]],Tabla3[[#All],[ACTIVIDAD]],$B$38,Tabla3[[#All],[CONCEPTO]],Tabla4[[#This Row],[ACTIVIDADES]]) -> 0 | O41: =SUM(Tabla4[[#This Row],[ENERO]:[DICIEMBRE]]) -> 1277000 | P41: 5500000 | Q41: =Tabla4[[#This Row],[TOTAL]]/Tabla4[[#This Row],[ESTIMADO]] -> 0.23218182 | R41: =Tabla4[[#This Row],[ESTIMADO]]/1170 -> 4700.8547
B42: COMBUSTIBLES | C42: =SUMIFS(Tabla3[[#All],[EGRESOS]],Tabla3[[#All],[PERIODO]],Tabla4[[#Headers],[ENERO]],Tabla3[[#All],[ACTIVIDAD]],ACTIVIDADES!B38,Tabla3[[#All],[CONCEPTO]],Tabla4[[#This Row],[ACTIVIDADES]]) -> 0 | D42: =SUMIFS(Tabla3[[#All],[EGRESOS]],Tabla3[[#All],[PERIODO]],Tabla4[[#Headers],[FEBRERO]],Tabla3[[#All],[ACTIVIDAD]],ACTIVIDADES!B38,Tabla3[[#All],[CONCEPTO]],Tabla4[[#This Row],[ACTIVIDADES]]) -> 0 | E42: =SUMIFS(Tabla3[[#All],[EGRESOS]],Tabla3[[#All],[PERIODO]],Tabla4[[#Headers],[MARZO]],Tabla3[[#All],[ACTIVIDAD]],ACTIVIDADES!B38,Tabla3[[#All],[CONCEPTO]],Tabla4[[#This Row],[ACTIVIDADES]]) -> 0 | F42: =SUMIFS(Tabla3[[#All],[EGRESOS]],Tabla3[[#All],[PERIODO]],Tabla4[[#Headers],[ABRIL]],Tabla3[[#All],[ACTIVIDAD]],ACTIVIDADES!B38,Tabla3[[#All],[CONCEPTO]],Tabla4[[#This Row],[ACTIVIDADES]]) -> 0 | G42: =SUMIFS(Tabla3[[#All],[EGRESOS]],Tabla3[[#All],[PERIODO]],Tabla4[[#Headers],[MAYO]],Tabla3[[#All],[ACTIVIDAD]],ACTIVIDADES!B38,Tabla3[[#All],[CONCEPTO]],Tabla4[[#This Row],[ACTIVIDADES]]) -> 0 | H42: =SUMIFS(Tabla3[[#All],[EGRESOS]],Tabla3[[#All],[PERIODO]],Tabla4[[#Headers],[JUNIO]],Tabla3[[#All],[ACTIVIDAD]],ACTIVIDADES!B38,Tabla3[[#All],[CONCEPTO]],Tabla4[[#This Row],[ACTIVIDADES]]) -> 0 | I42: =SUMIFS(Tabla3[EGRESOS],Tabla3[PERIODO],Tabla4[[#Headers],[JULIO]],Tabla3[ACTIVIDAD],ACTIVIDADES!B38,Tabla3[RUBRO],Tabla4[[#This Row],[ACTIVIDADES]]) -> 0 | J42: =SUMIFS(Tabla3[[#All],[EGRESOS]],Tabla3[[#All],[PERIODO]],Tabla4[[#Headers],[AGOSTO]],Tabla3[[#All],[ACTIVIDAD]],ACTIVIDADES!B38,Tabla3[[#All],[CONCEPTO]],Tabla4[[#This Row],[ACTIVIDADES]]) -> 0 | K42: =SUMIFS(Tabla3[[#All],[EGRESOS]],Tabla3[[#All],[PERIODO]],Tabla4[[#Headers],[SEPTIEMBRE]],Tabla3[[#All],[ACTIVIDAD]],ACTIVIDADES!B38,Tabla3[[#All],[CONCEPTO]],Tabla4[[#This Row],[ACTIVIDADES]]) -> 0 | L42: =SUMIFS(Tabla3[[#All],[EGRESOS]],Tabla3[[#All],[PERIODO]],Tabla4[[#Headers],[OCTUBRE]],Tabla3[[#All],[ACTIVIDAD]],$B$38,Tabla3[[#All],[CONCEPTO]],Tabla4[[#This Row],[ACTIVIDADES]]) -> 0 | M42: =SUMIFS(Tabla3[[#All],[EGRESOS]],Tabla3[[#All],[PERIODO]],Tabla4[[#Headers],[NOVIEMBRE]],Tabla3[[#All],[ACTIVIDAD]],$B$38,Tabla3[[#All],[CONCEPTO]],Tabla4[[#This Row],[ACTIVIDADES]]) -> 0 | O42: =SUM(Tabla4[[#This Row],[ENERO]:[DICIEMBRE]]) -> 0 | P42: 35000000 | Q42: =Tabla4[[#This Row],[TOTAL]]/Tabla4[[#This Row],[ESTIMADO]] -> 0 | R42: =Tabla4[[#This Row],[ESTIMADO]]/1170 -> 29914.53
B43: COMPRA TERN | C43: =SUMIFS(Tabla3[[#All],[EGRESOS]],Tabla3[[#All],[PERIODO]],Tabla4[[#Headers],[ENERO]],Tabla3[[#All],[ACTIVIDAD]],ACTIVIDADES!B38,Tabla3[[#All],[CONCEPTO]],Tabla4[[#This Row],[ACTIVIDADES]]) -> 0 | D43: =SUMIFS(Tabla3[[#All],[EGRESOS]],Tabla3[[#All],[PERIODO]],Tabla4[[#Headers],[FEBRERO]],Tabla3[[#All],[ACTIVIDAD]],ACTIVIDADES!B38,Tabla3[[#All],[CONCEPTO]],Tabla4[[#This Row],[ACTIVIDADES]]) -> 0 | E43: =SUMIFS(Tabla3[[#All],[EGRESOS]],Tabla3[[#All],[PERIODO]],Tabla4[[#Headers],[MARZO]],Tabla3[[#All],[ACTIVIDAD]],ACTIVIDADES!B38,Tabla3[[#All],[CONCEPTO]],Tabla4[[#This Row],[ACTIVIDADES]]) -> 0 | F43: =SUMIFS(Tabla3[[#All],[EGRESOS]],Tabla3[[#All],[PERIODO]],Tabla4[[#Headers],[ABRIL]],Tabla3[[#All],[ACTIVIDAD]],ACTIVIDADES!B38,Tabla3[[#All],[CONCEPTO]],Tabla4[[#This Row],[ACTIVIDADES]]) -> 0 | G43: =SUMIFS(Tabla3[EGRESOS],Tabla3[PERIODO],Tabla4[[#Headers],[MAYO]],Tabla3[ACTIVIDAD],ACTIVIDADES!B38,Tabla3[RUBRO],Tabla4[[#This Row],[ACTIVIDADES]]) -> 0 | H43: =SUMIFS(Tabla3[EGRESOS],Tabla3[PERIODO],Tabla4[[#Headers],[JUNIO]],Tabla3[ACTIVIDAD],ACTIVIDADES!B38,Tabla3[RUBRO],Tabla4[[#This Row],[ACTIVIDADES]]) -> 0 | I43: =SUMIFS(Tabla3[EGRESOS],Tabla3[PERIODO],Tabla4[[#Headers],[JULIO]],Tabla3[ACTIVIDAD],ACTIVIDADES!B38,Tabla3[RUBRO],Tabla4[[#This Row],[ACTIVIDADES]]) -> 0 | J43: =SUMIFS(Tabla3[EGRESOS],Tabla3[PERIODO],Tabla4[[#Headers],[AGOSTO]],Tabla3[ACTIVIDAD],ACTIVIDADES!B38,Tabla3[RUBRO],Tabla4[[#This Row],[ACTIVIDADES]]) -> 0 | K43: =SUMIFS(Tabla3[[#All],[EGRESOS]],Tabla3[[#All],[PERIODO]],Tabla4[[#Headers],[SEPTIEMBRE]],Tabla3[[#All],[ACTIVIDAD]],ACTIVIDADES!B38,Tabla3[[#All],[CONCEPTO]],Tabla4[[#This Row],[ACTIVIDADES]]) -> 0 | L43: =SUMIFS(Tabla3[[#All],[EGRESOS]],Tabla3[[#All],[PERIODO]],Tabla4[[#Headers],[OCTUBRE]],Tabla3[[#All],[ACTIVIDAD]],$B$38,Tabla3[[#All],[CONCEPTO]],Tabla4[[#This Row],[ACTIVIDADES]]) -> 0 | M43: =SUMIFS(Tabla3[[#All],[EGRESOS]],Tabla3[[#All],[PERIODO]],Tabla4[[#Headers],[NOVIEMBRE]],Tabla3[[#All],[ACTIVIDAD]],$B$38,Tabla3[[#All],[CONCEPTO]],Tabla4[[#This Row],[ACTIVIDADES]]) -> 0 | O43: =SUM(Tabla4[[#This Row],[ENERO]:[DICIEMBRE]]) -> 0 | P43: 400000000 | Q43: =Tabla4[[#This Row],[TOTAL]]/Tabla4[[#This Row],[ESTIMADO]] -> 0 | R43: =Tabla4[[#This Row],[ESTIMADO]]/1170 -> 341880.34
B44: TOTAL | C44: =C16+C38 -> 4317361.8 | D44: =D16+D38 -> 1370600 | E44: =E16+E38 -> 0 | F44: =F16+F38 -> 0 | G44: =G16+G38 -> #REF! | H44: =H16+H38 -> #REF! | I44: =I16+I38 -> 0 | J44: =J16+J38 -> 0 | ... N44: =N16+N38 -> 0
B48: ACTIVIDADES | C48: ENERO | D48: FEBRERO | E48: MARZO | F48: ABRIL | G48: MAYO | H48: JUNIO | I48: JULIO | J48: AGOSTO | K48: SEPTIEMBRE | L48: OCTUBRE | M48: NOVIEMBRE | N48: DICIEMBRE | O48: TOTAL
B49: SOJA
B50: ASESORAMIENTO | C50: =C17/$P$17 -> 0 | D50: =D17/$P$17 -> 0 | E50: =E17/$P$17 -> 0 | F50: =F17/$P$17 -> 0 | G50: =G17/$P$17 -> 0 | H50: =H17/$P$17 -> 0 | I50: =I17/$P$17 -> 0 | J50: =J17/$P$17 -> 0 | ... N50: =N17/$P$17 -> 0 | O50: =SUM(C50:N50) -> 0
B51: SIEMBRA | C51: =C19/$P$19 -> 0 | D51: =D19/$P$19 -> 0 | E51: =E19/$P$19 -> 0 | F51: =F19/$P$19 -> 0 | G51: =G19/$P$19 -> 0 | H51: =H19/$P$19 -> 0 | I51: =I19/$P$19 -> 0 | J51: =J19/$P$19 -> 0 | ... N51: =N19/$P$19 -> 0 | O51: =SUM(C51:N51) -> 0
B52: SEMILLAS | C52: =C20/$P$20 -> 0 | D52: =D20/$P$20 -> 0 | E52: =E20/$P$20 -> 0 | F52: =F20/$P$20 -> 0 | G52: =G20/$P$20 -> 0 | H52: =H20/$P$20 -> 0 | I52: =I20/$P$20 -> 0 | J52: =J20/$P$20 -> 0 | ... N52: =N20/$P$20 -> 0 | O52: =SUM(C52:N52) -> 0
B53: APLICACIONES | C53: =C21/$P$21 -> 0.17472004 | D53: =D21/$P$21 -> 0 | E53: =E21/$P$21 -> 0 | F53: =F21/$P$21 -> 0 | G53: =G21/$P$21 -> 0 | H53: =H21/$P$21 -> 0 | I53: =I21/$P$21 -> 0 | J53: =J21/$P$21 -> 0 | ... N53: =N21/$P$21 -> 0 | O53: =SUM(C53:N53) -> 0.17472004
B54: INSUMOS 2025 | C54: =C22/$P$22 -> 0 | D54: =D22/$P$22 -> 0 | E54: =E22/$P$22 -> 0 | F54: =F22/$P$22 -> 0 | G54: =G22/$P$22 -> 0 | H54: =H22/$P$22 -> 0 | I54: =I22/$P$22 -> 0 | J54: =J22/$P$22 -> 0 | ... N54: =N22/$P$22 -> 0 | O54: =SUM(C54:N54) -> 0
B55: FLETES | C55: =C23/$P$23 -> 0 | D55: =D23/$P$23 -> 0 | E55: =E23/$P$23 -> 0 | F55: =F23/$P$23 -> 0 | G55: =G23/$P$23 -> 0 | H55: =H23/$P$23 -> 0 | I55: =I23/$P$23 -> 0 | J55: =J23/$P$23 -> 0 | ... N55: =N23/$P$23 -> 0 | O55: =SUM(C55:N55) -> 0
B56: DESYUYADOR | C56: =C24/$P$24 -> 0 | D56: =D24/$P$24 -> 0 | E56: =E24/$P$24 -> 0 | F56: =F24/$P$24 -> 0 | G56: =G24/$P$24 -> 0 | H56: =H24/$P$24 -> 0 | I56: =I24/$P$24 -> 0 | J56: =J24/$P$24 -> 0 | ... N56: =N24/$P$24 -> 0 | O56: =SUM(C56:N56) -> 0
B57: COSECHA 114 HAS | C57: =C25/$P$25 -> 0 | D57: =D25/$P$25 -> 0 | E57: =E25/$P$25 -> 0 | F57: =F25/$P$25 -> 0 | G57: =G25/$P$25 -> 0 | H57: =H25/$P$25 -> 0 | I57: =I25/$P$25 -> 0 | J57: =J25/$P$25 -> 0 | ... N57: =N25/$P$25 -> 0 | O57: =SUM(C57:N57) -> 0
B58: MAIZ
B59: SIEMBRA | C59: =C29/$P$29 -> 0 | D59: =D29/$P$29 -> 0 | E59: =E29/$P$29 -> 0 | F59: =F29/$P$29 -> 0 | G59: =G29/$P$29 -> 0 | H59: =H29/$P$29 -> 0 | I59: =I29/$P$29 -> 0 | J59: =J29/$P$29 -> 0 | ... N59: =N29/$P$29 -> 0 | O59: =SUM(C59:N59) -> 0
B60: SEMILLAS | C60: =C30/$P$30 -> 0 | D60: =D30/$P$30 -> 0 | E60: =E30/$P$30 -> 0 | F60: =F30/$P$30 -> 0 | G60: =G30/$P$30 -> 0 | H60: =H30/$P$30 -> 0 | I60: =I30/$P$30 -> 0 | J60: =J30/$P$30 -> 0 | ... N60: =N30/$P$30 -> 0 | O60: =SUM(C60:N60) -> 0
B61: APLICACIONES | C61: =C31/$P$31 -> 0 | D61: =D31/$P$31 -> 0 | E61: =E31/$P$31 -> 0 | F61: =F31/$P$31 -> 0 | G61: =G31/$P$31 -> 0 | H61: =H31/$P$31 -> 0 | I61: =I31/$P$31 -> 0 | J61: =J31/$P$31 -> 0 | ... N61: =N31/$P$31 -> 0 | O61: =SUM(C61:N61) -> 0
B62: FLETES FERTILIZANTE | C62: =C32/$P$32 -> 0 | D62: =D32/$P$32 -> 0 | E62: =E32/$P$32 -> 0 | F62: =F32/$P$32 -> 0 | G62: =G32/$P$32 -> 0 | H62: =H32/$P$32 -> 0 | I62: =I32/$P$32 -> 0 | J62: =J32/$P$32 -> 0 | ... N62: =N32/$P$32 -> 0 | O62: =SUM(C62:N62) -> 0
B63: INSUMOS 2025 | C63: =C33/$P$33 -> 0 | D63: =D33/$P$33 -> 0 | E63: =E33/$P$33 -> 0 | F63: =F33/$P$33 -> 0 | G63: =G33/$P$33 -> 0 | H63: =H33/$P$33 -> 0 | I63: =I33/$P$33 -> 0 | J63: =J33/$P$33 -> 0 | ... N63: =N33/$P$33 -> 0 | O63: =SUM(C63:N63) -> 0
B64: FLETES | C64: =C34/$P$34 -> 0 | D64: =D34/$P$34 -> 0 | E64: =E34/$P$34 -> 0 | F64: =F34/$P$34 -> 0 | G64: =G34/$P$34 -> 0 | H64: =H34/$P$34 -> 0 | I64: =I34/$P$34 -> 0 | J64: =J34/$P$34 -> 0 | ... N64: =N34/$P$34 -> 0 | O64: =SUM(C64:N64) -> 0
B65: COSECHA MAIZ | C65: =C35/$P$35 -> 0 | D65: =D35/$P$35 -> 0 | E65: =E35/$P$35 -> 0 | F65: =F35/$P$35 -> 0 | G65: =G35/$P$35 -> 0 | H65: =H35/$P$35 -> 0 | I65: =I35/$P$35 -> 0 | J65: =J35/$P$35 -> 0 | ... N65: =N35/$P$35 -> 0 | O65: =SUM(C65:N65) -> 0
B66: PICADO | C66: =C36/$P$36 -> 0 | D66: =D36/$P$36 -> 0 | E66: =E36/$P$36 -> 0 | F66: =F36/$P$36 -> 0 | G66: =G36/$P$36 -> 0 | H66: =H36/$P$36 -> 0 | I66: =I36/$P$36 -> 0 | J66: =J36/$P$36 -> 0 | ... N66: =N36/$P$36 -> 0 | O66: =SUM(C66:N66) -> 0
B67: ACARREO | C67: =C37/$P$37 -> 0 | D67: =D37/$P$37 -> 0 | E67: =E37/$P$37 -> 0 | F67: =F37/$P$37 -> 0 | G67: =G37/$P$37 -> 0 | H67: =H37/$P$37 -> 0 | I67: =I37/$P$37 -> 0 | J67: =J37/$P$37 -> 0 | ... N67: =N37/$P$37 -> 0 | O67: =SUM(C67:N67) -> 0
C100: CAMPAÑA 2025-2026
C101: GIRASOL
C102: AGRONASAJA | D102: 12 BOLSAS | E102: 230 | F102: =12*230+1.21 -> 2761.21 | G102: =F102*1500 -> 4141815 | H102: FALLA LA SIEMBRA
C103: MAIZ
C104: SUPRA | F104: 28300 | G104: =F104*1500 -> 42450000
C105: TODO CAMPO | F105: 70000 | G105: =F105*1500 -> 105000000

Sheet MOV
A1: 2026 | C1: SALDO INICIAL BANCOS: | D1: -36721484 | E1: saldos con descub | F1: 0 | G1: =G2+D1 -> -40845486
E2: =SUBTOTAL(9,Tabla3[EGRESOS]) -> 2.3365279e+08 | F2: =SUBTOTAL(9,Tabla3[INGRESOS]) -> 2.2952879e+08 | G2: =F2-E2 -> -4124001.6 | J2: =SUBTOTAL(9,Tabla3[EGRES USD]) -> 161139.85 | K2: =SUBTOTAL(9,Tabla3[INGRES USD]) -> 158295.71
A3: PERIODO | B3: FECHA | C3: DESCRIPCION | D3: N DE REFERENCIA | E3: EGRESOS | F3: INGRESOS | G3: SALDO | H3: SALDO BANCO | I3: TC | J3: EGRES USD | K3: INGRES USD | L3: MONEDA | M3: CUENTA | N3: BANCO | O3: ACTIVIDAD | P3: RUBRO | Q3: CONCEPTO | R3: DETALLES | S3: PROVEEDOR CLIENTE | T3: FACTURA | U3: RDS | V3: SOCIO | W3: CAMPAÑA
A4: ="ENERO" -> ENERO | B4: 46024 | C4: COMISION PAQUETES | E4: 50000 | F4: 0 | G4: =Tabla3[[#This Row],[EGRESOS]]-Tabla3[[#This Row],[INGRESOS]] -> 50000 | H4: -8712582.8 | I4: 1450 | J4: =Tabla3[[#This Row],[EGRESOS]]/Tabla3[[#This Row],[TC]] -> 34.482759 | K4: =Tabla3[[#This Row],[INGRESOS]]/Tabla3[[#This Row],[TC]] -> 0 | L4: ARS | M4: CC | N4: NACION | O4: ADMINISTRACION | P4: GASTOS_BANC | Q4: COMISIONES | U4: 05. GASTOS_ADM | W4: 25/26
A5: ="ENERO" -> ENERO | B5: 46024 | C5: I.V.A. BASE | E5: 10500 | F5: 0 | G5: =Tabla3[[#This Row],[EGRESOS]]-Tabla3[[#This Row],[INGRESOS]] -> 10500 | H5: -8716463.6 | I5: 1450 | J5: =Tabla3[[#This Row],[EGRESOS]]/Tabla3[[#This Row],[TC]] -> 7.2413793 | K5: =Tabla3[[#This Row],[INGRESOS]]/Tabla3[[#This Row],[TC]] -> 0 | L5: ARS | M5: CC | N5: NACION | O5: ADMINISTRACION | P5: GASTOS_BANC | Q5: IMPUESTOS | R5: DEBITO IVA FISCAL | U5: 05. GASTOS_ADM | W5: 25/26
A6: ="ENERO" -> ENERO | B6: 46024 | C6: RETEN. I.V.A. RG.2408 | E6: 1500 | F6: 0 | G6: =Tabla3[[#This Row],[EGRESOS]]-Tabla3[[#This Row],[INGRESOS]] -> 1500 | H6: -8720344.4 | I6: 1450 | J6: =Tabla3[[#This Row],[EGRESOS]]/Tabla3[[#This Row],[TC]] -> 1.0344828 | K6: =Tabla3[[#This Row],[INGRESOS]]/Tabla3[[#This Row],[TC]] -> 0 | L6: ARS | M6: CC | N6: NACION | O6: ADMINISTRACION | P6: GASTOS_BANC | Q6: IMPUESTOS | R6: RETENCIONES | U6: 05. GASTOS_ADM | W6: 25/26
A7: ="ENERO" -> ENERO | B7: 46024 | C7: GRAVAMEN LEY 25413 S/DEB | E7: 300 | F7: 0 | G7: =Tabla3[[#This Row],[EGRESOS]]-Tabla3[[#This Row],[INGRESOS]] -> 300 | H7: -8724225.2 | I7: 1450 | J7: =Tabla3[[#This Row],[EGRESOS]]/Tabla3[[#This Row],[TC]] -> 0.20689655 | K7: =Tabla3[[#This Row],[INGRESOS]]/Tabla3[[#This Row],[TC]] -> 0 | L7: ARS | M7: CC | N7: NACION | O7: ADMINISTRACION | P7: GASTOS_BANC | Q7: IMPUESTOS | R7: TASA GENERAL | U7: 05. GASTOS_ADM | W7: 25/26
A8: ="ENERO" -> ENERO | B8: 46024 | C8: GRAVAMEN LEY 25413 S/DEB | E8: 63 | F8: 0 | G8: =Tabla3[[#This Row],[EGRESOS]]-Tabla3[[#This Row],[INGRESOS]] -> 63 | H8: -8728106 | I8: 1450 | J8: =Tabla3[[#This Row],[EGRESOS]]/Tabla3[[#This Row],[TC]] -> 0.043448276 | K8: =Tabla3[[#This Row],[INGRESOS]]/Tabla3[[#This Row],[TC]] -> 0 | L8: ARS | M8: CC | N8: NACION | O8: ADMINISTRACION | P8: GASTOS_BANC | Q8: IMPUESTOS | R8: TASA GENERAL | U8: 05. GASTOS_ADM | W8: 25/26
A9: ="ENERO" -> ENERO | B9: 46024 | C9: GRAVAMEN LEY 25413 S/DEB | E9: 9 | F9: 0 | G9: =Tabla3[[#This Row],[EGRESOS]]-Tabla3[[#This Row],[INGRESOS]] -> 9 | H9: -8731986.8 | I9: 1450 | J9: =Tabla3[[#This Row],[EGRESOS]]/Tabla3[[#This Row],[TC]] -> 0.0062068966 | K9: =Tabla3[[#This Row],[INGRESOS]]/Tabla3[[#This Row],[TC]] -> 0 | L9: ARS | M9: CC | N9: NACION | O9: ADMINISTRACION | P9: GASTOS_BANC | Q9: IMPUESTOS | R9: TASA GENERAL | U9: 05. GASTOS_ADM | W9: 25/26
A10: ="ENERO" -> ENERO | B10: 46036 | C10: DEB.TRAN.INTERB | E10: 600000 | F10: 0 | G10: =Tabla3[[#This Row],[EGRESOS]]-Tabla3[[#This Row],[INGRESOS]] -> 600000 | H10: -8735867.6 | I10: 1450 | J10: =Tabla3[[#This Row],[EGRESOS]]/Tabla3[[#This Row],[TC]] -> 413.7931 | K10: =Tabla3[[#This Row],[INGRESOS]]/Tabla3[[#This Row],[TC]] -> 0 | L10: ARS | M10: CC | N10: NACION | O10: ADMINISTRACION | P10: SOCIOS | Q10: RETIRO | S10: CLAUDIA ERRECALDE | U10: 12. UTILIDADES CLAUDIA | V10: CLAUDIA | W10: 25/26
A11: ="ENERO" -> ENERO | B11: 46036 | C11: GRAVAMEN LEY 25413 S/DEB | E11: 3600 | F11: 0 | G11: =Tabla3[[#This Row],[EGRESOS]]-Tabla3[[#This Row],[INGRESOS]] -> 3600 | H11: -8739748.4 | I11: 1450 | J11: =Tabla3[[#This Row],[EGRESOS]]/Tabla3[[#This Row],[TC]] -> 2.4827586 | K11: =Tabla3[[#This Row],[INGRESOS]]/Tabla3[[#This Row],[TC]] -> 0 | L11: ARS | M11: CC | N11: NACION | O11: ADMINISTRACION | P11: GASTOS_BANC | Q11: IMPUESTOS | R11: TASA GENERAL | U11: 05. GASTOS_ADM | W11: 25/26
A12: ="ENERO" -> ENERO | B12: 46037 | C12: CRED BE O BCO-MIS TIT IBK - CUIT/CUIL: 30708920882 | E12: 0 | F12: 2700000 | G12: =Tabla3[[#This Row],[EGRESOS]]-Tabla3[[#This Row],[INGRESOS]] -> -2700000 | H12: 71294.17 | I12: 1450 | J12: =Tabla3[[#This Row],[EGRESOS]]/Tabla3[[#This Row],[TC]] -> 0 | K12: =Tabla3[[#This Row],[INGRESOS]]/Tabla3[[#This Row],[TC]] -> 1862.069 | L12: ARS | M12: CC | N12: NACION | O12: FINANCIERA | P12: INTERBANKING | Q12: TRANSF. PROPIAS | R12: DESDE CC MACRO | U12: 06. COMPENSATORIOS | W12: 24/25
A13: ="ENERO" -> ENERO | B13: 46049 | C13: INTERESES | E13: 19690.77 | F13: 0 | G13: =Tabla3[[#This Row],[EGRESOS]]-Tabla3[[#This Row],[INGRESOS]] -> 19690.77 | I13: 1450 | J13: =Tabla3[[#This Row],[EGRESOS]]/Tabla3[[#This Row],[TC]] -> 13.579841 | K13: =Tabla3[[#This Row],[INGRESOS]]/Tabla3[[#This Row],[TC]] -> 0 | L13: ARS | M13: CC | N13: NACION | O13: ADMINISTRACION | P13: GASTOS_FIN | Q13: INTERESES | U13: 05. GASTOS_ADM | W13: 25/26
A14: ="ENERO" -> ENERO | B14: 46049 | C14: INTERESES | E14: 38029.83 | F14: 0 | G14: =Tabla3[[#This Row],[EGRESOS]]-Tabla3[[#This Row],[INGRESOS]] -> 38029.83 | I14: 1450 | J14: =Tabla3[[#This Row],[EGRESOS]]/Tabla3[[#This Row],[TC]] -> 26.227469 | K14: =Tabla3[[#This Row],[INGRESOS]]/Tabla3[[#This Row],[TC]] -> 0 | L14: ARS | M14: CC | N14: NACION | O14: ADMINISTRACION | P14: GASTOS_FIN | Q14: INTERESES | U14: 05. GASTOS_ADM | W14: 25/26
A15: ="ENERO" -> ENERO | B15: 46049 | C15: INTERESES | E15: 5622.29 | F15: 0 | G15: =Tabla3[[#This Row],[EGRESOS]]-Tabla3[[#This Row],[INGRESOS]] -> 5622.29 | I15: 1450 | J15: =Tabla3[[#This Row],[EGRESOS]]/Tabla3[[#This Row],[TC]] -> 3.8774414 | K15: =Tabla3[[#This Row],[INGRESOS]]/Tabla3[[#This Row],[TC]] -> 0 | L15: ARS | M15: CC | N15: NACION | O15: ADMINISTRACION | P15: GASTOS_FIN | Q15: INTERESES | U15: 05. GASTOS_ADM | W15: 25/26
A16: ="ENERO" -> ENERO | B16: 46049 | C16: GRAVAMEN LEY 25413 S/DEB | E16: 118.14 | F16: 0 | G16: =Tabla3[[#This Row],[EGRESOS]]-Tabla3[[#This Row],[INGRESOS]] -> 118.14 | I16: 1450 | J16: =Tabla3[[#This Row],[EGRESOS]]/Tabla3[[#This Row],[TC]] -> 0.081475862 | K16: =Tabla3[[#This Row],[INGRESOS]]/Tabla3[[#This Row],[TC]] -> 0 | L16: ARS | M16: CC | N16: NACION | O16: ADMINISTRACION | P16: GASTOS_BANC | Q16: IMPUESTOS | R16: TASA GENERAL | U16: 05. GASTOS_ADM | W16: 25/26
A17: ="ENERO" -> ENERO | B17: 46049 | C17: GRAVAMEN LEY 25413 S/DEB | E17: 228.18 | F17: 0 | G17: =Tabla3[[#This Row],[EGRESOS]]-Tabla3[[#This Row],[INGRESOS]] -> 228.18 | I17: 1450 | J17: =Tabla3[[#This Row],[EGRESOS]]/Tabla3[[#This Row],[TC]] -> 0.15736552 | K17: =Tabla3[[#This Row],[INGRESOS]]/Tabla3[[#This Row],[TC]] -> 0 | L17: ARS | M17: CC | N17: NACION | O17: ADMINISTRACION | P17: GASTOS_BANC | Q17: IMPUESTOS | R17: TASA GENERAL | U17: 05. GASTOS_ADM | W17: 25/26
A18: ="ENERO" -> ENERO | B18: 46049 | C18: GRAVAMEN LEY 25413 S/DEB | E18: 33.73 | F18: 0 | G18: =Tabla3[[#This Row],[EGRESOS]]-Tabla3[[#This Row],[INGRESOS]] -> 33.73 | H18: 7571.23 | I18: 1450 | J18: =Tabla3[[#This Row],[EGRESOS]]/Tabla3[[#This Row],[TC]] -> 0.023262069 | K18: =Tabla3[[#This Row],[INGRESOS]]/Tabla3[[#This Row],[TC]] -> 0 | L18: ARS | M18: CC | N18: NACION | O18: ADMINISTRACION | P18: GASTOS_BANC | Q18: IMPUESTOS | R18: TASA GENERAL | U18: 05. GASTOS_ADM | W18: 25/26
A19: ="ENERO" -> ENERO | B19: 46030 | C19: GRAVAMEN LEY 25413 S/DEB | E19: 296.56 | F19: 0 | G19: =Tabla3[[#This Row],[EGRESOS]]-Tabla3[[#This Row],[INGRESOS]] -> 296.56 | I19: 1450 | J19: =Tabla3[[#This Row],[EGRESOS]]/Tabla3[[#This Row],[TC]] -> 0.20452414 | K19: =Tabla3[[#This Row],[INGRESOS]]/Tabla3[[#This Row],[TC]] -> 0 | L19: ARS | M19: CC | N19: NACION | O19: ADMINISTRACION | P19: GASTOS_BANC | Q19: IMPUESTOS | R19: TASA GENERAL | U19: 05. GASTOS_ADM | W19: 25/26
A20: ="ENERO" -> ENERO | B20: 46050 | C20: PM/TOT. RES. AGRONACION | E20: 49426.18 | F20: 0 | G20: =Tabla3[[#This Row],[EGRESOS]]-Tabla3[[#This Row],[INGRESOS]] -> 49426.18 | H20: -42151.1 | I20: 1450 | J20: =Tabla3[[#This Row],[EGRESOS]]/Tabla3[[#This Row],[TC]] -> 34.087021 | K20: =Tabla3[[#This Row],[INGRESOS]]/Tabla3[[#This Row],[TC]] -> 0 | L20: ARS | M20: CC | N20: NACION | O20: ADMINISTRACION | P20: GASTOS_BANC | Q20: COMISIONES | U20: 05. GASTOS_ADM | W20: 25/26
A21: ="FEBRERO" -> FEBRERO | B21: 46055 | C21: COMISION PAQUETES | E21: 50000 | F21: 0 | G21: =Tabla3[[#This Row],[EGRESOS]]-Tabla3[[#This Row],[INGRESOS]] -> 50000 | I21: 1450 | J21: =Tabla3[[#This Row],[EGRESOS]]/Tabla3[[#This Row],[TC]] -> 34.482759 | K21: =Tabla3[[#This Row],[INGRESOS]]/Tabla3[[#This Row],[TC]] -> 0 | L21: ARS | M21: CC | N21: NACION | O21: ADMINISTRACION | P21: GASTOS_BANC | Q21: COMISIONES | U21: 05. GASTOS_ADM | W21: 25/26
A22: ="FEBRERO" -> FEBRERO | B22: 46055 | C22: I.V.A. BASE | E22: 10500 | F22: 0 | G22: =Tabla3[[#This Row],[EGRESOS]]-Tabla3[[#This Row],[INGRESOS]] -> 10500 | I22: 1450 | J22: =Tabla3[[#This Row],[EGRESOS]]/Tabla3[[#This Row],[TC]] -> 7.2413793 | K22: =Tabla3[[#This Row],[INGRESOS]]/Tabla3[[#This Row],[TC]] -> 0 | L22: ARS | M22: CC | N22: NACION | O22: ADMINISTRACION | P22: GASTOS_BANC | Q22: IMPUESTOS | R22: DEBITO IVA FISCAL | U22: 05. GASTOS_ADM | W22: 25/26
A23: ="FEBRERO" -> FEBRERO | B23: 46055 | C23: RETEN. I.V.A. RG.2408 | E23: 1500 | F23: 0 | G23: =Tabla3[[#This Row],[EGRESOS]]-Tabla3[[#This Row],[INGRESOS]] -> 1500 | I23: 1450 | J23: =Tabla3[[#This Row],[EGRESOS]]/Tabla3[[#This Row],[TC]] -> 1.0344828 | K23: =Tabla3[[#This Row],[INGRESOS]]/Tabla3[[#This Row],[TC]] -> 0 | L23: ARS | M23: CC | N23: NACION | O23: ADMINISTRACION | P23: GASTOS_BANC | Q23: IMPUESTOS | R23: RETENCIONES | U23: 05. GASTOS_ADM | W23: 25/26
A24: ="FEBRERO" -> FEBRERO | B24: 46055 | C24: GRAVAMEN LEY 25413 S/DEB | E24: 300 | F24: 0 | G24: =Tabla3[[#This Row],[EGRESOS]]-Tabla3[[#This Row],[INGRESOS]] -> 300 | I24: 1450 | J24: =Tabla3[[#This Row],[EGRESOS]]/Tabla3[[#This Row],[TC]] -> 0.20689655 | K24: =Tabla3[[#This Row],[INGRESOS]]/Tabla3[[#This Row],[TC]] -> 0 | L24: ARS | M24: CC | N24: NACION | O24: ADMINISTRACION | P24: GASTOS_BANC | Q24: IMPUESTOS | R24: TASA GENERAL | U24: 05. GASTOS_ADM | W24: 25/26
A25: ="FEBRERO" -> FEBRERO | B25: 46055 | C25: GRAVAMEN LEY 25413 S/DEB | E25: 63 | F25: 0 | G25: =Tabla3[[#This Row],[EGRESOS]]-Tabla3[[#This Row],[INGRESOS]] -> 63 | I25: 1450 | J25: =Tabla3[[#This Row],[EGRESOS]]/Tabla3[[#This Row],[TC]] -> 0.043448276 | K25: =Tabla3[[#This Row],[INGRESOS]]/Tabla3[[#This Row],[TC]] -> 0 | L25: ARS | M25: CC | N25: NACION | O25: ADMINISTRACION | P25: GASTOS_BANC | Q25: IMPUESTOS | R25: TASA GENERAL | U25: 05. GASTOS_ADM | W25: 25/26
A26: ="FEBRERO" -> FEBRERO | B26: 46055 | C26: GRAVAMEN LEY 25413 S/DEB | E26: 9 | F26: 0 | G26: =Tabla3[[#This Row],[EGRESOS]]-Tabla3[[#This Row],[INGRESOS]] -> 9 | H26: -104523.51 | I26: 1450 | J26: =Tabla3[[#This Row],[EGRESOS]]/Tabla3[[#This Row],[TC]] -> 0.0062068966 | K26: =Tabla3[[#This Row],[INGRESOS]]/Tabla3[[#This Row],[TC]] -> 0 | L26: ARS | M26: CC | N26: NACION | O26: ADMINISTRACION | P26: GASTOS_BANC | Q26: IMPUESTOS | R26: TASA GENERAL | U26: 05. GASTOS_ADM | W26: 25/26
A27: ="FEBRERO" -> FEBRERO | B27: 46057 | C27: CRED BE O BCO-MIS TIT IBK - CUIT/CUIL: 30708920882 | D27: - | E27: 0 | F27: 150000 | G27: =Tabla3[[#This Row],[EGRESOS]]-Tabla3[[#This Row],[INGRESOS]] -> -150000 | H27: 45476.49 | I27: 1450 | J27: =Tabla3[[#This Row],[EGRESOS]]/Tabla3[[#This Row],[TC]] -> 0 | K27: =Tabla3[[#This Row],[INGRESOS]]/Tabla3[[#This Row],[TC]] -> 103.44828 | L27: ARS | M27: CC | N27: NACION | O27: FINANCIERA | P27: INTERBANKING | Q27: TRANSF. PROPIAS | R27: DESDE CC MACRO | U27: 06. COMPENSATORIOS | W27: 24/25
A28: ="FEBRERO" -> FEBRERO | B28: 46062 | C28: CRED BE O BCO-MIS TIT IBK - CUIT/CUIL: 30708920882 | E28: 0 | F28: 30000000 | G28: =Tabla3[[#This Row],[EGRESOS]]-Tabla3[[#This Row],[INGRESOS]] -> -30000000 | I28: 1450 | J28: =Tabla3[[#This Row],[EGRESOS]]/Tabla3[[#This Row],[TC]] -> 0 | K28: =Tabla3[[#This Row],[INGRESOS]]/Tabla3[[#This Row],[TC]] -> 20689.655 | L28: ARS | M28: CC | N28: NACION | O28: FINANCIERA | P28: INTERBANKING | Q28: TRANSF. PROPIAS | R28: DESDE CC MACRO | U28: 06. COMPENSATORIOS | W28: 25/26
A29: ="FEBRERO" -> FEBRERO | B29: 46062 | C29: CRED BE O BCO-MIS TIT IBK - CUIT/CUIL: 30708920882 | E29: 0 | F29: 1700000 | G29: =Tabla3[[#This Row],[EGRESOS]]-Tabla3[[#This Row],[INGRESOS]] -> -1700000 | I29: 1450 | J29: =Tabla3[[#This Row],[EGRESOS]]/Tabla3[[#This Row],[TC]] -> 0 | K29: =Tabla3[[#This Row],[INGRESOS]]/Tabla3[[#This Row],[TC]] -> 1172.4138 | L29: ARS | M29: CC | N29: NACION | O29: FINANCIERA | P29: INTERBANKING | Q29: TRANSF. PROPIAS | R29: DESDE CC GALICIA | U29: 06. COMPENSATORIOS | W29: 25/26
A30: ="FEBRERO" -> FEBRERO | B30: 46062 | C30: TRANSF.INTER.MMO.TITULAR - CUIT/CUIL: 30708920882 | E30: 0 | F30: 19500000 | G30: =Tabla3[[#This Row],[EGRESOS]]-Tabla3[[#This Row],[INGRESOS]] -> -19500000 | I30: 1450 | J30: =Tabla3[[#This Row],[EGRESOS]]/Tabla3[[#This Row],[TC]] -> 0 | K30: =Tabla3[[#This Row],[INGRESOS]]/Tabla3[[#This Row],[TC]] -> 13448.276 | L30: ARS | M30: CC | N30: NACION | O30: FINANCIERA | P30: INTERBANKING | Q30: TRANSF. PROPIAS | R30: DESDE CC PAMPA | U30: 06. COMPENSATORIOS | W30: 25/26
A31: ="FEBRERO" -> FEBRERO | B31: 46062 | C31: CRED BE O BCO-MIS TIT IBK - CUIT/CUIL: 30708920882 | E31: 0 | F31: 3500000 | G31: =Tabla3[[#This Row],[EGRESOS]]-Tabla3[[#This Row],[INGRESOS]] -> -3500000 | I31: 1450 | J31: =Tabla3[[#This Row],[EGRESOS]]/Tabla3[[#This Row],[TC]] -> 0 | K31: =Tabla3[[#This Row],[INGRESOS]]/Tabla3[[#This Row],[TC]] -> 2413.7931 | L31: ARS | M31: CC | N31: NACION | O31: FINANCIERA | P31: INTERBANKING | Q31: TRANSF. PROPIAS | R31: DESDE CC MACRO | U31: 06. COMPENSATORIOS | W31: 25/26
A32: ="FEBRERO" -> FEBRERO | B32: 46062 | C32: CPRA.VTA.NO GRAVADA | E32: 50750000 | F32: 0 | G32: =Tabla3[[#This Row],[EGRESOS]]-Tabla3[[#This Row],[INGRESOS]] -> 50750000 | I32: 1450 | J32: =Tabla3[[#This Row],[EGRESOS]]/Tabla3[[#This Row],[TC]] -> 35000 | K32: =Tabla3[[#This Row],[INGRESOS]]/Tabla3[[#This Row],[TC]] -> 0 | L32: ARS | M32: CC | N32: NACION | O32: FINANCIERA | P32: AMORT. CREDITOS | Q32: CUOTA 1 | R32: SGR NACION | S32: NACION | U32: 17. CANC CREDITO SGR | V32: NACION | W32: 25/26
A33: ="FEBRERO" -> FEBRERO | B33: 46062 | C33: CPRA.VTA.NO GRAVADA | E33: 3880200 | F33: 0 | G33: =Tabla3[[#This Row],[EGRESOS]]-Tabla3[[#This Row],[INGRESOS]] -> 3880200 | I33: 1450 | J33: =Tabla3[[#This Row],[EGRESOS]]/Tabla3[[#This Row],[TC]] -> 2676 | K33: =Tabla3[[#This Row],[INGRESOS]]/Tabla3[[#This Row],[TC]] -> 0 | L33: ARS | M33: CC | N33: NACION | O33: FINANCIERA | P33: AMORT. CREDITOS | Q33: CUOTA 1 | R33: SGR NACION | S33: NACION | U33: 17. CANC CREDITO SGR | V33: NACION | W33: 25/26
A34: ="FEBRERO" -> FEBRERO | B34: 46062 | C34: DEBITO PAGO PRESTAMO | E34: 465508 | F34: 0 | G34: =Tabla3[[#This Row],[EGRESOS]]-Tabla3[[#This Row],[INGRESOS]] -> 465508 | I34: 1450 | J34: =Tabla3[[#This Row],[EGRESOS]]/Tabla3[[#This Row],[TC]] -> 321.04 | K34: =Tabla3[[#This Row],[INGRESOS]]/Tabla3[[#This Row],[TC]] -> 0 | L34: ARS | M34: CC | N34: NACION | O34: FINANCIERA | P34: AMORT. CREDITOS | Q34: CUOTA 1 | R34: SGR NACION | S34: NACION | U34: 17. CANC CREDITO SGR | V34: NACION | W34: 25/26
A35: ="FEBRERO" -> FEBRERO | B35: 46062 | C35: COMIS.DE COMPROMISO | E35: 37500 | F35: 0 | G35: =Tabla3[[#This Row],[EGRESOS]]-Tabla3[[#This Row],[INGRESOS]] -> 37500 | I35: 1450 | J35: =Tabla3[[#This Row],[EGRESOS]]/Tabla3[[#This Row],[TC]] -> 25.862069 | K35: =Tabla3[[#This Row],[INGRESOS]]/Tabla3[[#This Row],[TC]] -> 0 | L35: ARS | M35: CC | N35: NACION | O35: ADMINISTRACION | P35: GASTOS_BANC | Q35: COMISIONES | U35: 05. GASTOS_ADM | W35: 25/26
A36: ="FEBRERO" -> FEBRERO | B36: 46062 | C36: I.V.A. BASE | E36: 7875 | F36: 0 | G36: =Tabla3[[#This Row],[EGRESOS]]-Tabla3[[#This Row],[INGRESOS]] -> 7875 | I36: 1450 | J36: =Tabla3[[#This Row],[EGRESOS]]/Tabla3[[#This Row],[TC]] -> 5.4310345 | K36: =Tabla3[[#This Row],[INGRESOS]]/Tabla3[[#This Row],[TC]] -> 0 | L36: ARS | M36: CC | N36: NACION | O36: ADMINISTRACION | P36: GASTOS_BANC | Q36: IMPUESTOS | R36: DEBITO IVA FISCAL | U36: 05. GASTOS_ADM | W36: 25/26
A37: ="FEBRERO" -> FEBRERO | B37: 46062 | C37: RETEN. I.V.A. RG.2408 | E37: 1125 | F37: 0 | G37: =Tabla3[[#This Row],[EGRESOS]]-Tabla3[[#This Row],[INGRESOS]] -> 1125 | I37: 1450 | J37: =Tabla3[[#This Row],[EGRESOS]]/Tabla3[[#This Row],[TC]] -> 0.77586207 | K37: =Tabla3[[#This Row],[INGRESOS]]/Tabla3[[#This Row],[TC]] -> 0 | L37: ARS | M37: CC | N37: NACION | O37: ADMINISTRACION | P37: GASTOS_BANC | Q37: IMPUESTOS | R37: RETENCIONES | U37: 05. GASTOS_ADM | W37: 25/26
A38: ="FEBRERO" -> FEBRERO | B38: 46062 | C38: GRAVAMEN LEY 25413 S/DEB | E38: 2793.05 | F38: 0 | G38: =Tabla3[[#This Row],[EGRESOS]]-Tabla3[[#This Row],[INGRESOS]] -> 2793.05 | I38: 1450 | J38: =Tabla3[[#This Row],[EGRESOS]]/Tabla3[[#This Row],[TC]] -> 1.9262414 | K38: =Tabla3[[#This Row],[INGRESOS]]/Tabla3[[#This Row],[TC]] -> 0 | L38: ARS | M38: CC | N38: NACION | O38: ADMINISTRACION | P38: GASTOS_BANC | Q38: IMPUESTOS | R38: TASA GENERAL | U38: 05. GASTOS_ADM | W38: 25/26
A39: ="FEBRERO" -> FEBRERO | B39: 46062 | C39: GRAVAMEN LEY 25413 S/DEB | E39: 47.25 | F39: 0 | G39: =Tabla3[[#This Row],[EGRESOS]]-Tabla3[[#This Row],[INGRESOS]] -> 47.25 | I39: 1450 | J39: =Tabla3[[#This Row],[EGRESOS]]/Tabla3[[#This Row],[TC]] -> 0.032586207 | K39: =Tabla3[[#This Row],[INGRESOS]]/Tabla3[[#This Row],[TC]] -> 0 | L39: ARS | M39: CC | N39: NACION | O39: ADMINISTRACION | P39: GASTOS_BANC | Q39: IMPUESTOS | R39: TASA GENERAL | U39: 05. GASTOS_ADM | W39: 25/26
A40: ="FEBRERO" -> FEBRERO | B40: 46062 | C40: GRAVAMEN LEY 25413 S/DEB | E40: 6.75 | F40: 0 | G40: =Tabla3[[#This Row],[EGRESOS]]-Tabla3[[#This Row],[INGRESOS]] -> 6.75 | I40: 1450 | J40: =Tabla3[[#This Row],[EGRESOS]]/Tabla3[[#This Row],[TC]] -> 0.0046551724 | K40: =Tabla3[[#This Row],[INGRESOS]]/Tabla3[[#This Row],[TC]] -> 0 | L40: ARS | M40: CC | N40: NACION | O40: ADMINISTRACION | P40: GASTOS_BANC | Q40: IMPUESTOS | R40: TASA GENERAL | U40: 05. GASTOS_ADM | W40: 25/26
A41: ="FEBRERO" -> FEBRERO | B41: 46063 | C41: DEB.TRAN.INTERBMISMO TIT | E41: 700000 | F41: 0 | G41: =Tabla3[[#This Row],[EGRESOS]]-Tabla3[[#This Row],[INGRESOS]] -> 700000 | I41: 1450 | J41: =Tabla3[[#This Row],[EGRESOS]]/Tabla3[[#This Row],[TC]] -> 482.75862 | K41: =Tabla3[[#This Row],[INGRESOS]]/Tabla3[[#This Row],[TC]] -> 0 | L41: ARS | M41: CC | N41: NACION | O41: FINANCIERA | P41: INTERBANKING | Q41: TRANSF. PROPIAS | R41: HACIA CC GALICIA | U41: 06. COMPENSATORIOS | W41: 25/26
A42: ="FEBRERO" -> FEBRERO | B42: 46063 | C42: DEB.TRAN.INTERB HABERES | E42: 1074278 | F42: 0 | G42: =Tabla3[[#This Row],[EGRESOS]]-Tabla3[[#This Row],[INGRESOS]] -> 1074278 | I42: 1450 | J42: =Tabla3[[#This Row],[EGRESOS]]/Tabla3[[#This Row],[TC]] -> 740.88138 | K42: =Tabla3[[#This Row],[INGRESOS]]/Tabla3[[#This Row],[TC]] -> 0 | L42: ARS | M42: CC | N42: NACION | O42: ADMINISTRACION | P42: GASTOS_FIN | Q42: INTERESES | U42: 05. GASTOS_ADM | W42: 25/26
A43: ="FEBRERO" -> FEBRERO | B43: 46063 | C43: CAM.FED.DIST.PZA. O/BCOS. | E43: 0 | F43: 702900 | G43: =Tabla3[[#This Row],[EGRESOS]]-Tabla3[[#This Row],[INGRESOS]] -> -702900 | I43: 1450 | J43: =Tabla3[[#This Row],[EGRESOS]]/Tabla3[[#This Row],[TC]] -> 0 | K43: =Tabla3[[#This Row],[INGRESOS]]/Tabla3[[#This Row],[TC]] -> 484.75862 | L43: ARS | M43: CC | N43: NACION | O43: AGRICULTURA | P43: CULT. PRINCIPAL | Q43: SOJA | R43: BPAS | S43: CENTRO GANADERO | U43: 16. INGRESOS AGROPECUARIOS | W43: 25/26
A44: ="FEBRERO" -> FEBRERO | B44: 46063 | C44: COMIS. CANJE O/BANCOS | E44: 3514.5 | F44: 0 | G44: =Tabla3[[#This Row],[EGRESOS]]-Tabla3[[#This Row],[INGRESOS]] -> 3514.5 | I44: 1450 | J44: =Tabla3[[#This Row],[EGRESOS]]/Tabla3[[#This Row],[TC]] -> 2.4237931 | K44: =Tabla3[[#This Row],[INGRESOS]]/Tabla3[[#This Row],[TC]] -> 0 | L44: ARS | M44: CC | N44: NACION | O44: ADMINISTRACION | P44: GASTOS_BANC | Q44: COMISIONES | U44: 05. GASTOS_ADM | W44: 25/26
A45: ="FEBRERO" -> FEBRERO | B45: 46063 | C45: I.V.A. BASE | E45: 738.05 | F45: 0 | G45: =Tabla3[[#This Row],[EGRESOS]]-Tabla3[[#This Row],[INGRESOS]] -> 738.05 | I45: 1450 | J45: =Tabla3[[#This Row],[EGRESOS]]/Tabla3[[#This Row],[TC]] -> 0.509 | K45: =Tabla3[[#This Row],[INGRESOS]]/Tabla3[[#This Row],[TC]] -> 0 | L45: ARS | M45: CC | N45: NACION | O45: ADMINISTRACION | P45: GASTOS_BANC | Q45: IMPUESTOS | R45: DEBITO IVA FISCAL | U45: 05. GASTOS_ADM | W45: 25/26
A46: ="FEBRERO" -> FEBRERO | B46: 46063 | C46: RETEN. I.V.A. RG.2408 | E46: 105.44 | F46: 0 | G46: =Tabla3[[#This Row],[EGRESOS]]-Tabla3[[#This Row],[INGRESOS]] -> 105.44 | I46: 1450 | J46: =Tabla3[[#This Row],[EGRESOS]]/Tabla3[[#This Row],[TC]] -> 0.072717241 | K46: =Tabla3[[#This Row],[INGRESOS]]/Tabla3[[#This Row],[TC]] -> 0 | L46: ARS | M46: CC | N46: NACION | O46: ADMINISTRACION | P46: GASTOS_BANC | Q46: IMPUESTOS | R46: RETENCIONES | U46: 05. GASTOS_ADM | W46: 25/26
A47: ="FEBRERO" -> FEBRERO | B47: 46063 | C47: GRAVAMEN LEY 25413 S/DEB | E47: 6445.67 | F47: 0 | G47: =Tabla3[[#This Row],[EGRESOS]]-Tabla3[[#This Row],[INGRESOS]] -> 6445.67 | I47: 1450 | J47: =Tabla3[[#This Row],[EGRESOS]]/Tabla3[[#This Row],[TC]] -> 4.4452897 | K47: =Tabla3[[#This Row],[INGRESOS]]/Tabla3[[#This Row],[TC]] -> 0 | L47: ARS | M47: CC | N47: NACION | O47: ADMINISTRACION | P47: GASTOS_BANC | Q47: IMPUESTOS | R47: TASA GENERAL | U47: 05. GASTOS_ADM | W47: 25/26
A48: ="FEBRERO" -> FEBRERO | B48: 46063 | C48: GRAVAMEN LEY 25413 S/CRED | E48: 4217.4 | F48: 0 | G48: =Tabla3[[#This Row],[EGRESOS]]-Tabla3[[#This Row],[INGRESOS]] -> 4217.4 | I48: 1450 | J48: =Tabla3[[#This Row],[EGRESOS]]/Tabla3[[#This Row],[TC]] -> 2.9085517 | K48: =Tabla3[[#This Row],[INGRESOS]]/Tabla3[[#This Row],[TC]] -> 0 | L48: ARS | M48: CC | N48: NACION | O48: ADMINISTRACION | P48: GASTOS_BANC | Q48: IMPUESTOS | R48: TASA GENERAL | U48: 05. GASTOS_ADM | W48: 25/26
A49: ="FEBRERO" -> FEBRERO | B49: 46063 | C49: GRAVAMEN LEY 25413 S/DEB | E49: 21.09 | F49: 0 | G49: =Tabla3[[#This Row],[EGRESOS]]-Tabla3[[#This Row],[INGRESOS]] -> 21.09 | I49: 1450 | J49: =Tabla3[[#This Row],[EGRESOS]]/Tabla3[[#This Row],[TC]] -> 0.014544828 | K49: =Tabla3[[#This Row],[INGRESOS]]/Tabla3[[#This Row],[TC]] -> 0 | L49: ARS | M49: CC | N49: NACION | O49: ADMINISTRACION | P49: GASTOS_BANC | Q49: IMPUESTOS | R49: TASA GENERAL | U49: 05. GASTOS_ADM | W49: 25/26
A50: ="FEBRERO" -> FEBRERO | B50: 46063 | C50: GRAVAMEN LEY 25413 S/DEB | E50: 4.43 | F50: 0 | G50: =Tabla3[[#This Row],[EGRESOS]]-Tabla3[[#This Row],[INGRESOS]] -> 4.43 | I50: 1450 | J50: =Tabla3[[#This Row],[EGRESOS]]/Tabla3[[#This Row],[TC]] -> 0.0030551724 | K50: =Tabla3[[#This Row],[INGRESOS]]/Tabla3[[#This Row],[TC]] -> 0 | L50: ARS | M50: CC | N50: NACION | O50: ADMINISTRACION | P50: GASTOS_BANC | Q50: IMPUESTOS | R50: TASA GENERAL | U50: 05. GASTOS_ADM | W50: 25/26
A51: ="FEBRERO" -> FEBRERO | B51: 46063 | C51: GRAVAMEN LEY 25413 S/DEB | E51: 0.63 | F51: 0 | G51: =Tabla3[[#This Row],[EGRESOS]]-Tabla3[[#This Row],[INGRESOS]] -> 0.63 | I51: 1450 | J51: =Tabla3[[#This Row],[EGRESOS]]/Tabla3[[#This Row],[TC]] -> 0.00043448276 | K51: =Tabla3[[#This Row],[INGRESOS]]/Tabla3[[#This Row],[TC]] -> 0 | L51: ARS | M51: CC | N51: NACION | O51: ADMINISTRACION | P51: GASTOS_BANC | Q51: IMPUESTOS | R51: TASA GENERAL | U51: 05. GASTOS_ADM | W51: 25/26
A52: ="FEBRERO" -> FEBRERO | B52: 46064 | C52: DEB.TRAN.INTERBMISMO TIT | E52: 300 | F52: 0 | G52: =Tabla3[[#This Row],[EGRESOS]]-Tabla3[[#This Row],[INGRESOS]] -> 300 | I52: 1450 | J52: =Tabla3[[#This Row],[EGRESOS]]/Tabla3[[#This Row],[TC]] -> 0.20689655 | K52: =Tabla3[[#This Row],[INGRESOS]]/Tabla3[[#This Row],[TC]] -> 0 | L52: ARS | M52: CC | N52: NACION | O52: FINANCIERA | P52: INTERBANKING | Q52: TRANSF. PROPIAS | R52: HACIA CC GALICIA | U52: 06. COMPENSATORIOS | W52: 25/26
A53: ="FEBRERO" -> FEBRERO | B53: 46064 | C53: DEB.TRAN.INTERBMISMO TIT | E53: 300000 | F53: 0 | G53: =Tabla3[[#This Row],[EGRESOS]]-Tabla3[[#This Row],[INGRESOS]] -> 300000 | I53: 1450 | J53: =Tabla3[[#This Row],[EGRESOS]]/Tabla3[[#This Row],[TC]] -> 206.89655 | K53: =Tabla3[[#This Row],[INGRESOS]]/Tabla3[[#This Row],[TC]] -> 0 | L53: ARS | M53: CC | N53: NACION | O53: FINANCIERA | P53: INTERBANKING | Q53: TRANSF. PROPIAS | R53: HACIA CC GALICIA | U53: 06. COMPENSATORIOS | W53: 25/26
A54: ="FEBRERO" -> FEBRERO | B54: 46064 | C54: COM TRANSFE ELECTRONICA | E54: 956 | F54: 0 | G54: =Tabla3[[#This Row],[EGRESOS]]-Tabla3[[#This Row],[INGRESOS]] -> 956 | I54: 1450 | J54: =Tabla3[[#This Row],[EGRESOS]]/Tabla3[[#This Row],[TC]] -> 0.65931034 | K54: =Tabla3[[#This Row],[INGRESOS]]/Tabla3[[#This Row],[TC]] -> 0 | L54: ARS | M54: CC | N54: NACION | O54: ADMINISTRACION | P54: GASTOS_BANC | Q54: COMISIONES | U54: 05. GASTOS_ADM | W54: 25/26
A55: ="FEBRERO" -> FEBRERO | B55: 46064 | C55: COM TRANSFE ELECTRONICA | E55: 956 | F55: 0 | G55: =Tabla3[[#This Row],[EGRESOS]]-Tabla3[[#This Row],[INGRESOS]] -> 956 | I55: 1450 | J55: =Tabla3[[#This Row],[EGRESOS]]/Tabla3[[#This Row],[TC]] -> 0.65931034 | K55: =Tabla3[[#This Row],[INGRESOS]]/Tabla3[[#This Row],[TC]] -> 0 | L55: ARS | M55: CC | N55: NACION | O55: ADMINISTRACION | P55: GASTOS_BANC | Q55: COMISIONES | U55: 05. GASTOS_ADM | W55: 25/26
A56: ="FEBRERO" -> FEBRERO | B56: 46064 | C56: I.V.A. BASE | E56: 401.52 | F56: 0 | G56: =Tabla3[[#This Row],[EGRESOS]]-Tabla3[[#This Row],[INGRESOS]] -> 401.52 | I56: 1450 | J56: =Tabla3[[#This Row],[EGRESOS]]/Tabla3[[#This Row],[TC]] -> 0.27691034 | K56: =Tabla3[[#This Row],[INGRESOS]]/Tabla3[[#This Row],[TC]] -> 0 | L56: ARS | M56: CC | N56: NACION | O56: ADMINISTRACION | P56: GASTOS_BANC | Q56: IMPUESTOS | R56: DEBITO IVA FISCAL | U56: 05. GASTOS_ADM | W56: 25/26
A57: ="FEBRERO" -> FEBRERO | B57: 46064 | C57: GRAVAMEN LEY 25413 S/DEB | E57: 5.74 | F57: 0 | G57: =Tabla3[[#This Row],[EGRESOS]]-Tabla3[[#This Row],[INGRESOS]] -> 5.74 | I57: 1450 | J57: =Tabla3[[#This Row],[EGRESOS]]/Tabla3[[#This Row],[TC]] -> 0.0039586207 | K57: =Tabla3[[#This Row],[INGRESOS]]/Tabla3[[#This Row],[TC]] -> 0 | L57: ARS | M57: CC | N57: NACION | O57: ADMINISTRACION | P57: GASTOS_BANC | Q57: IMPUESTOS | R57: TASA GENERAL | U57: 05. GASTOS_ADM | W57: 25/26
A58: ="FEBRERO" -> FEBRERO | B58: 46064 | C58: GRAVAMEN LEY 25413 S/DEB | E58: 5.74 | F58: 0 | G58: =Tabla3[[#This Row],[EGRESOS]]-Tabla3[[#This Row],[INGRESOS]] -> 5.74 | I58: 1450 | J58: =Tabla3[[#This Row],[EGRESOS]]/Tabla3[[#This Row],[TC]] -> 0.0039586207 | K58: =Tabla3[[#This Row],[INGRESOS]]/Tabla3[[#This Row],[TC]] -> 0 | L58: ARS | M58: CC | N58: NACION | O58: ADMINISTRACION | P58: GASTOS_BANC | Q58: IMPUESTOS | R58: TASA GENERAL | U58: 05. GASTOS_ADM | W58: 25/26
A59: ="FEBRERO" -> FEBRERO | B59: 46064 | C59: GRAVAMEN LEY 25413 S/DEB | E59: 2.41 | F59: 0 | G59: =Tabla3[[#This Row],[EGRESOS]]-Tabla3[[#This Row],[INGRESOS]] -> 2.41 | I59: 1450 | J59: =Tabla3[[#This Row],[EGRESOS]]/Tabla3[[#This Row],[TC]] -> 0.001662069 | K59: =Tabla3[[#This Row],[INGRESOS]]/Tabla3[[#This Row],[TC]] -> 0 | L59: ARS | M59: CC | N59: NACION | O59: ADMINISTRACION | P59: GASTOS_BANC | Q59: IMPUESTOS | R59: TASA GENERAL | U59: 05. GASTOS_ADM | W59: 25/26
A60: ="FEBRERO" -> FEBRERO | B60: 46065 | C60: DEB.TRAN.INTERBMISMO TIT | E60: 1200000 | F60: 0 | G60: =Tabla3[[#This Row],[EGRESOS]]-Tabla3[[#This Row],[INGRESOS]] -> 1200000 | I60: 1450 | J60: =Tabla3[[#This Row],[EGRESOS]]/Tabla3[[#This Row],[TC]] -> 827.58621 | K60: =Tabla3[[#This Row],[INGRESOS]]/Tabla3[[#This Row],[TC]] -> 0 | L60: ARS | M60: CC | N60: NACION | O60: FINANCIERA | P60: INTERBANKING | Q60: TRANSF. PROPIAS | R60: HACIA CC GALICIA | U60: 06. COMPENSATORIOS | W60: 25/26
A61: ="FEBRERO" -> FEBRERO | B61: 46065 | C61: COM TRANSFE ELECTRONICA | E61: 535 | F61: 0 | G61: =Tabla3[[#This Row],[EGRESOS]]-Tabla3[[#This Row],[INGRESOS]] -> 535 | I61: 1450 | J61: =Tabla3[[#This Row],[EGRESOS]]/Tabla3[[#This Row],[TC]] -> 0.36896552 | K61: =Tabla3[[#This Row],[INGRESOS]]/Tabla3[[#This Row],[TC]] -> 0 | L61: ARS | M61: CC | N61: NACION | O61: ADMINISTRACION | P61: GASTOS_BANC | Q61: COMISIONES | U61: 05. GASTOS_ADM | W61: 25/26
A62: ="FEBRERO" -> FEBRERO | B62: 46065 | C62: I.V.A. BASE | E62: 112.35 | F62: 0 | G62: =Tabla3[[#This Row],[EGRESOS]]-Tabla3[[#This Row],[INGRESOS]] -> 112.35 | I62: 1450 | J62: =Tabla3[[#This Row],[EGRESOS]]/Tabla3[[#This Row],[TC]] -> 0.077482759 | K62: =Tabla3[[#This Row],[INGRESOS]]/Tabla3[[#This Row],[TC]] -> 0 | L62: ARS | M62: CC | N62: NACION | O62: ADMINISTRACION | P62: GASTOS_BANC | Q62: IMPUESTOS | R62: DEBITO IVA FISCAL | U62: 05. GASTOS_ADM | W62: 25/26
A63: ="FEBRERO" -> FEBRERO | B63: 46065 | C63: GRAVAMEN LEY 25413 S/DEB | E63: 3.21 | F63: 0 | G63: =Tabla3[[#This Row],[EGRESOS]]-Tabla3[[#This Row],[INGRESOS]] -> 3.21 | I63: 1450 | J63: =Tabla3[[#This Row],[EGRESOS]]/Tabla3[[#This Row],[TC]] -> 0.0022137931 | K63: =Tabla3[[#This Row],[INGRESOS]]/Tabla3[[#This Row],[TC]] -> 0 | L63: ARS | M63: CC | N63: NACION | O63: ADMINISTRACION | P63: GASTOS_BANC | Q63: IMPUESTOS | R63: TASA GENERAL | U63: 05. GASTOS_ADM | W63: 25/26
A64: ="FEBRERO" -> FEBRERO | B64: 46065 | C64: GRAVAMEN LEY 25413 S/DEB | E64: 0.67 | F64: 0 | G64: =Tabla3[[#This Row],[EGRESOS]]-Tabla3[[#This Row],[INGRESOS]] -> 0.67 | I64: 1450 | J64: =Tabla3[[#This Row],[EGRESOS]]/Tabla3[[#This Row],[TC]] -> 0.00046206897 | K64: =Tabla3[[#This Row],[INGRESOS]]/Tabla3[[#This Row],[TC]] -> 0 | L64: ARS | M64: CC | N64: NACION | O64: ADMINISTRACION | P64: GASTOS_BANC | Q64: IMPUESTOS | R64: TASA GENERAL | U64: 05. GASTOS_ADM | W64: 25/26
A65: ="FEBRERO" -> FEBRERO | B65: 46066 | C65: COM TRANSFE ELECTRONICA | E65: 956 | F65: 0 | G65: =Tabla3[[#This Row],[EGRESOS]]-Tabla3[[#This Row],[INGRESOS]] -> 956 | I65: 1450 | J65: =Tabla3[[#This Row],[EGRESOS]]/Tabla3[[#This Row],[TC]] -> 0.65931034 | K65: =Tabla3[[#This Row],[INGRESOS]]/Tabla3[[#This Row],[TC]] -> 0 | L65: ARS | M65: CC | N65: NACION | O65: ADMINISTRACION | P65: GASTOS_BANC | Q65: COMISIONES | U65: 05. GASTOS_ADM | W65: 25/26
A66: ="FEBRERO" -> FEBRERO | B66: 46066 | C66: I.V.A. BASE | E66: 200.76 | F66: 0 | G66: =Tabla3[[#This Row],[EGRESOS]]-Tabla3[[#This Row],[INGRESOS]] -> 200.76 | I66: 1450 | J66: =Tabla3[[#This Row],[EGRESOS]]/Tabla3[[#This Row],[TC]] -> 0.13845517 | K66: =Tabla3[[#This Row],[INGRESOS]]/Tabla3[[#This Row],[TC]] -> 0 | L66: ARS | M66: CC | N66: NACION | O66: ADMINISTRACION | P66: GASTOS_BANC | Q66: IMPUESTOS | R66: DEBITO IVA FISCAL | U66: 05. GASTOS_ADM | W66: 25/26
A67: ="FEBRERO" -> FEBRERO | B67: 46066 | C67: GRAVAMEN LEY 25413 S/DEB | E67: 5.74 | F67: 0 | G67: =Tabla3[[#This Row],[EGRESOS]]-Tabla3[[#This Row],[INGRESOS]] -> 5.74 | I67: 1450 | J67: =Tabla3[[#This Row],[EGRESOS]]/Tabla3[[#This Row],[TC]] -> 0.0039586207 | K67: =Tabla3[[#This Row],[INGRESOS]]/Tabla3[[#This Row],[TC]] -> 0 | L67: ARS | M67: CC | N67: NACION | O67: ADMINISTRACION | P67: GASTOS_BANC | Q67: IMPUESTOS | R67: TASA GENERAL | U67: 05. GASTOS_ADM | W67: 25/26
A68: ="FEBRERO" -> FEBRERO | B68: 46066 | C68: GRAVAMEN LEY 25413 S/DEB | E68: 1.2 | F68: 0 | G68: =Tabla3[[#This Row],[EGRESOS]]-Tabla3[[#This Row],[INGRESOS]] -> 1.2 | H68: -2990446.1 | I68: 1450 | J68: =Tabla3[[#This Row],[EGRESOS]]/Tabla3[[#This Row],[TC]] -> 0.00082758621 | K68: =Tabla3[[#This Row],[INGRESOS]]/Tabla3[[#This Row],[TC]] -> 0 | L68: ARS | M68: CC | N68: NACION | O68: ADMINISTRACION | P68: GASTOS_BANC | Q68: IMPUESTOS | R68: TASA GENERAL | U68: 05. GASTOS_ADM | W68: 25/26
A69: ="ENERO" -> ENERO | B69: 46035 | C69: DATANET EXENTO - 07089208823-G & E SA | E69: 0 | F69: 1500000 | G69: =Tabla3[[#This Row],[EGRESOS]]-Tabla3[[#This Row],[INGRESOS]] -> -1500000 | H69: -8735867.6 | I69: 1450 | J69: =Tabla3[[#This Row],[EGRESOS]]/Tabla3[[#This Row],[TC]] -> 0 | K69: =Tabla3[[#This Row],[INGRESOS]]/Tabla3[[#This Row],[TC]] -> 1034.4828 | L69: ARS | M69: CC | N69: PAMPA | O69: FINANCIERA | P69: INTERBANKING | Q69: TRANSF. PROPIAS | R69: DESDE CC MACRO | U69: 06. COMPENSATORIOS | W69: 24/25
A70: ="ENERO" -> ENERO | B70: 46037 | C70: DATANET EXENTO - 07089208823-G & E SA | E70: 0 | F70: 20000000 | G70: =Tabla3[[#This Row],[EGRESOS]]-Tabla3[[#This Row],[INGRESOS]] -> -20000000 | H70: 203836.75 | I70: 1450 | J70: =Tabla3[[#This Row],[EGRESOS]]/Tabla3[[#This Row],[TC]] -> 0 | K70: =Tabla3[[#This Row],[INGRESOS]]/Tabla3[[#This Row],[TC]] -> 13793.103 | L70: ARS | M70: CC | N70: PAMPA | O70: FINANCIERA | P70: INTERBANKING | Q70: TRANSF. PROPIAS | R70: DESDE CC MACRO | U70: 06. COMPENSATORIOS | W70: 24/25
A71: ="ENERO" -> ENERO | B71: 46053 | C71: IVA PERCEPCION ALICUOTA REDUCIDA | E71: 7123.86 | F71: 0 | G71: =Tabla3[[#This Row],[EGRESOS]]-Tabla3[[#This Row],[INGRESOS]] -> 7123.86 | I71: 1450 | J71: =Tabla3[[#This Row],[EGRESOS]]/Tabla3[[#This Row],[TC]] -> 4.9130069 | K71: =Tabla3[[#This Row],[INGRESOS]]/Tabla3[[#This Row],[TC]] -> 0 | L71: ARS | M71: CC | N71: PAMPA | O71: ADMINISTRACION | P71: GASTOS_BANC | Q71: IMPUESTOS | R71: IVA PERCEPCION | U71: 05. GASTOS_ADM | W71: 25/26
A72: ="ENERO" -> ENERO | B72: 46053 | C72: IVA PERCEPCION ALICUOTA REDUCIDA | E72: 396.31 | F72: 0 | G72: =Tabla3[[#This Row],[EGRESOS]]-Tabla3[[#This Row],[INGRESOS]] -> 396.31 | I72: 1450 | J72: =Tabla3[[#This Row],[EGRESOS]]/Tabla3[[#This Row],[TC]] -> 0.27331724 | K72: =Tabla3[[#This Row],[INGRESOS]]/Tabla3[[#This Row],[TC]] -> 0 | L72: ARS | M72: CC | N72: PAMPA | O72: ADMINISTRACION | P72: GASTOS_BANC | Q72: IMPUESTOS | R72: IVA PERCEPCION | U72: 05. GASTOS_ADM | W72: 25/26
A73: ="ENERO" -> ENERO | B73: 46053 | C73: IVA PERCEPCION ALICUOTA REDUCIDA | E73: 198.15 | F73: 0 | G73: =Tabla3[[#This Row],[EGRESOS]]-Tabla3[[#This Row],[INGRESOS]] -> 198.15 | I73: 1450 | J73: =Tabla3[[#This Row],[EGRESOS]]/Tabla3[[#This Row],[TC]] -> 0.13665517 | K73: =Tabla3[[#This Row],[INGRESOS]]/Tabla3[[#This Row],[TC]] -> 0 | L73: ARS | M73: CC | N73: PAMPA | O73: ADMINISTRACION | P73: GASTOS_BANC | Q73: IMPUESTOS | R73: IVA PERCEPCION | U73: 05. GASTOS_ADM | W73: 25/26
A74: ="ENERO" -> ENERO | B74: 46053 | C74: INTERESES ACUERDO SALDO DEUDOR | E74: 474923.92 | F74: 0 | G74: =Tabla3[[#This Row],[EGRESOS]]-Tabla3[[#This Row],[INGRESOS]] -> 474923.92 | I74: 1450 | J74: =Tabla3[[#This Row],[EGRESOS]]/Tabla3[[#This Row],[TC]] -> 327.53374 | K74: =Tabla3[[#This Row],[INGRESOS]]/Tabla3[[#This Row],[TC]] -> 0 | L74: ARS | M74: CC | N74: PAMPA | O74: ADMINISTRACION | P74: GASTOS_FIN | Q74: INTERESES | U74: 05. GASTOS_ADM | W74: 25/26
A75: ="ENERO" -> ENERO | B75: 46053 | C75: IMP. DEBITOS Y CRED. POR DEBITO | E75: 3888.01 | F75: 0 | G75: =Tabla3[[#This Row],[EGRESOS]]-Tabla3[[#This Row],[INGRESOS]] -> 3888.01 | I75: 1450 | J75: =Tabla3[[#This Row],[EGRESOS]]/Tabla3[[#This Row],[TC]] -> 2.6813862 | K75: =Tabla3[[#This Row],[INGRESOS]]/Tabla3[[#This Row],[TC]] -> 0 | L75: ARS | M75: CC | N75: PAMPA | O75: ADMINISTRACION | P75: GASTOS_BANC | Q75: IMPUESTOS | R75: DEBITO IVA FISCAL | U75: 05. GASTOS_ADM | W75: 25/26
A76: ="ENERO" -> ENERO | B76: 46053 | C76: IVA 10,5% | E76: 49867.01 | F76: 0 | G76: =Tabla3[[#This Row],[EGRESOS]]-Tabla3[[#This Row],[INGRESOS]] -> 49867.01 | I76: 1450 | J76: =Tabla3[[#This Row],[EGRESOS]]/Tabla3[[#This Row],[TC]] -> 34.391041 | K76: =Tabla3[[#This Row],[INGRESOS]]/Tabla3[[#This Row],[TC]] -> 0 | L76: ARS | M76: CC | N76: PAMPA | O76: ADMINISTRACION | P76: GASTOS_BANC | Q76: IMPUESTOS | R76: DEBITO IVA FISCAL | U76: 05. GASTOS_ADM | W76: 25/26
A77: ="ENERO" -> ENERO | B77: 46053 | C77: IVA 10,5% | E77: 2774.14 | F77: 0 | G77: =Tabla3[[#This Row],[EGRESOS]]-Tabla3[[#This Row],[INGRESOS]] -> 2774.14 | I77: 1450 | J77: =Tabla3[[#This Row],[EGRESOS]]/Tabla3[[#This Row],[TC]] -> 1.9132 | K77: =Tabla3[[#This Row],[INGRESOS]]/Tabla3[[#This Row],[TC]] -> 0 | L77: ARS | M77: CC | N77: PAMPA | O77: ADMINISTRACION | P77: GASTOS_BANC | Q77: IMPUESTOS | R77: DEBITO IVA FISCAL | U77: 05. GASTOS_ADM | W77: 25/26
A78: ="ENERO" -> ENERO | B78: 46053 | C78: IVA 10,5% | E78: 1387.07 | F78: 0 | G78: =Tabla3[[#This Row],[EGRESOS]]-Tabla3[[#This Row],[INGRESOS]] -> 1387.07 | I78: 1450 | J78: =Tabla3[[#This Row],[EGRESOS]]/Tabla3[[#This Row],[TC]] -> 0.9566 | K78: =Tabla3[[#This Row],[INGRESOS]]/Tabla3[[#This Row],[TC]] -> 0 | L78: ARS | M78: CC | N78: PAMPA | O78: ADMINISTRACION | P78: GASTOS_BANC | Q78: IMPUESTOS | R78: DEBITO IVA FISCAL | U78: 05. GASTOS_ADM | W78: 25/26
A79: ="ENERO" -> ENERO | B79: 46053 | C79: INTERESES EXCESO DESCUBIERTO | E79: 13210.2 | F79: 0 | G79: =Tabla3[[#This Row],[EGRESOS]]-Tabla3[[#This Row],[INGRESOS]] -> 13210.2 | I79: 1450 | J79: =Tabla3[[#This Row],[EGRESOS]]/Tabla3[[#This Row],[TC]] -> 9.1104828 | K79: =Tabla3[[#This Row],[INGRESOS]]/Tabla3[[#This Row],[TC]] -> 0 | L79: ARS | M79: CC | N79: PAMPA | O79: ADMINISTRACION | P79: GASTOS_FIN | Q79: INTERESES | U79: 05. GASTOS_ADM | W79: 25/26
A80: ="ENERO" -> ENERO | B80: 46053 | C80: IVA | E80: 10500 | F80: 0 | G80: =Tabla3[[#This Row],[EGRESOS]]-Tabla3[[#This Row],[INGRESOS]] -> 10500 | I80: 1450 | J80: =Tabla3[[#This Row],[EGRESOS]]/Tabla3[[#This Row],[TC]] -> 7.2413793 | K80: =Tabla3[[#This Row],[INGRESOS]]/Tabla3[[#This Row],[TC]] -> 0 | L80: ARS | M80: CC | N80: PAMPA | O80: ADMINISTRACION | P80: GASTOS_BANC | Q80: IMPUESTOS | R80: DEBITO IVA FISCAL | U80: 05. GASTOS_ADM | W80: 25/26
A81: ="ENERO" -> ENERO | B81: 46053 | C81: INTERESES DESCUBIERTO | E81: 26420.4 | F81: 0 | G81: =Tabla3[[#This Row],[EGRESOS]]-Tabla3[[#This Row],[INGRESOS]] -> 26420.4 | I81: 1450 | J81: =Tabla3[[#This Row],[EGRESOS]]/Tabla3[[#This Row],[TC]] -> 18.220966 | K81: =Tabla3[[#This Row],[INGRESOS]]/Tabla3[[#This Row],[TC]] -> 0 | L81: ARS | M81: CC | N81: PAMPA | O81: ADMINISTRACION | P81: GASTOS_FIN | Q81: INTERESES | U81: 05. GASTOS_ADM | W81: 25/26
A82: ="ENERO" -> ENERO | B82: 46053 | C82: IMPUESTO DE SELLOS | E82: 9192.08 | F82: 0 | G82: =Tabla3[[#This Row],[EGRESOS]]-Tabla3[[#This Row],[INGRESOS]] -> 9192.08 | I82: 1450 | J82: =Tabla3[[#This Row],[EGRESOS]]/Tabla3[[#This Row],[TC]] -> 6.3393655 | K82: =Tabla3[[#This Row],[INGRESOS]]/Tabla3[[#This Row],[TC]] -> 0 | L82: ARS | M82: CC | N82: PAMPA | O82: ADMINISTRACION | P82: GASTOS_BANC | Q82: IMPUESTOS | R82: SELLOS | U82: 05. GASTOS_ADM | W82: 25/26
A83: ="ENERO" -> ENERO | B83: 46053 | C83: IMPUESTO DE SELLOS | E83: 511.36 | F83: 0 | G83: =Tabla3[[#This Row],[EGRESOS]]-Tabla3[[#This Row],[INGRESOS]] -> 511.36 | I83: 1450 | J83: =Tabla3[[#This Row],[EGRESOS]]/Tabla3[[#This Row],[TC]] -> 0.35266207 | K83: =Tabla3[[#This Row],[INGRESOS]]/Tabla3[[#This Row],[TC]] -> 0 | L83: ARS | M83: CC | N83: PAMPA | O83: ADMINISTRACION | P83: GASTOS_BANC | Q83: IMPUESTOS | R83: SELLOS | U83: 05. GASTOS_ADM | W83: 25/26
A84: ="ENERO" -> ENERO | B84: 46053 | C84: COM. MANTENIMIENTO DE CUENTA | E84: 50000 | F84: 0 | G84: =Tabla3[[#This Row],[EGRESOS]]-Tabla3[[#This Row],[INGRESOS]] -> 50000 | I84: 1450 | J84: =Tabla3[[#This Row],[EGRESOS]]/Tabla3[[#This Row],[TC]] -> 34.482759 | K84: =Tabla3[[#This Row],[INGRESOS]]/Tabla3[[#This Row],[TC]] -> 0 | L84: ARS | M84: CC | N84: PAMPA | O84: ADMINISTRACION | P84: GASTOS_BANC | Q84: COMISIONES | U84: 05. GASTOS_ADM | W84: 25/26
A85: ="ENERO" -> ENERO | B85: 46053 | C85: IVA PERCEPCION | E85: 1500 | F85: 0 | G85: =Tabla3[[#This Row],[EGRESOS]]-Tabla3[[#This Row],[INGRESOS]] -> 1500 | H85: -448055.76 | I85: 1450 | J85: =Tabla3[[#This Row],[EGRESOS]]/Tabla3[[#This Row],[TC]] -> 1.0344828 | K85: =Tabla3[[#This Row],[INGRESOS]]/Tabla3[[#This Row],[TC]] -> 0 | L85: ARS | M85: CC | N85: PAMPA | O85: ADMINISTRACION | P85: GASTOS_BANC | Q85: IMPUESTOS | R85: IVA PERCEPCION | U85: 05. GASTOS_ADM | W85: 25/26
A86: ="FEBRERO" -> FEBRERO | B86: 46059 | C86: IMP. DEBITOS Y CRED. POR DEBITO | E86: 223.2 | F86: 0 | G86: =Tabla3[[#This Row],[EGRESOS]]-Tabla3[[#This Row],[INGRESOS]] -> 223.2 | I86: 1450 | J86: =Tabla3[[#This Row],[EGRESOS]]/Tabla3[[#This Row],[TC]] -> 0.15393103 | K86: =Tabla3[[#This Row],[INGRESOS]]/Tabla3[[#This Row],[TC]] -> 0 | L86: ARS | M86: CC | N86: PAMPA | O86: ADMINISTRACION | P86: GASTOS_BANC | Q86: IMPUESTOS | R86: DEBITO IVA FISCAL | U86: 05. GASTOS_ADM | W86: 25/26
A87: ="FEBRERO" -> FEBRERO | B87: 46059 | C87: IVA | E87: 6300 | F87: 0 | G87: =Tabla3[[#This Row],[EGRESOS]]-Tabla3[[#This Row],[INGRESOS]] -> 6300 | I87: 1450 | J87: =Tabla3[[#This Row],[EGRESOS]]/Tabla3[[#This Row],[TC]] -> 4.3448276 | K87: =Tabla3[[#This Row],[INGRESOS]]/Tabla3[[#This Row],[TC]] -> 0 | L87: ARS | M87: CC | N87: PAMPA | O87: ADMINISTRACION | P87: GASTOS_BANC | Q87: IMPUESTOS | R87: DEBITO IVA FISCAL | U87: 05. GASTOS_ADM | W87: 25/26
A88: ="FEBRERO" -> FEBRERO | B88: 46059 | C88: CHEQUERA | E88: 30000 | F88: 0 | G88: =Tabla3[[#This Row],[EGRESOS]]-Tabla3[[#This Row],[INGRESOS]] -> 30000 | I88: 1450 | J88: =Tabla3[[#This Row],[EGRESOS]]/Tabla3[[#This Row],[TC]] -> 20.689655 | K88: =Tabla3[[#This Row],[INGRESOS]]/Tabla3[[#This Row],[TC]] -> 0 | L88: ARS | M88: CC | N88: PAMPA | O88: ADMINISTRACION | P88: GASTOS_BANC | Q88: COMISIONES | U88: 05. GASTOS_ADM | W88: 25/26
A89: ="FEBRERO" -> FEBRERO | B89: 46059 | C89: IVA PERCEPCION | E89: 900 | F89: 0 | G89: =Tabla3[[#This Row],[EGRESOS]]-Tabla3[[#This Row],[INGRESOS]] -> 900 | I89: 1450 | J89: =Tabla3[[#This Row],[EGRESOS]]/Tabla3[[#This Row],[TC]] -> 0.62068966 | K89: =Tabla3[[#This Row],[INGRESOS]]/Tabla3[[#This Row],[TC]] -> 0 | L89: ARS | M89: CC | N89: PAMPA | O89: ADMINISTRACION | P89: GASTOS_BANC | Q89: IMPUESTOS | R89: PERCEPCION IVA | U89: 05. GASTOS_ADM | W89: 25/26
A90: ="FEBRERO" -> FEBRERO | B90: 46062 | C90: IMP. DEBITOS Y CRED. POR DEBITO | E90: 54.31 | F90: 0 | G90: =Tabla3[[#This Row],[EGRESOS]]-Tabla3[[#This Row],[INGRESOS]] -> 54.31 | I90: 1450 | J90: =Tabla3[[#This Row],[EGRESOS]]/Tabla3[[#This Row],[TC]] -> 0.037455172 | K90: =Tabla3[[#This Row],[INGRESOS]]/Tabla3[[#This Row],[TC]] -> 0 | L90: ARS | M90: CC | N90: PAMPA | O90: ADMINISTRACION | P90: GASTOS_BANC | Q90: IMPUESTOS | R90: DEBITO IVA FISCAL | U90: 05. GASTOS_ADM | W90: 25/26
A91: ="FEBRERO" -> FEBRERO | B91: 46062 | C91: TRANSF. PROPIA ENVIADA PD - 30708920882-G & E S.A. | E91: 19500000 | F91: 0 | G91: =Tabla3[[#This Row],[EGRESOS]]-Tabla3[[#This Row],[INGRESOS]] -> 19500000 | I91: 1450 | J91: =Tabla3[[#This Row],[EGRESOS]]/Tabla3[[#This Row],[TC]] -> 13448.276 | K91: =Tabla3[[#This Row],[INGRESOS]]/Tabla3[[#This Row],[TC]] -> 0 | L91: ARS | M91: CC | N91: PAMPA | O91: FINANCIERA | P91: INTERBANKING | Q91: TRANSF. PROPIAS | R91: HACIA CC NACION | U91: 06. COMPENSATORIOS | W91: 24/25
A92: ="FEBRERO" -> FEBRERO | B92: 46062 | C92: COM. TRANSF. PAMPA DIGITAL | E92: 7300 | F92: 0 | G92: =Tabla3[[#This Row],[EGRESOS]]-Tabla3[[#This Row],[INGRESOS]] -> 7300 | I92: 1450 | J92: =Tabla3[[#This Row],[EGRESOS]]/Tabla3[[#This Row],[TC]] -> 5.0344828 | K92: =Tabla3[[#This Row],[INGRESOS]]/Tabla3[[#This Row],[TC]] -> 0 | L92: ARS | M92: CC | N92: PAMPA | O92: ADMINISTRACION | P92: GASTOS_BANC | Q92: COMISIONES | U92: 05. GASTOS_ADM | W92: 25/26
A93: ="FEBRERO" -> FEBRERO | B93: 46062 | C93: IVA | E93: 1533 | F93: 0 | G93: =Tabla3[[#This Row],[EGRESOS]]-Tabla3[[#This Row],[INGRESOS]] -> 1533 | I93: 1450 | J93: =Tabla3[[#This Row],[EGRESOS]]/Tabla3[[#This Row],[TC]] -> 1.0572414 | K93: =Tabla3[[#This Row],[INGRESOS]]/Tabla3[[#This Row],[TC]] -> 0 | L93: ARS | M93: CC | N93: PAMPA | O93: ADMINISTRACION | P93: GASTOS_BANC | Q93: IMPUESTOS | R93: DEBITO IVA FISCAL | U93: 05. GASTOS_ADM | W93: 25/26
A94: ="FEBRERO" -> FEBRERO | B94: 46062 | C94: IVA PERCEPCION | E94: 219 | F94: 0 | G94: =Tabla3[[#This Row],[EGRESOS]]-Tabla3[[#This Row],[INGRESOS]] -> 219 | H94: -19994585 | I94: 1450 | J94: =Tabla3[[#This Row],[EGRESOS]]/Tabla3[[#This Row],[TC]] -> 0.15103448 | K94: =Tabla3[[#This Row],[INGRESOS]]/Tabla3[[#This Row],[TC]] -> 0 | L94: ARS | M94: CC | N94: PAMPA | O94: ADMINISTRACION | P94: GASTOS_BANC | Q94: IMPUESTOS | R94: PERCEPCION IVA | U94: 05. GASTOS_ADM | W94: 25/26
A95: ="FEBRERO" -> FEBRERO | B95: 46071 | C95: ACREDITACION PRESTAMO COMERCIAL | E95: 0 | F95: 29496000 | G95: =Tabla3[[#This Row],[EGRESOS]]-Tabla3[[#This Row],[INGRESOS]] -> -29496000 | I95: 1450 | J95: =Tabla3[[#This Row],[EGRESOS]]/Tabla3[[#This Row],[TC]] -> 0 | K95: =Tabla3[[#This Row],[INGRESOS]]/Tabla3[[#This Row],[TC]] -> 20342.069 | L95: ARS | M95: CC | N95: PAMPA | O95: FINANCIERA | P95: CREDITOS | Q95: 6 MESES | R95: PAMPA | S95: PAMPA | U95: 19. CANCELACION CREDITO PAMPA | W95: 25/26
A96: ="FEBRERO" -> FEBRERO | B96: 46072 | C96: IMP. DEBITOS Y CRED. POR DEBITO | E96: 7073.91 | F96: 0 | G96: =Tabla3[[#This Row],[EGRESOS]]-Tabla3[[#This Row],[INGRESOS]] -> 7073.91 | I96: 1450 | J96: =Tabla3[[#This Row],[EGRESOS]]/Tabla3[[#This Row],[TC]] -> 4.8785586 | K96: =Tabla3[[#This Row],[INGRESOS]]/Tabla3[[#This Row],[TC]] -> 0 | L96: ARS | M96: CC | N96: PAMPA | O96: ADMINISTRACION | P96: GASTOS_BANC | Q96: IMPUESTOS | R96: DEBITO IVA FISCAL | U96: 05. GASTOS_ADM | W96: 25/26
A97: ="FEBRERO" -> FEBRERO | B97: 46072 | C97: TRANSF. PROPIA ENVIADA PD - 30708920882-G & E S.A. | E97: 2000000 | F97: 0 | G97: =Tabla3[[#This Row],[EGRESOS]]-Tabla3[[#This Row],[INGRESOS]] -> 2000000 | I97: 1450 | J97: =Tabla3[[#This Row],[EGRESOS]]/Tabla3[[#This Row],[TC]] -> 1379.3103 | K97: =Tabla3[[#This Row],[INGRESOS]]/Tabla3[[#This Row],[TC]] -> 0 | L97: ARS | M97: CC | N97: PAMPA | O97: FINANCIERA | P97: INTERBANKING | Q97: TRANSF. PROPIAS | R97: HACIA CC MACRO | U97: 06. COMPENSATORIOS | W97: 25/26
A98: ="FEBRERO" -> FEBRERO | B98: 46072 | C98: TRANSF. ENVIADA PAMPA DIGITAL - 20170457715-BECERRA ADRIAN OSCAR | E98: 1178985 | F98: 0 | G98: =Tabla3[[#This Row],[EGRESOS]]-Tabla3[[#This Row],[INGRESOS]] -> 1178985 | H98: 6315355.8 | I98: 1450 | J98: =Tabla3[[#This Row],[EGRESOS]]/Tabla3[[#This Row],[TC]] -> 813.0931 | K98: =Tabla3[[#This Row],[INGRESOS]]/Tabla3[[#This Row],[TC]] -> 0 | L98: ARS | M98: CC | N98: PAMPA | O98: ADMINISTRACION | P98: TERCEROS | Q98: DEVOLUCION | S98: ADRIAN BECERRA | U98: 20. TERCEROS | W98: 25/26
A99: ="FEBRERO" -> FEBRERO | B99: 46073 | C99: IMP. DEBITOS Y CRED. POR DEBITO | E99: 19338 | F99: 0 | G99: =Tabla3[[#This Row],[EGRESOS]]-Tabla3[[#This Row],[INGRESOS]] -> 19338 | I99: 1450 | J99: =Tabla3[[#This Row],[EGRESOS]]/Tabla3[[#This Row],[TC]] -> 13.336552 | K99: =Tabla3[[#This Row],[INGRESOS]]/Tabla3[[#This Row],[TC]] -> 0 | L99: ARS | M99: CC | N99: PAMPA | O99: ADMINISTRACION | P99: GASTOS_BANC | Q99: IMPUESTOS | R99: DEBITO IVA FISCAL | U99: 05. GASTOS_ADM | W99: 25/26
A100: ="FEBRERO" -> FEBRERO | B100: 46073 | C100: TRANSF. ENVIADA PAMPA DIGITAL - 20164045693-ERRECALDE RAUL ALBERTO | E100: 1510000 | F100: 0 | G100: =Tabla3[[#This Row],[EGRESOS]]-Tabla3[[#This Row],[INGRESOS]] -> 1510000 | I100: 1450 | J100: =Tabla3[[#This Row],[EGRESOS]]/Tabla3[[#This Row],[TC]] -> 1041.3793 | K100: =Tabla3[[#This Row],[INGRESOS]]/Tabla3[[#This Row],[TC]] -> 0 | L100: ARS | M100: CC | N100: PAMPA | O100: ADMINISTRACION | P100: SOCIOS | Q100: DEVOLUCION | S100: RAUL ERRECALDE | U100: 15. APORTE SOCIO RAUL | V100: RAUL | W100: 25/26
...

Sheet RDOS
B1: ASIGNACIONES RESULTADOS 2026
B2: RESULTADO ANUAL
B3: Suma de EGRESOS | C3: Etiquetas de columna | L3: Suma de INGRESOS | M3: Etiquetas de columna
B4: Etiquetas de fila | C4: ADMINISTRACION | D4: AGRICULTURA | E4: ESTRUCTURA | F4: FINANCIERA | G4: GANADERIA | H4: Total general | L4: Etiquetas de fila | M4: ADMINISTRACION | N4: AGRICULTURA | O4: ESTRUCTURA | P4: FINANCIERA | Q4: GANADERIA | R4: Total general
B5: ENERO | C5: 19437064 | D5: 7022574.9 | E5: 6368450 | F5: 38523424 | G5: 4078511.7 | H5: 75430024 | L5: ENERO | M5: 2652487.5 | N5: 64686741 | O5: 0 | P5: 36702718 | Q5: 0 | R5: 1.0404195e+08
B6: 01. FACT PAGADAS 25 | D6: 2469057.2 | E6: 750000 | H6: 3219057.2 | L6: 01. FACT PAGADAS 25 | N6: 0 | O6: 0 | R6: 0
B7: 02. FACT PAGADAS 26 | D7: 4553517.7 | E7: 5356450 | G7: 4078511.7 | H7: 13988479 | L7: 02. FACT PAGADAS 26 | N7: 0 | O7: 0 | Q7: 0 | R7: 0
B8: 05. GASTOS_ADM | C8: 2381820.1 | E8: 209000 | H8: 2590820.1 | L8: 05. GASTOS_ADM | M8: 66987.53 | O8: 0 | R8: 66987.53
B9: 06. COMPENSATORIOS | F9: 36702718 | H9: 36702718 | L9: 06. COMPENSATORIOS | P9: 36702718 | R9: 36702718
B10: 07. GASTOS_ESTRUCTURA | C10: 26724 | E10: 35000 | H10: 61724 | L10: 07. GASTOS_ESTRUCTURA | M10: 0 | O10: 0 | R10: 0
B11: 08. FLETES | E11: 18000 | H11: 18000 | L11: 08. FLETES | O11: 0 | R11: 0
B12: 10. SUELDOS Y JORNALES | C12: 6164361.5 | H12: 6164361.5 | L12: 10. SUELDOS Y JORNALES | M12: 0 | R12: 0
B13: 12. UTILIDADES CLAUDIA | C13: 2588000 | H13: 2588000 | L13: 12. UTILIDADES CLAUDIA | M13: 0 | R13: 0
B14: 13. UTILIDADES ADL MONICA | C14: 2000000 | H14: 2000000 | L14: 13. UTILIDADES ADL MONICA | M14: 0 | R14: 0
B15: 14. A CTA DE HONORARIOS RAUL | C15: 2795658 | H15: 2795658 | L15: 14. A CTA DE HONORARIOS RAUL | M15: 0 | R15: 0
B16: 15. APORTE SOCIO RAUL | C16: 0 | H16: 0 | L16: 15. APORTE SOCIO RAUL | M16: 135000 | R16: 135000
B17: 16. INGRESOS AGROPECUARIOS | D17: 0 | H17: 0 | L17: 16. INGRESOS AGROPECUARIOS | N17: 64686741 | R17: 64686741
B18: 18. CANC CREDITO GALICIA | F18: 1820705.5 | H18: 1820705.5 | L18: 18. CANC CREDITO GALICIA | P18: 0 | R18: 0
B19: 20. TERCEROS | C19: 3480500 | H19: 3480500 | L19: 20. TERCEROS | M19: 2450500 | R19: 2450500
B20: FEBRERO | C20: 19123431 | D20: 10589919 | E20: 7149598.7 | F20: 1.1998922e+08 | G20: 1370600 | H20: 1.5822276e+08 | L20: FEBRERO | M20: 3784765 | N20: 702900 | O20: 0 | P20: 1.2099917e+08 | Q20: 0 | R20: 1.2548684e+08
B21: 01. FACT PAGADAS 25 | D21: 10000000 | E21: 2164212 | H21: 12164212 | L21: 01. FACT PAGADAS 25 | N21: 0 | O21: 0 | R21: 0
B22: 02. FACT PAGADAS 26 | C22: 100000 | D22: 589918.56 | E22: 4605386.7 | G22: 1370600 | H22: 6665905.3 | L22: 02. FACT PAGADAS 26 | M22: 0 | N22: 0 | O22: 0 | Q22: 0 | R22: 0
B23: 04. CREDITOS | F23: 0 | H23: 0 | L23: 04. CREDITOS | P23: 28420000 | R23: 28420000
B24: 05. GASTOS_ADM | C24: 2126880.4 | H24: 2126880.4 | L24: 05. GASTOS_ADM | M24: 0 | R24: 0
B25: 06. COMPENSATORIOS | F25: 63083174 | H25: 63083174 | L25: 06. COMPENSATORIOS | P25: 63083174 | R25: 63083174
B26: 08. FLETES | E26: 380000 | H26: 380000 | L26: 08. FLETES | O26: 0 | R26: 0
B27: 09. SERVICIOS SOCIALES | C27: 30000 | H27: 30000 | L27: 09. SERVICIOS SOCIALES | M27: 0 | R27: 0
B28: 10. SUELDOS Y JORNALES | C28: 3381498.2 | H28: 3381498.2 | L28: 10. SUELDOS Y JORNALES | M28: 0 | R28: 0
B29: 12. UTILIDADES CLAUDIA | C29: 8213000 | H29: 8213000 | L29: 12. UTILIDADES CLAUDIA | M29: 0 | R29: 0
B30: 13. UTILIDADES ADL MONICA | C30: 1000000 | H30: 1000000 | L30: 13. UTILIDADES ADL MONICA | M30: 0 | R30: 0
B31: 14. A CTA DE HONORARIOS RAUL | C31: 1583067 | H31: 1583067 | L31: 14. A CTA DE HONORARIOS RAUL | M31: 0 | R31: 0
B32: 15. APORTE SOCIO RAUL | C32: 1510000 | H32: 1510000 | L32: 15. APORTE SOCIO RAUL | M32: 1510000 | R32: 1510000
B33: 16. INGRESOS AGROPECUARIOS | D33: 0 | H33: 0 | L33: 16. INGRESOS AGROPECUARIOS | N33: 702900 | R33: 702900
B34: 17. CANC CREDITO SGR | F34: 55095708 | H34: 55095708 | L34: 17. CANC CREDITO SGR | P34: 0 | R34: 0
B35: 18. CANC CREDITO GALICIA | F35: 1810333.6 | H35: 1810333.6 | L35: 18. CANC CREDITO GALICIA | P35: 0 | R35: 0
B36: 19. CANCELACION CREDITO PAMPA | F36: 0 | H36: 0 | L36: 19. CANCELACION CREDITO PAMPA | P36: 29496000 | R36: 29496000
B37: 20. TERCEROS | C37: 1178985 | H37: 1178985 | L37: 20. TERCEROS | M37: 2274765 | R37: 2274765
B38: Total general | C38: 38560494 | D38: 17612493 | E38: 13518049 | F38: 1.5851264e+08 | G38: 5449111.7 | H38: 2.3365279e+08 | L38: Total general | M38: 6437252.5 | N38: 65389641 | O38: 0 | P38: 1.5770189e+08 | Q38: 0 | R38: 2.2952879e+08

Sheet CAPITAL
B1: IMPUTACION DE MONTOS DE LAS ACTIVIDADES PRODUCTIVAS 2025
B15: ACTIVIDADES | C15: ENERO | D15: FEBRERO | E15: MARZO | F15: ABRIL | G15: MAYO | H15: JUNIO | I15: JULIO | J15: AGOSTO | K15: SEPTIEMBRE | L15: OCTUBRE | M15: NOVIEMBRE | N15: DICIEMBRE | O15: TOTAL
B16: INGRESOS | C16: =C17+C21 -> 135000 | D16: =D17+D21 -> 2710000 | E16: =E17+E21 -> 0 | F16: =F17+F21 -> 0 | G16: =G17+G21 -> 0 | H16: =H17+H21 -> 0 | I16: =I17+I21 -> 0 | J16: =J17+J21 -> 0 | ... N16: =N17+N21 -> 0 | O16: =SUM(O17:O33) -> 18879725
B17: SOCIOS | C17: =SUM(C18:C20) -> 135000 | D17: =SUM(D18:D20) -> 1510000 | E17: =SUM(E18:E20) -> 0 | F17: =SUM(F18:F20) -> 0 | G17: =SUM(G18:G20) -> 0 | H17: =SUM(H18:H20) -> 0 | I17: =SUM(I18:I20) -> 0 | J17: =SUM(J18:J20) -> 0 | ... N17: =SUM(N18:N20) -> 0 | O17: =SUM(Tabla45[[#This Row],[ENERO]:[DICIEMBRE]]) -> 1645000
B18: RAUL | C18: =SUMIFS(Tabla3[INGRESOS],Tabla3[SOCIO],Tabla45[[#This Row],[ACTIVIDADES]],Tabla3[PERIODO],Tabla45[[#Headers],[ENERO]]) -> 135000 | D18: =SUMIFS(Tabla3[INGRESOS],Tabla3[SOCIO],Tabla45[[#This Row],[ACTIVIDADES]],Tabla3[PERIODO],Tabla45[[#Headers],[FEBRERO]]) -> 1510000 | E18: =SUMIFS(Tabla3[INGRESOS],Tabla3[SOCIO],Tabla45[[#This Row],[ACTIVIDADES]],Tabla3[PERIODO],Tabla45[[#Headers],[MARZO]]) -> 0 | F18: =SUMIFS(Tabla3[INGRESOS],Tabla3[SOCIO],Tabla45[[#This Row],[ACTIVIDADES]],Tabla3[PERIODO],Tabla45[[#Headers],[ABRIL]]) -> 0 | G18: =SUMIFS(Tabla3[INGRESOS],Tabla3[SOCIO],Tabla45[[#This Row],[ACTIVIDADES]],Tabla3[PERIODO],Tabla45[[#Headers],[MAYO]]) -> 0 | H18: =SUMIFS(Tabla3[INGRESOS],Tabla3[SOCIO],Tabla45[[#This Row],[ACTIVIDADES]],Tabla3[PERIODO],Tabla45[[#Headers],[JUNIO]]) -> 0 | I18: =SUMIFS(Tabla3[INGRESOS],Tabla3[SOCIO],Tabla45[[#This Row],[ACTIVIDADES]],Tabla3[PERIODO],Tabla45[[#Headers],[JULIO]]) -> 0 | O18: =SUM(Tabla45[[#This Row],[ENERO]:[DICIEMBRE]]) -> 1645000
B19: CLAUDIA | C19: =SUMIFS(Tabla3[INGRESOS],Tabla3[SOCIO],Tabla45[[#This Row],[ACTIVIDADES]],Tabla3[PERIODO],Tabla45[[#Headers],[ENERO]]) -> 0 | D19: =SUMIFS(Tabla3[INGRESOS],Tabla3[SOCIO],Tabla45[[#This Row],[ACTIVIDADES]],Tabla3[PERIODO],Tabla45[[#Headers],[FEBRERO]]) -> 0 | E19: =SUMIFS(Tabla3[INGRESOS],Tabla3[SOCIO],Tabla45[[#This Row],[ACTIVIDADES]],Tabla3[PERIODO],Tabla45[[#Headers],[MARZO]]) -> 0 | F19: =SUMIFS(Tabla3[INGRESOS],Tabla3[SOCIO],Tabla45[[#This Row],[ACTIVIDADES]],Tabla3[PERIODO],Tabla45[[#Headers],[ABRIL]]) -> 0 | G19: =SUMIFS(Tabla3[INGRESOS],Tabla3[SOCIO],Tabla45[[#This Row],[ACTIVIDADES]],Tabla3[PERIODO],Tabla45[[#Headers],[MAYO]]) -> 0 | O19: =SUM(Tabla45[[#This Row],[ENERO]:[DICIEMBRE]]) -> 0
B20: MONICA | O20: =SUM(Tabla45[[#This Row],[ENERO]:[DICIEMBRE]]) -> 0
B21: TERCEROS | C21: =SUM(C22:C23) -> 0 | D21: =SUM(D22:D23) -> 1200000 | E21: =SUM(E22:E23) -> 0 | F21: =SUM(F22:F23) -> 0 | G21: =SUM(G22:G23) -> 0 | H21: =SUM(H22:H23) -> 0 | I21: =SUM(I22:I23) -> 0 | J21: =SUM(J22:J23) -> 0 | ... N21: =SUM(N22:N23) -> 0 | O21: =SUM(Tabla45[[#This Row],[ENERO]:[DICIEMBRE]]) -> 1200000
B22: SANTIAGO ERRECALDE | C22: =SUMIFS(Tabla3[INGRESOS],Tabla3[PROVEEDOR CLIENTE],Tabla45[[#This Row],[ACTIVIDADES]],Tabla3[PERIODO],Tabla45[[#Headers],[ENERO]]) -> 0 | D22: =SUMIFS(Tabla3[INGRESOS],Tabla3[PROVEEDOR CLIENTE],Tabla45[[#This Row],[ACTIVIDADES]],Tabla3[PERIODO],Tabla45[[#Headers],[FEBRERO]]) -> 1200000 | E22: =SUMIFS(Tabla3[INGRESOS],Tabla3[PROVEEDOR CLIENTE],Tabla45[[#This Row],[ACTIVIDADES]],Tabla3[PERIODO],Tabla45[[#Headers],[MARZO]]) -> 0 | F22: =SUMIFS(Tabla3[INGRESOS],Tabla3[PROVEEDOR CLIENTE],Tabla45[[#This Row],[ACTIVIDADES]],Tabla3[PERIODO],Tabla45[[#Headers],[ABRIL]]) -> 0 | G22: =SUMIFS(Tabla3[INGRESOS],Tabla3[PROVEEDOR CLIENTE],Tabla45[[#This Row],[ACTIVIDADES]],Tabla3[PERIODO],Tabla45[[#Headers],[MAYO]]) -> 0 | O22: =SUM(Tabla45[[#This Row],[ENERO]:[DICIEMBRE]]) -> 1200000
B23: BECERRA ADRIAN | C23: =SUMIFS(Tabla3[INGRESOS],Tabla3[PROVEEDOR CLIENTE],Tabla45[[#This Row],[ACTIVIDADES]],Tabla3[PERIODO],Tabla45[[#Headers],[ENERO]]) -> 0 | D23: =SUMIFS(Tabla3[INGRESOS],Tabla3[PROVEEDOR CLIENTE],Tabla45[[#This Row],[ACTIVIDADES]],Tabla3[PERIODO],Tabla45[[#Headers],[FEBRERO]]) -> 0 | E23: =SUMIFS(Tabla3[INGRESOS],Tabla3[PROVEEDOR CLIENTE],Tabla45[[#This Row],[ACTIVIDADES]],Tabla3[PERIODO],Tabla45[[#Headers],[MARZO]]) -> 0 | F23: =SUMIFS(Tabla3[INGRESOS],Tabla3[PROVEEDOR CLIENTE],Tabla45[[#This Row],[ACTIVIDADES]],Tabla3[PERIODO],Tabla45[[#Headers],[ABRIL]]) -> 0 | G23: =SUMIFS(Tabla3[INGRESOS],Tabla3[PROVEEDOR CLIENTE],Tabla45[[#This Row],[ACTIVIDADES]],Tabla3[PERIODO],Tabla45[[#Headers],[MAYO]]) -> 0 | O23: =SUM(Tabla45[[#This Row],[ENERO]:[DICIEMBRE]]) -> 0
O24: =SUM(Tabla45[[#This Row],[ENERO]:[DICIEMBRE]]) -> 0
B25: EGRESOS | C25: =-(+C26+C30) -> -7383658 | D25: =-(+D26+D30) -> -5806067 | E25: =-(+E26+E30) -> 0 | F25: =-(+F26+F30) -> 0 | G25: =-(+G26+G30) -> 0 | H25: =-(+H26+H30) -> 0 | I25: =-(+I26+I30) -> 0 | J25: =-(+J26+J30) -> 0 | ... N25: =-(+N26+N30) -> 0 | O25: =SUM(Tabla45[[#This Row],[ENERO]:[DICIEMBRE]]) -> -13189725
B26: SOCIOS | C26: =SUM(C27:C29) -> 7383658 | D26: =SUM(D27:D29) -> 5806067 | E26: =SUM(E27:E29) -> 0 | F26: =SUM(F27:F29) -> 0 | G26: =SUM(G27:G29) -> 0 | H26: =SUM(H27:H29) -> 0 | I26: =SUM(I27:I29) -> 0 | J26: =SUM(J27:J29) -> 0 | ... N26: =SUM(N27:N29) -> 0 | O26: =SUM(Tabla45[[#This Row],[ENERO]:[DICIEMBRE]]) -> 13189725
B27: RAUL | C27: =SUMIFS(Tabla3[EGRESOS],Tabla3[SOCIO],Tabla45[[#This Row],[ACTIVIDADES]],Tabla3[PERIODO],Tabla45[[#Headers],[ENERO]]) -> 2795658 | D27: =SUMIFS(Tabla3[EGRESOS],Tabla3[SOCIO],Tabla45[[#This Row],[ACTIVIDADES]],Tabla3[PERIODO],Tabla45[[#Headers],[FEBRERO]]) -> 3093067 | E27: =SUMIFS(Tabla3[EGRESOS],Tabla3[SOCIO],Tabla45[[#This Row],[ACTIVIDADES]],Tabla3[PERIODO],Tabla45[[#Headers],[MARZO]]) -> 0 | F27: =SUMIFS(Tabla3[EGRESOS],Tabla3[SOCIO],Tabla45[[#This Row],[ACTIVIDADES]],Tabla3[PERIODO],Tabla45[[#Headers],[ABRIL]]) -> 0 | G27: =SUMIFS(Tabla3[EGRESOS],Tabla3[SOCIO],Tabla45[[#This Row],[ACTIVIDADES]],Tabla3[PERIODO],Tabla45[[#Headers],[MAYO]]) -> 0 | H27: =SUMIFS(Tabla3[EGRESOS],Tabla3[SOCIO],Tabla45[[#This Row],[ACTIVIDADES]],Tabla3[PERIODO],Tabla45[[#Headers],[JUNIO]]) -> 0 | I27: =SUMIFS(Tabla3[EGRESOS],Tabla3[SOCIO],Tabla45[[#This Row],[ACTIVIDADES]],Tabla3[PERIODO],Tabla45[[#Headers],[JULIO]]) -> 0 | J27: =SUMIFS(Tabla3[EGRESOS],Tabla3[SOCIO],Tabla45[[#This Row],[ACTIVIDADES]],Tabla3[PERIODO],Tabla45[[#Headers],[AGOSTO]]) -> 0 | K27: =SUMIFS(Tabla3[EGRESOS],Tabla3[SOCIO],Tabla45[[#This Row],[ACTIVIDADES]],Tabla3[PERIODO],Tabla45[[#Headers],[SEPTIEMBRE]]) -> 0 | L27: =SUMIFS(Tabla3[EGRESOS],Tabla3[SOCIO],Tabla45[[#This Row],[ACTIVIDADES]],Tabla3[PERIODO],Tabla45[[#Headers],[OCTUBRE]]) -> 0 | M27: =SUMIFS(Tabla3[EGRESOS],Tabla3[SOCIO],Tabla45[[#This Row],[ACTIVIDADES]],Tabla3[PERIODO],Tabla45[[#Headers],[NOVIEMBRE]]) -> 0 | N27: =SUMIFS(Tabla3[EGRESOS],Tabla3[SOCIO],Tabla45[[#This Row],[ACTIVIDADES]],Tabla3[PERIODO],Tabla45[[#Headers],[DICIEMBRE]]) -> 0 | O27: =SUM(Tabla45[[#This Row],[ENERO]:[DICIEMBRE]]) -> 5888725
B28: CLAUDIA | C28: =SUMIFS(Tabla3[EGRESOS],Tabla3[SOCIO],Tabla45[[#This Row],[ACTIVIDADES]],Tabla3[PERIODO],Tabla45[[#Headers],[ENERO]]) -> 2588000 | D28: =SUMIFS(Tabla3[EGRESOS],Tabla3[SOCIO],Tabla45[[#This Row],[ACTIVIDADES]],Tabla3[PERIODO],Tabla45[[#Headers],[FEBRERO]]) -> 1713000 | E28: =SUMIFS(Tabla3[EGRESOS],Tabla3[SOCIO],Tabla45[[#This Row],[ACTIVIDADES]],Tabla3[PERIODO],Tabla45[[#Headers],[MARZO]]) -> 0 | F28: =SUMIFS(Tabla3[EGRESOS],Tabla3[SOCIO],Tabla45[[#This Row],[ACTIVIDADES]],Tabla3[PERIODO],Tabla45[[#Headers],[ABRIL]]) -> 0 | G28: =SUMIFS(Tabla3[EGRESOS],Tabla3[SOCIO],Tabla45[[#This Row],[ACTIVIDADES]],Tabla3[PERIODO],Tabla45[[#Headers],[MAYO]]) -> 0 | H28: =SUMIFS(Tabla3[EGRESOS],Tabla3[SOCIO],Tabla45[[#This Row],[ACTIVIDADES]],Tabla3[PERIODO],Tabla45[[#Headers],[JUNIO]]) -> 0 | I28: =SUMIFS(Tabla3[EGRESOS],Tabla3[SOCIO],Tabla45[[#This Row],[ACTIVIDADES]],Tabla3[PERIODO],Tabla45[[#Headers],[JULIO]]) -> 0 | J28: =SUMIFS(Tabla3[EGRESOS],Tabla3[SOCIO],Tabla45[[#This Row],[ACTIVIDADES]],Tabla3[PERIODO],Tabla45[[#Headers],[AGOSTO]]) -> 0 | K28: =SUMIFS(Tabla3[EGRESOS],Tabla3[SOCIO],Tabla45[[#This Row],[ACTIVIDADES]],Tabla3[PERIODO],Tabla45[[#Headers],[SEPTIEMBRE]]) -> 0 | L28: =SUMIFS(Tabla3[EGRESOS],Tabla3[SOCIO],Tabla45[[#This Row],[ACTIVIDADES]],Tabla3[PERIODO],Tabla45[[#Headers],[OCTUBRE]]) -> 0 | M28: =SUMIFS(Tabla3[EGRESOS],Tabla3[SOCIO],Tabla45[[#This Row],[ACTIVIDADES]],Tabla3[PERIODO],Tabla45[[#Headers],[NOVIEMBRE]]) -> 0 | N28: =SUMIFS(Tabla3[EGRESOS],Tabla3[SOCIO],Tabla45[[#This Row],[ACTIVIDADES]],Tabla3[PERIODO],Tabla45[[#Headers],[DICIEMBRE]]) -> 0 | O28: =SUM(Tabla45[[#This Row],[ENERO]:[DICIEMBRE]]) -> 4301000
B29: MONICA | C29: =SUMIFS(Tabla3[EGRESOS],Tabla3[SOCIO],Tabla45[[#This Row],[ACTIVIDADES]],Tabla3[PERIODO],Tabla45[[#Headers],[ENERO]]) -> 2000000 | D29: =SUMIFS(Tabla3[EGRESOS],Tabla3[SOCIO],Tabla45[[#This Row],[ACTIVIDADES]],Tabla3[PERIODO],Tabla45[[#Headers],[FEBRERO]]) -> 1000000 | E29: =SUMIFS(Tabla3[EGRESOS],Tabla3[SOCIO],Tabla45[[#This Row],[ACTIVIDADES]],Tabla3[PERIODO],Tabla45[[#Headers],[MARZO]]) -> 0 | F29: =SUMIFS(Tabla3[EGRESOS],Tabla3[SOCIO],Tabla45[[#This Row],[ACTIVIDADES]],Tabla3[PERIODO],Tabla45[[#Headers],[ABRIL]]) -> 0 | G29: =SUMIFS(Tabla3[EGRESOS],Tabla3[SOCIO],Tabla45[[#This Row],[ACTIVIDADES]],Tabla3[PERIODO],Tabla45[[#Headers],[MAYO]]) -> 0 | H29: =SUMIFS(Tabla3[EGRESOS],Tabla3[SOCIO],Tabla45[[#This Row],[ACTIVIDADES]],Tabla3[PERIODO],Tabla45[[#Headers],[JUNIO]]) -> 0 | I29: =SUMIFS(Tabla3[EGRESOS],Tabla3[SOCIO],Tabla45[[#This Row],[ACTIVIDADES]],Tabla3[PERIODO],Tabla45[[#Headers],[JULIO]]) -> 0 | J29: =SUMIFS(Tabla3[EGRESOS],Tabla3[SOCIO],Tabla45[[#This Row],[ACTIVIDADES]],Tabla3[PERIODO],Tabla45[[#Headers],[AGOSTO]]) -> 0 | K29: =SUMIFS(Tabla3[EGRESOS],Tabla3[SOCIO],Tabla45[[#This Row],[ACTIVIDADES]],Tabla3[PERIODO],Tabla45[[#Headers],[SEPTIEMBRE]]) -> 0 | L29: =SUMIFS(Tabla3[EGRESOS],Tabla3[SOCIO],Tabla45[[#This Row],[ACTIVIDADES]],Tabla3[PERIODO],Tabla45[[#Headers],[OCTUBRE]]) -> 0 | M29: =SUMIFS(Tabla3[EGRESOS],Tabla3[SOCIO],Tabla45[[#This Row],[ACTIVIDADES]],Tabla3[PERIODO],Tabla45[[#Headers],[NOVIEMBRE]]) -> 0 | N29: =SUMIFS(Tabla3[EGRESOS],Tabla3[SOCIO],Tabla45[[#This Row],[ACTIVIDADES]],Tabla3[PERIODO],Tabla45[[#Headers],[DICIEMBRE]]) -> 0 | O29: =SUM(Tabla45[[#This Row],[ENERO]:[DICIEMBRE]]) -> 3000000
B30: TERCEROS | C30: =SUBTOTAL(109,C31:C33) -> 0 | D30: =SUBTOTAL(109,D31:D33) -> 0 | E30: =SUBTOTAL(109,E31:E33) -> 0 | F30: =SUBTOTAL(109,F31:F33) -> 0 | G30: =SUBTOTAL(109,G31:G33) -> 0 | H30: =SUBTOTAL(109,H31:H33) -> 0 | I30: =SUBTOTAL(109,I31:I33) -> 0 | J30: =SUBTOTAL(109,J31:J33) -> 0 | ... N30: =SUBTOTAL(109,N31:N33) -> 0 | O30: =SUM(Tabla45[[#This Row],[ENERO]:[DICIEMBRE]]) -> 0
B31: SANTIAGO ERRECALDE | C31: =SUMIFS(Tabla3[EGRESOS],Tabla3[PROVEEDOR CLIENTE],Tabla45[[#This Row],[ACTIVIDADES]],Tabla3[PERIODO],Tabla45[[#Headers],[ENERO]]) -> 0 | D31: =SUMIFS(Tabla3[EGRESOS],Tabla3[PROVEEDOR CLIENTE],Tabla45[[#This Row],[ACTIVIDADES]],Tabla3[PERIODO],Tabla45[[#Headers],[FEBRERO]]) -> 0 | E31: =SUMIFS(Tabla3[EGRESOS],Tabla3[PROVEEDOR CLIENTE],Tabla45[[#This Row],[ACTIVIDADES]],Tabla3[PERIODO],Tabla45[[#Headers],[MARZO]]) -> 0 | F31: =SUMIFS(Tabla3[EGRESOS],Tabla3[PROVEEDOR CLIENTE],Tabla45[[#This Row],[ACTIVIDADES]],Tabla3[PERIODO],Tabla45[[#Headers],[ABRIL]]) -> 0 | G31: =SUMIFS(Tabla3[EGRESOS],Tabla3[PROVEEDOR CLIENTE],Tabla45[[#This Row],[ACTIVIDADES]],Tabla3[PERIODO],Tabla45[[#Headers],[MAYO]]) -> 0 | O31: =SUM(Tabla45[[#This Row],[ENERO]:[DICIEMBRE]]) -> 0
B32: BECERRA ADRIAN | C32: =SUMIFS(Tabla3[EGRESOS],Tabla3[PROVEEDOR CLIENTE],Tabla45[[#This Row],[ACTIVIDADES]],Tabla3[PERIODO],Tabla45[[#Headers],[ENERO]]) -> 0 | D32: =SUMIFS(Tabla3[EGRESOS],Tabla3[PROVEEDOR CLIENTE],Tabla45[[#This Row],[ACTIVIDADES]],Tabla3[PERIODO],Tabla45[[#Headers],[FEBRERO]]) -> 0 | E32: =SUMIFS(Tabla3[EGRESOS],Tabla3[PROVEEDOR CLIENTE],Tabla45[[#This Row],[ACTIVIDADES]],Tabla3[PERIODO],Tabla45[[#Headers],[MARZO]]) -> 0 | F32: =SUMIFS(Tabla3[EGRESOS],Tabla3[PROVEEDOR CLIENTE],Tabla45[[#This Row],[ACTIVIDADES]],Tabla3[PERIODO],Tabla45[[#Headers],[ABRIL]]) -> 0 | G32: =SUMIFS(Tabla3[EGRESOS],Tabla3[PROVEEDOR CLIENTE],Tabla45[[#This Row],[ACTIVIDADES]],Tabla3[PERIODO],Tabla45[[#Headers],[MAYO]]) -> 0 | O32: =SUM(Tabla45[[#This Row],[ENERO]:[DICIEMBRE]]) -> 0
O33: =SUM(Tabla45[[#This Row],[ENERO]:[DICIEMBRE]]) -> 0
B34: SALDO | C34: =C16+C25 -> -7248658 | D34: =D16+D25 -> -3096067 | E34: =E16+E25 -> 0 | F34: =F16+F25 -> 0 | G34: =G16+G25 -> 0 | H34: =H16+H25 -> 0 | I34: =I16+I25 -> 0 | J34: =J16+J25 -> 0 | ... N34: =N16+N25 -> 0
B35: SALDO ACUM | C35: =C34 -> -7248658 | D35: =Tabla45[[#This Row],[ENERO]]+D34 -> -10344725 | E35: =Tabla45[[#This Row],[FEBRERO]]+E34 -> -10344725 | F35: =Tabla45[[#This Row],[MARZO]]+F34 -> -10344725 | G35: =Tabla45[[#This Row],[ABRIL]]+G34 -> -10344725 | H35: =Tabla45[[#This Row],[MAYO]]+H34 -> -10344725 | I35: =Tabla45[[#This Row],[JUNIO]]+I34 -> -10344725 | J35: =Tabla45[[#This Row],[JULIO]]+J34 -> -10344725 | K35: =Tabla45[[#This Row],[AGOSTO]]+K34 -> -10344725 | L35: =Tabla45[[#This Row],[SEPTIEMBRE]]+L34 -> -10344725 | M35: =Tabla45[[#This Row],[OCTUBRE]]+M34 -> -10344725 | N35: =Tabla45[[#This Row],[NOVIEMBRE]]+N34 -> -10344725

Sheet LISTA
A1: ACTIVIDADES | C1: ADMINISTRACION | L1: FINACIERA | P1: AGRICULTURA | S1: GANADERIA | U1: ESTRUCTURA | Z1: OTROS
A2: ADMINISTRACION | C2: PERSONAL | F2: SOCIOS | G2: TERCEROS | H2: IMPUESTOS | I2: GASTOS_ADM | J2: SEGUROS | L2: AMORT. CRED | M2: PRESTAMOS | N2: INVERSIONES | P2: CULTIVO PRINCIPAL | Q2: CULTIVO COBERTURA | S2: HACIENDA | U2: ESTABLECIMIENTO | V2: MAQUINARIAS | W2: VEHICULOS | X2: HERRAMIENTAS | Z2: OVINO | AA2: PORCINOS | AB2: CAPRINOS | AC2: PERROS | AD2: GALLINAS
A3: AGRICULTURA | C3: SUELDOS | D3: SEGUROS | E3: GASTOS_VARIOS | F3: APORTES | G3: APORTE | H3: BIENES PERSONALES | I3: INTERESES | J3: HILUX | L3: CUOTAS PRESTAMOS | N3: PLAZO FIJO | P3: ANALISIS LAB. | Q3: ANALISIS LAB. | S3: ANALISIS LAB. | U3: REPARACIONES | V3: DESMALEZADORA | W3: HILUX | X3: GENERADOR HONDA | Z3: ESQUILA | AA3: VETERINARIA | AB3: VETERINARIA | AC3: VETERINARIA
A4: GANADERIA | C4: WALTER MEDINA | F4: RETIROS | G4: DEVOLUCION | H4: GANANCIAS | I4: HONORARIOS | J4: DHUSTER | P4: FERTILIZANTES | Q4: FERTILIZANTES | S4: INSUMOS | U4: MANTENIMIENTO | V4: MIXER | W4: DHUSTER | X4: PINCHES ROLLOS | Z4: VETERINARIA | AA4: VETERINARIO | AB4: VARIOS
A5: ESTRUCTURA | C5: KEVIN TOLEDO | H5: INMOBILIARIOS | I5: COMISIONES | P5: HERBICIDAS | Q5: HERBICIDAS | S5: MEDICAMENTOS | U5: CONSTRUCCION | V5: PALA CARGADORA | Z5: VARIOS
A6: OTROS | C6: ANDRES TOLEDO | H6: IVA | I6: MULTAS | P6: INSECTICIDAS | Q6: INSECTICIDAS | S6: VETERINARIA | U6: INSUMOS | V6: REPUESTOS_SEM
H7: IVA PERCEPCION | I7: ESCRIBANIA | P7: FUNGICIDA | Q7: FUNGICIDA | S7: FORRAJERIA | U7: SUPERMERCADO | V7: REPUESTOS_SEM PLA
H8: IVA REDUCCION | I8: VARIOS | P8: SEMILLAS | Q8: SEMILLAS | S8: ASESORAMIENTO | U8: PANADERIA | V8: TRACTOR 780
H9: TASAS | P9: SIEMBRA | Q9: SIEMBRA | S9: VENTA HAC. | U9: SERVICIOS | V9: TRACTOR JD
P10: COSECHA | Q10: COSECHA | S10: GUIAS | U10: ALQUILERES
P11: GRANOS | Q11: GRANOS | S11: FLETES | U11: GASTOS_VARIOS
P12: APLICACIONES | Q12: APLICACIONES | S12: ESTRUCTURA
P13: INOCULANTE | Q13: INOCULANTE | S13: COMBUSTIBLES
P14: INSUMOS | Q14: INSUMOS
P15: FLETES | Q15: FLETES
P16: ASESORAMIENTO PROF. | Q16: ASESORAMIENTO PROF.
P17: VENTA CEREALES
P18: EXTRACCION MAIZ
